Workbook

Sheet TB
A3: 1 | B3: What Month? | O3: =A3 -> 1 | X3: =IF(A3-1 > 0, A3 - 1, 12) -> 12
A4: 2026 | B4: What Year? | O4: =A4-1 -> 2025 | X4: =IF(A3 = 1, A4-1, A4) -> 2025
B5: AccountNo | C5: Year | D5: Month | E5: YTD | F5: MTD | G5: Description | H5: Type | P5: AccountNo | Q5: Year | R5: Month | S5: YTD | T5: MTD | U5: Description | V5: Type | Y5: AccountNo | Z5: AccountField | AA5: YTD | AB5: MTD | AC5: Type | AD5: Description
B6: 1010101 | C6: 2026 | D6: 1 | E6: 5676709.9 | F6: 2500000 | G6: Cash In Bank - Money Market | H6: A | P6: 1010101 | Q6: 2025 | R6: 1 | S6: 5860198.8 | T6: 18597.1 | U6: Cash In Bank - Money Market | V6: A | Y6: 1010101 | Z6: Actual | AA6: 3176709.9 | AB6: -491755.12 | AC6: A | AD6: Cash In Bank - Money Market
B7: 1011001 | C7: 2026 | D7: 1 | E7: 1134287.9 | F7: -1039335.2 | G7: Cash In Bank - Checking | H7: A | P7: 1011001 | Q7: 2025 | R7: 1 | S7: 1374677.6 | T7: -726208.21 | U7: Cash In Bank - Checking | V7: A | Y7: 1011001 | Z7: Actual | AA7: 2173623.1 | AB7: 761514.13 | AC7: A | AD7: Cash In Bank - Checking
B8: 1014001 | C8: 2026 | D8: 1 | E8: 0 | F8: 0 | G8: Accounts Receivable-Other | H8: A | P8: 1014001 | Q8: 2025 | R8: 1 | S8: 0 | T8: 0 | U8: Accounts Receivable-Other | V8: A | Y8: 1014001 | Z8: Actual | AA8: 0 | AB8: 0 | AC8: A | AD8: Accounts Receivable-Other
B9: 1015001 | C9: 2026 | D9: 1 | E9: 0 | F9: 0 | G9: Accounts Receivable-Promler Properties | H9: A | P9: 1015001 | Q9: 2025 | R9: 1 | S9: 0 | T9: 0 | U9: Accounts Receivable-Promler Properties | V9: A | Y9: 1015001 | Z9: Actual | AA9: 0 | AB9: 0 | AC9: A | AD9: Accounts Receivable-Promler Properties
B10: 1016001 | C10: 2026 | D10: 1 | E10: 0 | F10: 0 | G10: Accounts Receivable-Ed Jr | H10: A | P10: 1016001 | Q10: 2025 | R10: 1 | S10: 0 | T10: 0 | U10: Accounts Receivable-Ed Jr | V10: A | Y10: 1016001 | Z10: Actual | AA10: 0 | AB10: 0 | AC10: A | AD10: Accounts Receivable-Ed Jr
B11: 1017001 | C11: 2026 | D11: 1 | E11: 0 | F11: 0 | G11: Accounts Receivable-Mark | H11: A | P11: 1017001 | Q11: 2025 | R11: 1 | S11: 0 | T11: 0 | U11: Accounts Receivable-Mark | V11: A | Y11: 1017001 | Z11: Actual | AA11: 0 | AB11: 0 | AC11: A | AD11: Accounts Receivable-Mark
B12: 1031001 | C12: 2026 | D12: 1 | E12: 1385493.2 | F12: -1078366.9 | G12: Accounts Receivable-Trade | H12: A | P12: 1031001 | Q12: 2025 | R12: 1 | S12: 2489058.2 | T12: 827347.32 | U12: Accounts Receivable-Trade | V12: A | Y12: 1031001 | Z12: Actual | AA12: 2463860.1 | AB12: -729029.03 | AC12: A | AD12: Accounts Receivable-Trade
B13: 1032001 | C13: 2026 | D13: 1 | E13: -2000.11 | F13: 0 | G13: Accounts Receivable-Employees | H13: A | P13: 1032001 | Q13: 2025 | R13: 1 | S13: -1918.43 | T13: 0 | U13: Accounts Receivable-Employees | V13: A | Y13: 1032001 | Z13: Actual | AA13: -2000.11 | AB13: -81.68 | AC13: A | AD13: Accounts Receivable-Employees
B14: 1110001 | C14: 2026 | D14: 1 | E14: 1550239.2 | F14: -391768.91 | G14: New Equipment Inventory | H14: A | P14: 1110001 | Q14: 2025 | R14: 1 | S14: 3148086.6 | T14: -242335.47 | U14: New Equipment Inventory | V14: A | Y14: 1110001 | Z14: Actual | AA14: 1942008.2 | AB14: 586927.23 | AC14: A | AD14: New Equipment Inventory
B15: 1120001 | C15: 2026 | D15: 1 | E15: 622576.08 | F15: 82970.2 | G15: Used Equipment Inventory | H15: A | P15: 1120001 | Q15: 2025 | R15: 1 | S15: 395371.73 | T15: 23483.72 | U15: Used Equipment Inventory | V15: A | Y15: 1120001 | Z15: Actual | AA15: 539605.88 | AB15: 1000 | AC15: A | AD15: Used Equipment Inventory
B16: 1120501 | C16: 2026 | D16: 1 | E16: 75346.38 | F16: -18331.89 | G16: AMI Used Equipment Inventory | H16: A | P16: 1120501 | Q16: 2025 | R16: 1 | S16: 113984.72 | T16: 42549.66 | U16: AMI Used Equipment Inventory | V16: A | Y16: 1120501 | Z16: Actual | AA16: 93678.27 | AB16: 900.66 | AC16: A | AD16: AMI Used Equipment Inventory
B17: 1129901 | C17: 2026 | D17: 1 | E17: 329107.42 | F17: 227563.21 | G17: Parts Inventory | H17: A | P17: 1129901 | Q17: 2025 | R17: 1 | S17: 429956.31 | T17: 111860.15 | U17: Parts Inventory | V17: A | Y17: 1129901 | Z17: Actual | AA17: 101544.21 | AB17: -240169.03 | AC17: A | AD17: Parts Inventory
... B752: 6980504 | C752: 2026 | D752: 1 | E752: 0 | F752: 0 | G752: G & A Allocation - DSS | H752: E | P752: 6990000 | Q752: 2025 | R752: 1 | S752: 0 | T752: 0 | U752: Deferred Income Tax Expense | V752: E | Y752: 6990000 | Z752: Actual | AA752: 0 | AB752: 0 | AC752: E | AD752: Deferred Income Tax Expense
B753: 6980601 | C753: 2026 | D753: 1 | E753: 0 | F753: 0 | G753: G & A Allocation | H753: E
B754: 6980602 | C754: 2026 | D754: 1 | E754: 0 | F754: 0 | G754: G & A Allocation | H754: E | S754: =SUBTOTAL(109,Table_TB1_1[YTD]) -> -1.1674274e-08 | T754: =SUBTOTAL(109,Table_TB1_1[MTD]) -> 4.3291948e-10
B755: 6980701 | C755: 2026 | D755: 1 | E755: 0 | F755: 0 | G755: G & A Allocation | H755: E
B756: 6980702 | C756: 2026 | D756: 1 | E756: 0 | F756: 0 | G756: G & A Allocation | H756: E
B757: 6980801 | C757: 2026 | D757: 1 | E757: 0 | F757: 0 | G757: G & A Allocation | H757: E
B758: 6980901 | C758: 2026 | D758: 1 | E758: 0 | F758: 0 | G758: G & A Allocation | H758: E
B759: 6980902 | C759: 2026 | D759: 1 | E759: 0 | F759: 0 | G759: G & A Allocation | H759: E
B760: 6990000 | C760: 2026 | D760: 1 | E760: 0 | F760: 0 | G760: Deferred Income Tax Expense | H760: E
E761: =SUBTOTAL(109,E6:E760) -> -7.6834112e-09 | F761: =SUBTOTAL(109,F6:F760) -> 6.9849193e-10

Sheet Balance Sheet
A1: Industrial Parts + Service Company
A2: Balance Sheet
A3: =DATEVALUE(TB!A3&"/"&TB!A4) -> 46023
C4: Assets | E4: YTD | G4: MTD
A5: 1010101 | C5: Cash In Bank - Money Market | E5: =VLOOKUP(A5,TB!TB,4,FALSE) -> 5676709.9 | G5: =VLOOKUP(A5,TB!TB,5,FALSE) -> 2500000
A6: 1011001 | C6: Cash In Bank - Checking | E6: =VLOOKUP(A6,TB!TB,4,FALSE) -> 1134287.9 | G6: =VLOOKUP(A6,TB!TB,5,FALSE) -> -1039335.2
C7: Total Checking | E7: =SUM(E5:E6) -> 6810997.8 | G7: =SUM(G5:G6) -> 1460664.8
A9: 1014001 | C9: Accounts Receivable-Other | E9: =VLOOKUP(A9,TB!TB,4,FALSE) -> 0 | G9: =VLOOKUP(A9,TB!TB,5,FALSE) -> 0
A10: 1031001 | C10: Accounts Receivable-Trade | E10: =VLOOKUP(A10,TB!TB,4,FALSE) -> 1385493.2 | G10: =VLOOKUP(A10,TB!TB,5,FALSE) -> -1078366.9
A11: 1032001 | C11: Accounts Receivable-Employees | E11: =VLOOKUP(A11,TB!TB,4,FALSE) -> -2000.11 | G11: =VLOOKUP(A11,TB!TB,5,FALSE) -> 0
A12: 1015001 | C12: Accounts Receivable-Promler Properties | E12: =VLOOKUP(A12,TB!TB,4,FALSE) -> 0 | G12: =VLOOKUP(A12,TB!TB,5,FALSE) -> 0
A13: 1016001 | C13: Accounts Receivable-Ed Jr | E13: =VLOOKUP(A13,TB!TB,4,FALSE) -> 0 | G13: =VLOOKUP(A13,TB!TB,5,FALSE) -> 0
A14: 1017001 | C14: Accounts Receivable-Mark | E14: =VLOOKUP(A14,TB!TB,4,FALSE) -> 0 | G14: =VLOOKUP(A14,TB!TB,5,FALSE) -> 0
C15: Total Receivable | E15: =SUM(E9:E14) -> 1383493.1 | G15: =SUM(G9:G14) -> -1078366.9
A17: 1110001 | C17: New Equipment Inventory | E17: =VLOOKUP(A17,TB!TB,4,FALSE) -> 1550239.2 | G17: =VLOOKUP(A17,TB!TB,5,FALSE) -> -391768.91
A18: 1120001 | C18: Used Equipment Inventory | E18: =VLOOKUP(A18,TB!TB,4,FALSE) -> 622576.08 | G18: =VLOOKUP(A18,TB!TB,5,FALSE) -> 82970.2
A19: 1120501 | C19: AMI Used Equipment Inventory | E19: =VLOOKUP(A19,TB!TB,4,FALSE) -> 75346.38 | G19: =VLOOKUP(A19,TB!TB,5,FALSE) -> -18331.89
A20: 1129901 | C20: Parts Inventory | E20: =VLOOKUP(A20,TB!TB,4,FALSE) -> 329107.42 | G20: =VLOOKUP(A20,TB!TB,5,FALSE) -> 227563.21
A21: 1140001 | C21: Allied Lines Inventory | E21: =VLOOKUP(A21,TB!TB,4,FALSE) -> 765025.01 | G21: =VLOOKUP(A21,TB!TB,5,FALSE) -> 258530.22
A22: 1150001 | C22: Work in Progress-Labor | E22: =VLOOKUP(A22,TB!TB,4,FALSE) -> 107823.53 | G22: =VLOOKUP(A22,TB!TB,5,FALSE) -> 56501.38
C23: Total Inventory | E23: =SUM(E17:E22) -> 3450117.7 | G23: =SUM(G17:G22) -> 215464.21
A25: 1600011 | C25: Clearing Account | E25: =VLOOKUP(A25,TB!TB,4,FALSE) -> 172.26 | G25: =VLOOKUP(A25,TB!TB,5,FALSE) -> 0
A26: 1210001 | C26: Prepaid Expense | E26: =VLOOKUP(A26,TB!TB,4,FALSE) -> 225.75 | G26: =VLOOKUP(A26,TB!TB,5,FALSE) -> 0
A27: 1213001 | C27: Prepaid Income Tax | E27: =VLOOKUP(A27,TB!TB,4,FALSE) -> 0 | G27: =VLOOKUP(A27,TB!TB,5,FALSE) -> 0
A28: 1216001 | C28: Prepaid Interest | E28: =VLOOKUP(A28,TB!TB,4,FALSE) -> 0 | G28: =VLOOKUP(A28,TB!TB,5,FALSE) -> 0
C29: Other Current Assets | E29: =SUM(E25:E28) -> 398.01 | G29: =SUM(G25:G28) -> 0
C31: Total Current Assets | E31: =E29+E23+E15+E7 -> 11645007 | G31: =G29+G23+G15+G7 -> 597762.04
A33: 1220001 | C33: Furniture and Fixtures-Shop | E33: =VLOOKUP(A33,TB!TB,4,FALSE) -> 70257.94 | G33: =VLOOKUP(A33,TB!TB,5,FALSE) -> 0
A34: 1230001 | C34: Furniture and Fixtures-Office | E34: =VLOOKUP(A34,TB!TB,4,FALSE) -> 330121.91 | G34: =VLOOKUP(A34,TB!TB,5,FALSE) -> 0
A35: 1241001 | C35: Furniture and Fixtures-Parts | E35: =VLOOKUP(A35,TB!TB,4,FALSE) -> 63994.71 | G35: =VLOOKUP(A35,TB!TB,5,FALSE) -> 0
A36: 1242001 | C36: Service Vehicles | E36: =VLOOKUP(A36,TB!TB,4,FALSE) -> 1979268.1 | G36: =VLOOKUP(A36,TB!TB,5,FALSE) -> 0
A37: 1240501 | C37: Demo Fleet | E37: =VLOOKUP(A37,TB!TB,4,FALSE) -> 744383.56 | G37: =VLOOKUP(A37,TB!TB,5,FALSE) -> -35911
A38: 1250001 | C38: Rental Fleet | E38: =VLOOKUP(A38,TB!TB,4,FALSE) -> 4777540.4 | G38: =VLOOKUP(A38,TB!TB,5,FALSE) -> 42574.25
A39: 1250101 | C39: AMI Lease Fleet | E39: =VLOOKUP(A39,TB!TB,4,FALSE) -> 21288661 | G39: =VLOOKUP(A39,TB!TB,5,FALSE) -> -46986.08
A40: 1250201 | C40: Used - AMI Return | E40: =VLOOKUP(A40,TB!TB,4,FALSE) -> 0 | G40: =VLOOKUP(A40,TB!TB,5,FALSE) -> 0
A41: 1250501 | C41: IPS Lease Fleet | E41: =VLOOKUP(A41,TB!TB,4,FALSE) -> 1335535.7 | G41: =VLOOKUP(A41,TB!TB,5,FALSE) -> 0
A42: 1260001 | C42: Leasehold Improvements | E42: =VLOOKUP(A42,TB!TB,4,FALSE) -> 34894.66 | G42: =VLOOKUP(A42,TB!TB,5,FALSE) -> 0
A43: 1513001 | C43: Accum.Depr.- F & E Shop | E43: =VLOOKUP(A43,TB!TB,4,FALSE) -> -67905.31 | G43: =VLOOKUP(A43,TB!TB,5,FALSE) -> -111.93
A44: 1514001 | C44: Accum.Depr.- F & E Office | E44: =VLOOKUP(A44,TB!TB,4,FALSE) -> -304567.86 | G44: =VLOOKUP(A44,TB!TB,5,FALSE) -> -1860.7
... A56: 1219000 | C56: Finance Lease-6440 Promler | E56: =VLOOKUP(A56,TB!TB,4,FALSE) -> 318755.7 | G56: =VLOOKUP(A56,TB!TB,5,FALSE) -> 0
C57: Total Other Assets | E57: =SUM(E33:E56) -> 18115452 | G57: =SUM(G33:G56) -> -246298.35
A59: 1260401 | C59: Deposits | E59: =VLOOKUP(A59,TB!TB,4,FALSE) -> -1155 | G59: =VLOOKUP(A59,TB!TB1_1,4,FALSE) -> 5197.5
A60: 1260402 | C60: Note - Ed Jr | E60: =VLOOKUP(A60,TB!TB,4,FALSE) -> 5588262.8 | G60: 0
C61: Total Assets | E61: =E60+E59+E57+E31 -> 35347566 | G61: =G60+G59+G57+G31 -> 356661.19
A64: Balance Sheet
A65: Industrial Parts + Service Company
A66: =DATEVALUE(TB!A3&"/"&TB!A4) -> 46023
C68: Liabilities | E68: YTD | G68: MTD
A70: 2041901 | C70: Paycheck Protection-Credit Line | E70: =VLOOKUP(A70,TB!TB,4,FALSE)*-1 -> 0 | G70: =VLOOKUP(A70,TB!TB,5,FALSE)*-1 -> 0
A71: 2042001 | C71: Notes Payable-Credit Line | E71: =VLOOKUP(A71,TB!TB,4,FALSE)*-1 -> 0 | G71: =VLOOKUP(A71,TB!TB,5,FALSE)*-1 -> 0
A72: 2042101 | C72: Notes Payable S T Other | E72: =VLOOKUP(A72,TB!TB,4,FALSE)*-1 -> 0 | G72: =VLOOKUP(A72,TB!TB,5,FALSE)*-1 -> 0
A73: 2042102 | C73: Note Payable Mark Mauser - Current | E73: =VLOOKUP(A73,TB!TB,4,FALSE)*-1 -> 408353.3 | G73: =VLOOKUP(A73,TB!TB,5,FALSE)*-1 -> 0
A74: 2042201 | C74: Notes Payable S.T. Floorplan | E74: =VLOOKUP(A74,TB!TB,4,FALSE)*-1 -> -365.91 | G74: =VLOOKUP(A74,TB!TB,5,FALSE)*-1 -> 0
C75: Total Current Notes Payable | E75: =SUM(E70:E74) -> 407987.39 | G75: =SUM(G70:G74) -> 0
A77: 2049501 | C77: Suspense Account | E77: =VLOOKUP(A77,TB!TB,4,FALSE)*-1 -> 0 | G77: =VLOOKUP(A77,TB!TB,5,FALSE)*-1 -> 0
A78: 2050001 | C78: Accounts Payable Trade | E78: =VLOOKUP(A78,TB!TB,4,FALSE)*-1 -> 2146398.3 | G78: =VLOOKUP(A78,TB!TB,5,FALSE)*-1 -> 299810.6
A79: 2051001 | C79: Accounts Payable Credit Card | E79: =VLOOKUP(A79,TB!TB,4,FALSE)*-1 -> 0 | G79: =VLOOKUP(A79,TB!TB,5,FALSE)*-1 -> 0
C80: Total Accounts Payable | E80: =SUM(E77:E79) -> 2146398.3 | G80: =SUM(G77:G79) -> 299810.6
A82: 2071001 | C82: Accrued Federal Withholding | E82: =VLOOKUP(A82,TB!TB,4,FALSE)*-1 -> 0 | G82: =VLOOKUP(A82,TB!TB,5,FALSE)*-1 -> 0
A83: 2072001 | C83: Accrued FICA Employer | E83: =VLOOKUP(A83,TB!TB,4,FALSE)*-1 -> 12017.73 | G83: =VLOOKUP(A83,TB!TB,5,FALSE)*-1 -> 0
A84: 2073001 | C84: Accrues State Withholding | E84: =VLOOKUP(A84,TB!TB,4,FALSE)*-1 -> 0 | G84: =VLOOKUP(A84,TB!TB,5,FALSE)*-1 -> 0
A85: 2073501 | C85: Accrued School Income Tax | E85: =VLOOKUP(A85,TB!TB,4,FALSE)*-1 -> 0 | G85: =VLOOKUP(A85,TB!TB,5,FALSE)*-1 -> 0
A86: 2074001 | C86: Accrued FICA Employee | E86: =VLOOKUP(A86,TB!TB,4,FALSE)*-1 -> 0 | G86: =VLOOKUP(A86,TB!TB,5,FALSE)*-1 -> 0
A87: 2074501 | C87: Accured City Withholding | E87: =VLOOKUP(A87,TB!TB,4,FALSE)*-1 -> 0 | G87: =VLOOKUP(A87,TB!TB,5,FALSE)*-1 -> 0
A88: 2075001 | C88: Accrued FUTA | E88: =VLOOKUP(A88,TB!TB,4,FALSE)*-1 -> 0 | G88: =VLOOKUP(A88,TB!TB,5,FALSE)*-1 -> 0
A89: 2076001 | C89: Accrued SUTA | E89: =VLOOKUP(A89,TB!TB,4,FALSE)*-1 -> 0 | G89: =VLOOKUP(A89,TB!TB,5,FALSE)*-1 -> 0
A90: 2077001 | C90: Accrued BWC | E90: =VLOOKUP(A90,TB!TB,4,FALSE)*-1 -> -28372.08 | G90: =VLOOKUP(A90,TB!TB,5,FALSE)*-1 -> 0
A91: 2076002 | C91: Accrued SUTA Florida | E91: =VLOOKUP(A91,TB!TB,4,FALSE)*-1 -> 0 | G91: =VLOOKUP(A91,TB!TB,5,FALSE)*-1 -> 0
A92: 2077301 | C92: Accrued Payroll Taxes | E92: =VLOOKUP(A92,TB!TB,4,FALSE)*-1 -> 0 | G92: =VLOOKUP(A92,TB!TB,5,FALSE)*-1 -> 0
A93: 2093001 | C93: Accrued CAT Tax | E93: =VLOOKUP(A93,TB!TB,4,FALSE)*-1 -> 12519 | G93: =VLOOKUP(A93,TB!TB,5,FALSE)*-1 -> 0
C94: Accrued Government Tax | E94: =SUM(E82:E93) -> -3835.35 | G94: =SUM(G82:G93) -> 0
A97: 2077201 | C97: Payroll Withholding Grp. Ins. | E97: =VLOOKUP(A97,TB!TB,4,FALSE)*-1 -> 0 | G97: =VLOOKUP(A97,TB!TB,5,FALSE)*-1 -> 0
A98: 2078401 | C98: Payroll Withholding Garnishment | E98: =VLOOKUP(A98,TB!TB,4,FALSE)*-1 -> 0 | G98: =VLOOKUP(A98,TB!TB,5,FALSE)*-1 -> 0
A99: 2081001 | C99: Accrued Personal Property Tax | E99: =VLOOKUP(A99,TB!TB,4,FALSE)*-1 -> 0 | G99: =VLOOKUP(A99,TB!TB,5,FALSE)*-1 -> 0
A100: 2082001 | C100: Accrued Income Tax | E100: =VLOOKUP(A100,TB!TB,4,FALSE)*-1 -> -180282.3 | G100: =VLOOKUP(A100,TB!TB,5,FALSE)*-1 -> 0
A101: 2090501 | C101: Accrued Payroll | E101: =VLOOKUP(A101,TB!TB,4,FALSE)*-1 -> 149403.66 | G101: =VLOOKUP(A101,TB!TB,5,FALSE)*-1 -> 0
A102: 2091000 | C102: Accrued Rent Payable | E102: =VLOOKUP(A102,TB!TB,4,FALSE)*-1 -> 0 | G102: =VLOOKUP(A102,TB!TB,5,FALSE)*-1 -> 0
A103: 2091001 | C103: Accrued Commission | E103: =VLOOKUP(A103,TB!TB,4,FALSE)*-1 -> 352936.77 | G103: =VLOOKUP(A103,TB!TB,5,FALSE)*-1 -> -255631.18
A104: 2092001 | C104: Accrued Interest | E104: =VLOOKUP(A104,TB!TB,4,FALSE)*-1 -> 0 | G104: =VLOOKUP(A104,TB!TB,5,FALSE)*-1 -> 0
A105: 2078601 | C105: Payroll Withholding 401K | E105: =VLOOKUP(A105,TB!TB,4,FALSE)*-1 -> 0.4 | G105: =VLOOKUP(A105,TB!TB,5,FALSE)*-1 -> 0
C106: Accrued Payroll | E106: =SUM(E97:E105) -> 322058.53 | G106: =SUM(G97:G105) -> -255631.18
A108: 2080001 | C108: Sales Tax Payable - Ohio | E108: =VLOOKUP(A108,TB!TB,4,FALSE)*-1 -> 30051.41 | G108: =VLOOKUP(A108,TB!TB,5,FALSE)*-1 -> 5184.02
A109: 2080002 | C109: Sales Tax Payable - Alabama | E109: =VLOOKUP(A109,TB!TB,4,FALSE)*-1 -> -6351.97 | G109: =VLOOKUP(A109,TB!TB,5,FALSE)*-1 -> 3991.7
A110: 2080003 | C110: Sales Tax Payable - Arizona | E110: =VLOOKUP(A110,TB!TB,4,FALSE)*-1 -> -1954.37 | G110: =VLOOKUP(A110,TB!TB,5,FALSE)*-1 -> 0
A111: 2080004 | C111: Sales Tax Payable - Florida | E111: =VLOOKUP(A111,TB!TB,4,FALSE)*-1 -> 549 | G111: =VLOOKUP(A111,TB!TB,5,FALSE)*-1 -> -3434
A112: 2080005 | C112: Sales Tax Payable - Illinois | E112: =VLOOKUP(A112,TB!TB,4,FALSE)*-1 -> 12265.2 | G112: =VLOOKUP(A112,TB!TB,5,FALSE)*-1 -> 0
A113: 2080006 | C113: Sales Tax Payable - Kansas | E113: =VLOOKUP(A113,TB!TB,4,FALSE)*-1 -> 4191.15 | G113: =VLOOKUP(A113,TB!TB,5,FALSE)*-1 -> -207
A114: 2080007 | C114: Sales Tax Payable - Kentucky | E114: =VLOOKUP(A114,TB!TB,4,FALSE)*-1 -> -3.44 | G114: =VLOOKUP(A114,TB!TB,5,FALSE)*-1 -> -12642.71
A115: 2080008 | C115: Sales Tax Payable - Maryland | E115: =VLOOKUP(A115,TB!TB,4,FALSE)*-1 -> 803.77 | G115: =VLOOKUP(A115,TB!TB,5,FALSE)*-1 -> 0
A116: 2080009 | C116: Sales Tax Payable - Massachusetts | E116: =VLOOKUP(A116,TB!TB,4,FALSE)*-1 -> 8117.49 | G116: =VLOOKUP(A116,TB!TB,5,FALSE)*-1 -> 0
A117: 2080010 | C117: Sales Tax Payable - Minnisota | E117: =VLOOKUP(A117,TB!TB,4,FALSE)*-1 -> 3264.7 | G117: =VLOOKUP(A117,TB!TB,5,FALSE)*-1 -> 0
A118: 2080011 | C118: Sales Tax Payable - Missouri | E118: =VLOOKUP(A118,TB!TB,4,FALSE)*-1 -> 8179.88 | G118: =VLOOKUP(A118,TB!TB,5,FALSE)*-1 -> 0
A119: 2080012 | C119: Sales Tax Payable - Oklahoma | E119: =VLOOKUP(A119,TB!TB,4,FALSE)*-1 -> 10193.25 | G119: =VLOOKUP(A119,TB!TB,5,FALSE)*-1 -> 8753.35
... A148: 2080050 | C148: Sales Tax Payable-Last State | E148: =VLOOKUP(A148,TB!TB,4,FALSE)*-1 -> 0 | G148: =VLOOKUP(A148,TB!TB,5,FALSE)*-1 -> 0
C149: Sales Tax Payable | E149: =SUM(E108:E148) -> 86398.41 | G149: =SUM(G108:G148) -> -66738.77
C151: Total Current Liablities | E151: =E149+E106+E94+E80+E75 -> 2959007.3 | G151: =G149+G106+G94+G80+G75 -> -22559.35
A153: 2030201 | C153: Notes Payable L.T. Floorplan | E153: =VLOOKUP(A153,TB!TB,4,FALSE)*-1 -> 0 | G153: =VLOOKUP(A153,TB!TB,5,FALSE)*-1 -> 0
A154: 2030302 | C154: Note Payable Mark Mauser - Long-Term | E154: =VLOOKUP(A154,TB!TB,4,FALSE)*-1 -> 966924.52 | G154: =VLOOKUP(A154,TB!TB,5,FALSE)*-1 -> 0
A155: 2030301 | C155: Notes Payable L.T.-Other | E155: =VLOOKUP(A155,TB!TB,4,FALSE)*-1 -> 0 | G155: =VLOOKUP(A155,TB!TB,5,FALSE)*-1 -> 0
A156: 2030300 | C156: L/T Lease Liability-6400 Promler | E156: =VLOOKUP(A156,TB!TB,4,FALSE)*-1 -> 58502.64 | G156: =VLOOKUP(A156,TB!TB,5,FALSE)*-1 -> 0
...

Sheet Trial Balance
A1: Industrial Parts + Service Company
A2: Trial Balance
A3: =DATEVALUE(TB!$A$3&"/"&TB!$A$4) -> 46023
A5: Account # | B5: Type | C5: Account Name | E5: Begin Balance | G5: Period Debits | I5: Period Credits | K5: Net Change | M5: Ending Balance
A7: 1010101 | B7: A | C7: Cash In Bank - Money Market | E7: =VLOOKUP(A7,TB!TB2_,3,FALSE) -> 3176709.9 | G7: =VLOOKUP(A7,TB!TB2_,4,FALSE) -> -491755.12 | I7: =VLOOKUP(A7,TB!TB2_,4,FALSE) -> -491755.12 | K7: =I7+G7 -> -983510.24 | M7: =VLOOKUP(A7,TB!TB,4,FALSE) -> 5676709.9
A8: 1011001 | B8: A | C8: Cash In Bank - Checking | E8: =VLOOKUP(A8,TB!TB2_,3,FALSE) -> 2173623.1 | G8: =VLOOKUP(A8,TB!TB2_,4,FALSE) -> 761514.13 | I8: =VLOOKUP(A8,TB!TB2_,4,FALSE) -> 761514.13 | K8: =I8+G8 -> 1523028.3 | M8: =VLOOKUP(A8,TB!TB,4,FALSE) -> 1134287.9
A9: 1014001 | B9: A | C9: Accounts Receivable-Other | E9: =VLOOKUP(A9,TB!TB2_,3,FALSE) -> 0 | G9: =VLOOKUP(A9,TB!TB2_,4,FALSE) -> 0 | I9: =VLOOKUP(A9,TB!TB2_,4,FALSE) -> 0 | K9: =I9+G9 -> 0 | M9: =VLOOKUP(A9,TB!TB,4,FALSE) -> 0
A10: 1015001 | B10: A | C10: Accounts Receivable-Promler Properties | E10: =VLOOKUP(A10,TB!TB2_,3,FALSE) -> 0 | G10: =VLOOKUP(A10,TB!TB2_,4,FALSE) -> 0 | I10: =VLOOKUP(A10,TB!TB2_,4,FALSE) -> 0 | K10: =I10+G10 -> 0 | M10: =VLOOKUP(A10,TB!TB,4,FALSE) -> 0
A11: 1016001 | B11: A | C11: Accounts Receivable-Ed Jr | E11: =VLOOKUP(A11,TB!TB2_,3,FALSE) -> 0 | G11: =VLOOKUP(A11,TB!TB2_,4,FALSE) -> 0 | I11: =VLOOKUP(A11,TB!TB2_,4,FALSE) -> 0 | K11: =I11+G11 -> 0 | M11: =VLOOKUP(A11,TB!TB,4,FALSE) -> 0
A12: 1017001 | B12: A | C12: Accounts Receivable-Mark | E12: =VLOOKUP(A12,TB!TB2_,3,FALSE) -> 0 | G12: =VLOOKUP(A12,TB!TB2_,4,FALSE) -> 0 | I12: =VLOOKUP(A12,TB!TB2_,4,FALSE) -> 0 | K12: =I12+G12 -> 0 | M12: =VLOOKUP(A12,TB!TB,4,FALSE) -> 0
A13: 1031001 | B13: A | C13: Accounts Receivable-Trade | E13: =VLOOKUP(A13,TB!TB2_,3,FALSE) -> 2463860.1 | G13: =VLOOKUP(A13,TB!TB2_,4,FALSE) -> -729029.03 | I13: =VLOOKUP(A13,TB!TB2_,4,FALSE) -> -729029.03 | K13: =I13+G13 -> -1458058.1 | M13: =VLOOKUP(A13,TB!TB,4,FALSE) -> 1385493.2
A14: 1032001 | B14: A | C14: Accounts Receivable-Employees | E14: =VLOOKUP(A14,TB!TB2_,3,FALSE) -> -2000.11 | G14: =VLOOKUP(A14,TB!TB2_,4,FALSE) -> -81.68 | I14: =VLOOKUP(A14,TB!TB2_,4,FALSE) -> -81.68 | K14: =I14+G14 -> -163.36 | M14: =VLOOKUP(A14,TB!TB,4,FALSE) -> -2000.11
A15: 1016001 | B15: A | C15: Accounts Receivable-Ed Jr | E15: =VLOOKUP(A15,TB!TB2_,3,FALSE) -> 0 | G15: =VLOOKUP(A15,TB!TB2_,4,FALSE) -> 0 | I15: =VLOOKUP(A15,TB!TB2_,4,FALSE) -> 0 | K15: =I15+G15 -> 0 | M15: =VLOOKUP(A15,TB!TB,4,FALSE) -> 0
A16: 1017001 | B16: A | C16: Accounts Receivable-Mark | E16: =VLOOKUP(A16,TB!TB2_,3,FALSE) -> 0 | G16: =VLOOKUP(A16,TB!TB2_,4,FALSE) -> 0 | I16: =VLOOKUP(A16,TB!TB2_,4,FALSE) -> 0 | K16: =I16+G16 -> 0 | M16: =VLOOKUP(A16,TB!TB,4,FALSE) -> 0
A17: 1110001 | B17: A | C17: New Equipment Inventory | E17: =VLOOKUP(A17,TB!TB2_,3,FALSE) -> 1942008.2 | G17: =VLOOKUP(A17,TB!TB2_,4,FALSE) -> 586927.23 | I17: =VLOOKUP(A17,TB!TB2_,4,FALSE) -> 586927.23 | K17: =I17+G17 -> 1173854.5 | M17: =VLOOKUP(A17,TB!TB,4,FALSE) -> 1550239.2
A18: 1120001 | B18: A | C18: Used Equipment Inventory | E18: =VLOOKUP(A18,TB!TB2_,3,FALSE) -> 539605.88 | G18: =VLOOKUP(A18,TB!TB2_,4,FALSE) -> 1000 | I18: =VLOOKUP(A18,TB!TB2_,4,FALSE) -> 1000 | K18: =I18+G18 -> 2000 | M18: =VLOOKUP(A18,TB!TB,4,FALSE) -> 622576.08
... A49: 2030301 | B49: L | C49: Notes Payable L.T.-Other | E49: =VLOOKUP(A49,TB!TB2_,3,FALSE) -> 0 | G49: =VLOOKUP(A49,TB!TB2_,4,FALSE) -> 0 | I49: =VLOOKUP(A49,TB!TB2_,4,FALSE) -> 0 | K49: =I49+G49 -> 0 | M49: =VLOOKUP(A49,TB!TB,4,FALSE) -> 0
A50: 2030303 | B50: L | C50: Note - Ed Mauser Jr | E50: 0 | G50: 0 | I50: 0 | K50: 0 | M50: 0
A51: 2041901 | B51: L | C51: Paycheck Protection-Credit Line | E51: =VLOOKUP(A51,TB!TB2_,3,FALSE) -> 0 | G51: =VLOOKUP(A51,TB!TB2_,4,FALSE) -> 0 | I51: =VLOOKUP(A51,TB!TB2_,4,FALSE) -> 0 | K51: =I51+G51 -> 0 | M51: =VLOOKUP(A51,TB!TB,4,FALSE) -> 0
A52: 2042001 | B52: L | C52: Notes Payable-Credit Line | E52: =VLOOKUP(A52,TB!TB2_,3,FALSE) -> 0 | G52: =VLOOKUP(A52,TB!TB2_,4,FALSE) -> 0 | I52: =VLOOKUP(A52,TB!TB2_,4,FALSE) -> 0 | K52: =I52+G52 -> 0 | M52: =VLOOKUP(A52,TB!TB,4,FALSE) -> 0
A53: 2042101 | B53: L | C53: Notes Payable S T Other | E53: =VLOOKUP(A53,TB!TB2_,3,FALSE) -> 0 | G53: =VLOOKUP(A53,TB!TB2_,4,FALSE) -> 0 | I53: =VLOOKUP(A53,TB!TB2_,4,FALSE) -> 0 | K53: =I53+G53 -> 0 | M53: =VLOOKUP(A53,TB!TB,4,FALSE) -> 0
A54: 2042102 | B54: L | C54: Note Payable Mark Mauser - Current | E54: =VLOOKUP(A54,TB!TB2_,3,FALSE) -> -408353.3 | G54: =VLOOKUP(A54,TB!TB2_,4,FALSE) -> 0 | I54: =VLOOKUP(A54,TB!TB2_,4,FALSE) -> 0 | K54: =I54+G54 -> 0 | M54: =VLOOKUP(A54,TB!TB,4,FALSE) -> -408353.3
A55: 2042201 | B55: L | C55: Notes Payable S.T. Floorplan | E55: =VLOOKUP(A55,TB!TB2_,3,FALSE) -> 365.91 | G55: =VLOOKUP(A55,TB!TB2_,4,FALSE) -> 0 | I55: =VLOOKUP(A55,TB!TB2_,4,FALSE) -> 0 | K55: =I55+G55 -> 0 | M55: =VLOOKUP(A55,TB!TB,4,FALSE) -> 365.91
A56: 2049501 | B56: L | C56: Suspense Account | E56: =VLOOKUP(A56,TB!TB2_,3,FALSE) -> 0 | G56: =VLOOKUP(A56,TB!TB2_,4,FALSE) -> 0 | I56: =VLOOKUP(A56,TB!TB2_,4,FALSE) -> 0 | K56: =I56+G56 -> 0 | M56: =VLOOKUP(A56,TB!TB,4,FALSE) -> 0
A57: 2050001 | B57: L | C57: Accounts Payable Trade | E57: =VLOOKUP(A57,TB!TB2_,3,FALSE) -> -1846587.7 | G57: =VLOOKUP(A57,TB!TB2_,4,FALSE) -> 556061.5 | I57: =VLOOKUP(A57,TB!TB2_,4,FALSE) -> 556061.5 | K57: =I57+G57 -> 1112123 | M57: =VLOOKUP(A57,TB!TB,4,FALSE) -> -2146398.3
A58: 2051001 | B58: L | C58: Accounts Payable Credit Card | E58: =VLOOKUP(A58,TB!TB2_,3,FALSE) -> 0 | G58: =VLOOKUP(A58,TB!TB2_,4,FALSE) -> 0 | I58: =VLOOKUP(A58,TB!TB2_,4,FALSE) -> 0 | K58: =I58+G58 -> 0 | M58: =VLOOKUP(A58,TB!TB,4,FALSE) -> 0
A59: 2071001 | B59: L | C59: Accrued Federal Withholding | E59: =VLOOKUP(A59,TB!TB2_,3,FALSE) -> 0 | G59: =VLOOKUP(A59,TB!TB2_,4,FALSE) -> 0 | I59: =VLOOKUP(A59,TB!TB2_,4,FALSE) -> 0 | K59: =I59+G59 -> 0 | M59: =VLOOKUP(A59,TB!TB,4,FALSE) -> 0
A60: 2072001 | B60: L | C60: Accrued FICA Employer | E60: =VLOOKUP(A60,TB!TB2_,3,FALSE) -> -12017.73 | G60: =VLOOKUP(A60,TB!TB2_,4,FALSE) -> 0 | I60: =VLOOKUP(A60,TB!TB2_,4,FALSE) -> 0 | K60: =I60+G60 -> 0 | M60: =VLOOKUP(A60,TB!TB,4,FALSE) -> -12017.73
A61: 2073001 | B61: L | C61: Accrues State Withholding | E61: =VLOOKUP(A61,TB!TB2_,3,FALSE) -> 0 | G61: =VLOOKUP(A61,TB!TB2_,4,FALSE) -> 0 | I61: =VLOOKUP(A61,TB!TB2_,4,FALSE) -> 0 | K61: =I61+G61 -> 0 | M61: =VLOOKUP(A61,TB!TB,4,FALSE) -> 0
A62: 2073501 | B62: L | C62: Accrued School Income Tax | E62: =VLOOKUP(A62,TB!TB2_,3,FALSE) -> 0 | G62: =VLOOKUP(A62,TB!TB2_,4,FALSE) -> 0 | I62: =VLOOKUP(A62,TB!TB2_,4,FALSE) -> 0 | K62: =I62+G62 -> 0 | M62: =VLOOKUP(A62,TB!TB,4,FALSE) -> 0
... A81: 2080010 | B81: L | C81: Sales Tax Payable - Minnisota | E81: =VLOOKUP(A81,TB!TB2_,3,FALSE) -> -3264.7 | G81: =VLOOKUP(A81,TB!TB2_,4,FALSE) -> 0 | I81: =VLOOKUP(A81,TB!TB2_,4,FALSE) -> 0 | K81: =I81+G81 -> 0 | M81: =VLOOKUP(A81,TB!TB,4,FALSE) -> -3264.7
A83: Industrial Parts + Service Company
A84: Trial Balance
A85: =DATEVALUE(TB!$A$3&"/"&TB!$A$4) -> 46023
A86: 2080011 | B86: L | C86: Sales Tax Payable - Missouri | E86: =VLOOKUP(A86,TB!TB2_,3,FALSE) -> -8179.88 | G86: =VLOOKUP(A86,TB!TB2_,4,FALSE) -> 0 | I86: =VLOOKUP(A86,TB!TB2_,4,FALSE) -> 0 | K86: =I86+G86 -> 0 | M86: =VLOOKUP(A86,TB!TB,4,FALSE) -> -8179.88
A87: 2080012 | B87: L | C87: Sales Tax Payable - Oklahoma | E87: =VLOOKUP(A87,TB!TB2_,3,FALSE) -> -1439.9 | G87: =VLOOKUP(A87,TB!TB2_,4,FALSE) -> -1289.06 | I87: =VLOOKUP(A87,TB!TB2_,4,FALSE) -> -1289.06 | K87: =I87+G87 -> -2578.12 | M87: =VLOOKUP(A87,TB!TB,4,FALSE) -> -10193.25
A88: 2080013 | B88: L | C88: Sales Tax Payable - Texas | E88: =VLOOKUP(A88,TB!TB2_,3,FALSE) -> -11446.54 | G88: =VLOOKUP(A88,TB!TB2_,4,FALSE) -> 35273.56 | I88: =VLOOKUP(A88,TB!TB2_,4,FALSE) -> 35273.56 | K88: =I88+G88 -> 70547.12 | M88: =VLOOKUP(A88,TB!TB,4,FALSE) -> -270.98
A89: 2080014 | B89: L | C89: Sales Tax Payable - Virginia | E89: =VLOOKUP(A89,TB!TB2_,3,FALSE) -> 0 | G89: =VLOOKUP(A89,TB!TB2_,4,FALSE) -> 0 | I89: =VLOOKUP(A89,TB!TB2_,4,FALSE) -> 0 | K89: =I89+G89 -> 0 | M89: =VLOOKUP(A89,TB!TB,4,FALSE) -> 0
A90: 2080015 | B90: L | C90: Sales Tax Payable - Washington | E90: =VLOOKUP(A90,TB!TB2_,3,FALSE) -> -26028.48 | G90: =VLOOKUP(A90,TB!TB2_,4,FALSE) -> -8213.92 | I90: =VLOOKUP(A90,TB!TB2_,4,FALSE) -> -8213.92 | K90: =I90+G90 -> -16427.84 | M90: =VLOOKUP(A90,TB!TB,4,FALSE) -> -7691.18
A91: 2080016 | B91: L | C91: Sales Tax Payable - West Virginia | E91: =VLOOKUP(A91,TB!TB2_,3,FALSE) -> -376.08 | G91: =VLOOKUP(A91,TB!TB2_,4,FALSE) -> 0 | I91: =VLOOKUP(A91,TB!TB2_,4,FALSE) -> 0 | K91: =I91+G91 -> 0 | M91: =VLOOKUP(A91,TB!TB,4,FALSE) -> -356.78
A92: 2080017 | B92: L | C92: Sales Tax Payable - New York | E92: =VLOOKUP(A92,TB!TB2_,3,FALSE) -> 1540.49 | G92: =VLOOKUP(A92,TB!TB2_,4,FALSE) -> 0 | I92: =VLOOKUP(A92,TB!TB2_,4,FALSE) -> 0 | K92: =I92+G92 -> 0 | M92: =VLOOKUP(A92,TB!TB,4,FALSE) -> 1540.49
A93: 2080018 | B93: L | C93: Sales Tax Payable - California | E93: =VLOOKUP(A93,TB!TB2_,3,FALSE) -> -12948.17 | G93: =VLOOKUP(A93,TB!TB2_,4,FALSE) -> -180.75 | I93: =VLOOKUP(A93,TB!TB2_,4,FALSE) -> -180.75 | K93: =I93+G93 -> -361.5 | M93: =VLOOKUP(A93,TB!TB,4,FALSE) -> -827.76
A94: 2080019 | B94: L | C94: Sales Tax Payable - Connecticut | E94: =VLOOKUP(A94,TB!TB2_,3,FALSE) -> -11708.15 | G94: =VLOOKUP(A94,TB!TB2_,4,FALSE) -> -3463.09 | I94: =VLOOKUP(A94,TB!TB2_,4,FALSE) -> -3463.09 | K94: =I94+G94 -> -6926.18 | M94: =VLOOKUP(A94,TB!TB,4,FALSE) -> -8245.06
A95: 2080020 | B95: L | C95: Sales Tax Payable - Iowa | E95: =VLOOKUP(A95,TB!TB2_,3,FALSE) -> -1097.48 | G95: =VLOOKUP(A95,TB!TB2_,4,FALSE) -> -1097.48 | I95: =VLOOKUP(A95,TB!TB2_,4,FALSE) -> -1097.48 | K95: =I95+G95 -> -2194.96 | M95: =VLOOKUP(A95,TB!TB,4,FALSE) -> -1097.48
A96: 2080021 | B96: L | C96: Sales Tax Payable - New Jersey | E96: =VLOOKUP(A96,TB!TB2_,3,FALSE) -> -353.22 | G96: =VLOOKUP(A96,TB!TB2_,4,FALSE) -> -181.31 | I96: =VLOOKUP(A96,TB!TB2_,4,FALSE) -> -181.31 | K96: =I96+G96 -> -362.62 | M96: =VLOOKUP(A96,TB!TB,4,FALSE) -> -202.73
A97: 2080022 | B97: L | C97: Sales Tax Payable - North Carolina | E97: =VLOOKUP(A97,TB!TB2_,3,FALSE) -> -8625.97 | G97: =VLOOKUP(A97,TB!TB2_,4,FALSE) -> 0 | I97: =VLOOKUP(A97,TB!TB2_,4,FALSE) -> 0 | K97: =I97+G97 -> 0 | M97: =VLOOKUP(A97,TB!TB,4,FALSE) -> -22.01
... A121: 2092001 | B121: L | C121: Accrued Interest | E121: =VLOOKUP(A121,TB!TB2_,3,FALSE) -> 0 | G121: =VLOOKUP(A121,TB!TB2_,4,FALSE) -> 0 | I121: =VLOOKUP(A121,TB!TB2_,4,FALSE) -> 0 | K121: =I121+G121 -> 0 | M121: =VLOOKUP(A121,TB!TB,4,FALSE) -> 0
C122: Final Total | E122: =SUM(E7:E121) -> 25288285 | G122: =SUM(G7:G121) -> 611056.93 | I122: =SUM(I7:I121) -> 611056.93 | K122: =SUM(K7:K121) -> 1222113.9 | M122: =SUM(M7:M121) -> 25659369
A124: Account # | B124: Type | C124: Account Name | E124: Begin Balance | G124: Period Debits | I124: Period Credits | K124: Net Change | M124: Ending Balance
A126: 3911001 | C126: Common Stock | E126: =VLOOKUP(A126,TB!TB2_,3,FALSE) -> -750 | G126: =VLOOKUP(A126,TB!TB2_,4,FALSE) -> 0 | I126: =VLOOKUP(A126,TB!TB2_,4,FALSE) -> 0 | K126: =I126+G126 -> 0 | M126: =VLOOKUP(A126,TB!TB,4,FALSE) -> -750
A127: 3911002 | C127: Treasury Stock | E127: =VLOOKUP(A127,TB!TB2_,3,FALSE) -> 5499409.5 | G127: =VLOOKUP(A127,TB!TB2_,4,FALSE) -> 0 | I127: =VLOOKUP(A127,TB!TB2_,4,FALSE) -> 0 | K127: =I127+G127 -> 0 | M127: =VLOOKUP(A127,TB!TB,4,FALSE) -> 5499409.5
A128: 3920001 | C128: Officer Advance | E128: =VLOOKUP(A128,TB!TB2_,3,FALSE) -> 20400 | G128: =VLOOKUP(A128,TB!TB2_,4,FALSE) -> 4000 | I128: =VLOOKUP(A128,TB!TB2_,4,FALSE) -> 4000 | K128: =I128+G128 -> 8000 | M128: =VLOOKUP(A128,TB!TB,4,FALSE) -> 20400
A129: 3940001 | C129: Year to Date Net Income | E129: =VLOOKUP(A129,TB!TB2_,3,FALSE) -> 0 | G129: =VLOOKUP(A129,TB!TB2_,4,FALSE) -> 0 | I129: =VLOOKUP(A129,TB!TB2_,4,FALSE) -> 0 | K129: =I129+G129 -> 0 | M129: =VLOOKUP(A129,TB!TB,4,FALSE) -> 0
A130: 3940101 | C130: Retained Earnings | E130: =VLOOKUP(A130,TB!TB2_,3,FALSE) -> -28313413 | G130: =VLOOKUP(A130,TB!TB2_,4,FALSE) -> 0 | I130: =VLOOKUP(A130,TB!TB2_,4,FALSE) -> 0 | K130: =I130+G130 -> 0 | M130: =VLOOKUP(A130,TB!TB,4,FALSE) -> -33371520
M131: =SUM(M126:M130) -> -27852460
C132: Profit | E132: =E122+E126+E129+E130+E128 -> -3005478.7 | G132: =G122+G126+G129+G130+G128 -> 615056.93 | I132: =I122+I126+I129+I130+I128 -> 615056.93 | K132: =K122+K126+K129+K130+K128 -> 1230113.9 | M132: =+M131+M122 -> -2193091.2

Sheet Combined Detail P and L
A1: Industrial Parts + Service Company
A2: Consolidated Detail P and L
A3: =DATEVALUE(TB!A3&"/"&TB!A4) -> 46023
C4: Description | E4: =TB!O4 -> 2025 | H4: =TB!A4 -> 2026 | K4: =TB!O4 -> 2025 | N4: =TB!A4 -> 2026
A5: Account # | C5: Revenue | E5: MTD | F5: % of Sales | H5: MTD | I5: % of Sales | K5: YTD | L5: % of Sales | N5: YTD | O5: % of Sales
A7: 4036503 | C7: Parts Sales to CH Steel | E7: =VLOOKUP(A7,TB!TB1_1,5,FALSE)*-1 -> 0 | F7: =IF(E$160,E7/E$160,0) -> 0 | H7: =VLOOKUP(A7,TB!TB,5,FALSE)*-1 -> 0 | I7: =IF(H$160,H7/H$160,0) -> 0 | K7: =VLOOKUP(A7,TB!TB1_1,4,FALSE)*-1 -> 0 | L7: =IF(K$160,K7/K$160,0) -> 0 | N7: =VLOOKUP(A7,TB!TB,4,FALSE)*-1 -> 0 | O7: =IF(N$160,N7/N$160,0) -> 0
A8: 4110501 | C8: New Equipment Linde - Canton | E8: =VLOOKUP(A8,TB!TB1_1,5,FALSE)*-1 -> 73800 | F8: =IF(E$160,E8/E$160,0) -> 0.024947055 | H8: =VLOOKUP(A8,TB!TB,5,FALSE)*-1 -> 239550 | I8: =IF(H$160,H8/H$160,0) -> 0.10868515 | K8: =VLOOKUP(A8,TB!TB1_1,4,FALSE)*-1 -> 73800 | L8: =IF(K$160,K8/K$160,0) -> 0.024947055 | N8: =VLOOKUP(A8,TB!TB,4,FALSE)*-1 -> 239550 | O8: =IF(N$160,N8/N$160,0) -> 0.10868515
A9: 4110502 | C9: New Equipment Linde - Cleveland | E9: =VLOOKUP(A9,TB!TB1_1,5,FALSE)*-1 -> 114900 | F9: =IF(E$160,E9/E$160,0) -> 0.038840333 | H9: =VLOOKUP(A9,TB!TB,5,FALSE)*-1 -> 111968 | I9: =IF(H$160,H9/H$160,0) -> 0.050800498 | K9: =VLOOKUP(A9,TB!TB1_1,4,FALSE)*-1 -> 114900 | L9: =IF(K$160,K9/K$160,0) -> 0.038840333 | N9: =VLOOKUP(A9,TB!TB,4,FALSE)*-1 -> 111968 | O9: =IF(N$160,N9/N$160,0) -> 0.050800498
A10: 4110503 | C10: New Equipment Linde - C H Steel | E10: =VLOOKUP(A10,TB!TB1_1,5,FALSE)*-1 -> 0 | F10: =IF(E$160,E10/E$160,0) -> 0 | H10: =VLOOKUP(A10,TB!TB,5,FALSE)*-1 -> 0 | I10: =IF(H$160,H10/H$160,0) -> 0 | K10: =VLOOKUP(A10,TB!TB1_1,4,FALSE)*-1 -> 0 | L10: =IF(K$160,K10/K$160,0) -> 0 | N10: =VLOOKUP(A10,TB!TB,4,FALSE)*-1 -> 0 | O10: =IF(N$160,N10/N$160,0) -> 0
A11: 4110504 | C11: New Equipment Linde - DSS | E11: =VLOOKUP(A11,TB!TB1_1,5,FALSE)*-1 -> 0 | F11: =IF(E$160,E11/E$160,0) -> 0 | H11: =VLOOKUP(A11,TB!TB,5,FALSE)*-1 -> 0 | I11: =IF(H$160,H11/H$160,0) -> 0 | K11: =VLOOKUP(A11,TB!TB1_1,4,FALSE)*-1 -> 0 | L11: =IF(K$160,K11/K$160,0) -> 0 | N11: =VLOOKUP(A11,TB!TB,4,FALSE)*-1 -> 0 | O11: =IF(N$160,N11/N$160,0) -> 0
A12: 4112001 | C12: Commission-Allied - Canton | E12: =VLOOKUP(A12,TB!TB1_1,5,FALSE)*-1 -> 0 | F12: =IF(E$160,E12/E$160,0) -> 0 | H12: =VLOOKUP(A12,TB!TB,5,FALSE)*-1 -> 0 | I12: =IF(H$160,H12/H$160,0) -> 0 | K12: =VLOOKUP(A12,TB!TB1_1,4,FALSE)*-1 -> 0 | L12: =IF(K$160,K12/K$160,0) -> 0 | N12: =VLOOKUP(A12,TB!TB,4,FALSE)*-1 -> 0 | O12: =IF(N$160,N12/N$160,0) -> 0
A13: 4112002 | C13: Commission-Allied - Cleveland | E13: =VLOOKUP(A13,TB!TB1_1,5,FALSE)*-1 -> 0 | F13: =IF(E$160,E13/E$160,0) -> 0 | H13: =VLOOKUP(A13,TB!TB,5,FALSE)*-1 -> 0 | I13: =IF(H$160,H13/H$160,0) -> 0 | K13: =VLOOKUP(A13,TB!TB1_1,4,FALSE)*-1 -> 0 | L13: =IF(K$160,K13/K$160,0) -> 0 | N13: =VLOOKUP(A13,TB!TB,4,FALSE)*-1 -> 0 | O13: =IF(N$160,N13/N$160,0) -> 0
A14: 4112203 | C14: Commission-Allied - CH Steel | E14: =VLOOKUP(A14,TB!TB1_1,5,FALSE)*-1 -> 0 | F14: =IF(E$160,E14/E$160,0) -> 0 | H14: =VLOOKUP(A14,TB!TB,5,FALSE)*-1 -> 0 | I14: =IF(H$160,H14/H$160,0) -> 0 | K14: =VLOOKUP(A14,TB!TB1_1,4,FALSE)*-1 -> 0 | L14: =IF(K$160,K14/K$160,0) -> 0 | N14: =VLOOKUP(A14,TB!TB,4,FALSE)*-1 -> 0 | O14: =IF(N$160,N14/N$160,0) -> 0
A15: 4112204 | C15: Commission-Allied - DSS | E15: =VLOOKUP(A15,TB!TB1_1,5,FALSE)*-1 -> 0 | F15: =IF(E$160,E15/E$160,0) -> 0 | H15: =VLOOKUP(A15,TB!TB,5,FALSE)*-1 -> 0 | I15: =IF(H$160,H15/H$160,0) -> 0 | K15: =VLOOKUP(A15,TB!TB1_1,4,FALSE)*-1 -> 0 | L15: =IF(K$160,K15/K$160,0) -> 0 | N15: =VLOOKUP(A15,TB!TB,4,FALSE)*-1 -> 0 | O15: =IF(N$160,N15/N$160,0) -> 0
A16: 4111401 | C16: Commission-Used Equipment - Canton | E16: =VLOOKUP(A16,TB!TB1_1,5,FALSE)*-1 -> 0 | F16: =IF(E$160,E16/E$160,0) -> 0 | H16: =VLOOKUP(A16,TB!TB,5,FALSE)*-1 -> 0 | I16: =IF(H$160,H16/H$160,0) -> 0 | K16: =VLOOKUP(A16,TB!TB1_1,4,FALSE)*-1 -> 0 | L16: =IF(K$160,K16/K$160,0) -> 0 | N16: =VLOOKUP(A16,TB!TB,4,FALSE)*-1 -> 0 | O16: =IF(N$160,N16/N$160,0) -> 0
A17: 4111402 | C17: Commission-Used Equipment - Cleveland | E17: =VLOOKUP(A17,TB!TB1_1,5,FALSE)*-1 -> 0 | F17: =IF(E$160,E17/E$160,0) -> 0 | H17: =VLOOKUP(A17,TB!TB,5,FALSE)*-1 -> 0 | I17: =IF(H$160,H17/H$160,0) -> 0 | K17: =VLOOKUP(A17,TB!TB1_1,4,FALSE)*-1 -> 0 | L17: =IF(K$160,K17/K$160,0) -> 0 | N17: =VLOOKUP(A17,TB!TB,4,FALSE)*-1 -> 0 | O17: =IF(N$160,N17/N$160,0) -> 0
A18: 4111403 | C18: Commission-Used Equipment - CH Steel | E18: =VLOOKUP(A18,TB!TB1_1,5,FALSE)*-1 -> 0 | F18: =IF(E$160,E18/E$160,0) -> 0 | H18: =VLOOKUP(A18,TB!TB,5,FALSE)*-1 -> 0 | I18: =IF(H$160,H18/H$160,0) -> 0 | K18: =VLOOKUP(A18,TB!TB1_1,4,FALSE)*-1 -> 0 | L18: =IF(K$160,K18/K$160,0) -> 0 | N18: =VLOOKUP(A18,TB!TB,4,FALSE)*-1 -> 0 | O18: =IF(N$160,N18/N$160,0) -> 0
... A44: 4126602 | C44: Combi Parts Sale - Cleveland | E44: =VLOOKUP(A44,TB!TB1_1,5,FALSE)*-1 -> 0 | F44: =IF(E$160,E44/E$160,0) -> 0 | H44: =VLOOKUP(A44,TB!TB,5,FALSE)*-1 -> 0 | I44: =IF(H$160,H44/H$160,0) -> 0 | K44: =VLOOKUP(A44,TB!TB1_1,4,FALSE)*-1 -> 0 | L44: =IF(K$160,K44/K$160,0) -> 0 | N44: =VLOOKUP(A44,TB!TB,4,FALSE)*-1 -> 0 | O44: =IF(N$160,N44/N$160,0) -> 0
A45: 4146601 | C45: TVH Parts Sale - Canton | E45: 0 | F45: =IF(E$160,E45/E$160,0) -> 0 | H45: =VLOOKUP(A45,TB!TB,5,FALSE)*-1 -> 2046.32 | I45: =IF(H$160,H45/H$160,0) -> 0.00092842665 | K45: 0 | L45: =IF(K$160,K45/K$160,0) -> 0 | N45: =VLOOKUP(A45,TB!TB,4,FALSE)*-1 -> 2046.32 | O45: =IF(N$160,N45/N$160,0) -> 0.00092842665
A46: 4127601 | C46: Tire Sale - Canton | E46: =VLOOKUP(A46,TB!TB1_1,5,FALSE)*-1 -> 1272.33 | F46: =IF(E$160,E46/E$160,0) -> 0.00043009331 | H46: =VLOOKUP(A46,TB!TB,5,FALSE)*-1 -> 0 | I46: =IF(H$160,H46/H$160,0) -> 0 | K46: =VLOOKUP(A46,TB!TB1_1,4,FALSE)*-1 -> 1272.33 | L46: =IF(K$160,K46/K$160,0) -> 0.00043009331 | N46: =VLOOKUP(A46,TB!TB,4,FALSE)*-1 -> 0 | O46: =IF(N$160,N46/N$160,0) -> 0
A47: 4127602 | C47: Tire Sale - Cleveland | E47: =VLOOKUP(A47,TB!TB1_1,5,FALSE)*-1 -> 0 | F47: =IF(E$160,E47/E$160,0) -> 0 | H47: =VLOOKUP(A47,TB!TB,5,FALSE)*-1 -> 0 | I47: =IF(H$160,H47/H$160,0) -> 0 | K47: =VLOOKUP(A47,TB!TB1_1,4,FALSE)*-1 -> 0 | L47: =IF(K$160,K47/K$160,0) -> 0 | N47: =VLOOKUP(A47,TB!TB,4,FALSE)*-1 -> 0 | O47: =IF(N$160,N47/N$160,0) -> 0
A48: 4128601 | C48: Freight - Parts - Canton | E48: =VLOOKUP(A48,TB!TB1_1,5,FALSE)*-1 -> 10554.19 | F48: =IF(E$160,E48/E$160,0) -> 0.0035676959 | H48: =VLOOKUP(A48,TB!TB,5,FALSE)*-1 -> 7977.85 | I48: =IF(H$160,H48/H$160,0) -> 0.0036195944 | K48: =VLOOKUP(A48,TB!TB1_1,4,FALSE)*-1 -> 10554.19 | L48: =IF(K$160,K48/K$160,0) -> 0.0035676959 | N48: =VLOOKUP(A48,TB!TB,4,FALSE)*-1 -> 7977.85 | O48: =IF(N$160,N48/N$160,0) -> 0.0036195944
A49: 4128602 | C49: Freight - Parts - Cleveland | E49: =VLOOKUP(A49,TB!TB1_1,5,FALSE)*-1 -> 0 | F49: =IF(E$160,E49/E$160,0) -> 0 | H49: =VLOOKUP(A49,TB!TB,5,FALSE)*-1 -> 0 | I49: =IF(H$160,H49/H$160,0) -> 0 | K49: =VLOOKUP(A49,TB!TB1_1,4,FALSE)*-1 -> 0 | L49: =IF(K$160,K49/K$160,0) -> 0 | N49: =VLOOKUP(A49,TB!TB,4,FALSE)*-1 -> 0 | O49: =IF(N$160,N49/N$160,0) -> 0
A50: 4129601 | C50: Parts Sale Other - Canton | E50: =VLOOKUP(A50,TB!TB1_1,5,FALSE)*-1 -> 52716.39 | F50: =IF(E$160,E50/E$160,0) -> 0.017820036 | H50: =VLOOKUP(A50,TB!TB,5,FALSE)*-1 -> 42014.11 | I50: =IF(H$160,H50/H$160,0) -> 0.019062033 | K50: =VLOOKUP(A50,TB!TB1_1,4,FALSE)*-1 -> 52716.39 | L50: =IF(K$160,K50/K$160,0) -> 0.017820036 | N50: =VLOOKUP(A50,TB!TB,4,FALSE)*-1 -> 42014.11 | O50: =IF(N$160,N50/N$160,0) -> 0.019062033
A51: 4129602 | C51: Parts Sale Other - Cleveland | E51: =VLOOKUP(A51,TB!TB1_1,5,FALSE)*-1 -> 0 | F51: =IF(E$160,E51/E$160,0) -> 0 | H51: =VLOOKUP(A51,TB!TB,5,FALSE)*-1 -> 0 | I51: =IF(H$160,H51/H$160,0) -> 0 | K51: =VLOOKUP(A51,TB!TB1_1,4,FALSE)*-1 -> 0 | L51: =IF(K$160,K51/K$160,0) -> 0 | N51: =VLOOKUP(A51,TB!TB,4,FALSE)*-1 -> 0 | O51: =IF(N$160,N51/N$160,0) -> 0
A52: 4130601 | C52: Shop Parts-Linde - Canton | E52: =VLOOKUP(A52,TB!TB1_1,5,FALSE)*-1 -> 5050.8 | F52: =IF(E$160,E52/E$160,0) -> 0.0017073521 | H52: =VLOOKUP(A52,TB!TB,5,FALSE)*-1 -> 13032.79 | I52: =IF(H$160,H52/H$160,0) -> 0.0059130485 | K52: =VLOOKUP(A52,TB!TB1_1,4,FALSE)*-1 -> 5050.8 | L52: =IF(K$160,K52/K$160,0) -> 0.0017073521 | N52: =VLOOKUP(A52,TB!TB,4,FALSE)*-1 -> 13032.79 | O52: =IF(N$160,N52/N$160,0) -> 0.0059130485
A53: 4130602 | C53: Shop Parts-Linde - Cleveland | E53: =VLOOKUP(A53,TB!TB1_1,5,FALSE)*-1 -> 0 | F53: =IF(E$160,E53/E$160,0) -> 0 | H53: =VLOOKUP(A53,TB!TB,5,FALSE)*-1 -> 0 | I53: =IF(H$160,H53/H$160,0) -> 0 | K53: =VLOOKUP(A53,TB!TB1_1,4,FALSE)*-1 -> 0 | L53: =IF(K$160,K53/K$160,0) -> 0 | N53: =VLOOKUP(A53,TB!TB,4,FALSE)*-1 -> 0 | O53: =IF(N$160,N53/N$160,0) -> 0
A54: 4131601 | C54: Shop Parts-Combi - Canton | E54: =VLOOKUP(A54,TB!TB1_1,5,FALSE)*-1 -> -360.16 | F54: =IF(E$160,E54/E$160,0) -> -0.00012174704 | H54: =VLOOKUP(A54,TB!TB,5,FALSE)*-1 -> 1044.46 | I54: =IF(H$160,H54/H$160,0) -> 0.00047387725 | K54: =VLOOKUP(A54,TB!TB1_1,4,FALSE)*-1 -> -360.16 | L54: =IF(K$160,K54/K$160,0) -> -0.00012174704 | N54: =VLOOKUP(A54,TB!TB,4,FALSE)*-1 -> 1044.46 | O54: =IF(N$160,N54/N$160,0) -> 0.00047387725
A55: 4131602 | C55: Shop Parts-Combi - Cleveland | E55: =VLOOKUP(A55,TB!TB1_1,5,FALSE)*-1 -> 0 | F55: =IF(E$160,E55/E$160,0) -> 0 | H55: =VLOOKUP(A55,TB!TB,5,FALSE)*-1 -> 0 | I55: =IF(H$160,H55/H$160,0) -> 0 | K55: =VLOOKUP(A55,TB!TB1_1,4,FALSE)*-1 -> 0 | L55: =IF(K$160,K55/K$160,0) -> 0 | N55: =VLOOKUP(A55,TB!TB,4,FALSE)*-1 -> 0 | O55: =IF(N$160,N55/N$160,0) -> 0
A56: 4141601 | C56: Shop Parts-TVH - Canton | E56: 0 | F56: =IF(E$160,E56/E$160,0) -> 0 | H56: =VLOOKUP(A56,TB!TB,5,FALSE)*-1 -> 357.17 | I56: =IF(H$160,H56/H$160,0) -> 0.00016204999 | K56: 0 | L56: =IF(K$160,K56/K$160,0) -> 0 | N56: =VLOOKUP(A56,TB!TB,4,FALSE)*-1 -> 357.17 | O56: =IF(N$160,N56/N$160,0) -> 0.00016204999
A57: 4132601 | C57: Shop Parts-Other - Canton | E57: =VLOOKUP(A57,TB!TB1_1,5,FALSE)*-1 -> 17214.34 | F57: =IF(E$160,E57/E$160,0) -> 0.0058190661 | H57: =VLOOKUP(A57,TB!TB,5,FALSE)*-1 -> 9825.13 | I57: =IF(H$160,H57/H$160,0) -> 0.0044577156 | K57: =VLOOKUP(A57,TB!TB1_1,4,FALSE)*-1 -> 17214.34 | L57: =IF(K$160,K57/K$160,0) -> 0.0058190661 | N57: =VLOOKUP(A57,TB!TB,4,FALSE)*-1 -> 9825.13 | O57: =IF(N$160,N57/N$160,0) -> 0.0044577156
A58: 4132602 | C58: Shop Parts-Other - Cleveland | E58: =VLOOKUP(A58,TB!TB1_1,5,FALSE)*-1 -> 0 | F58: =IF(E$160,E58/E$160,0) -> 0 | H58: =VLOOKUP(A58,TB!TB,5,FALSE)*-1 -> 0 | I58: =IF(H$160,H58/H$160,0) -> 0 | K58: =VLOOKUP(A58,TB!TB1_1,4,FALSE)*-1 -> 0 | L58: =IF(K$160,K58/K$160,0) -> 0 | N58: =VLOOKUP(A58,TB!TB,4,FALSE)*-1 -> 0 | O58: =IF(N$160,N58/N$160,0) -> 0
A59: 4133601 | C59: Road Parts-Linde - Canton | E59: =VLOOKUP(A59,TB!TB1_1,5,FALSE)*-1 -> 31657.28 | F59: =IF(E$160,E59/E$160,0) -> 0.010701299 | H59: =VLOOKUP(A59,TB!TB,5,FALSE)*-1 -> 26290.97 | I59: =IF(H$160,H59/H$160,0) -> 0.011928358 | K59: =VLOOKUP(A59,TB!TB1_1,4,FALSE)*-1 -> 31657.28 | L59: =IF(K$160,K59/K$160,0) -> 0.010701299 | N59: =VLOOKUP(A59,TB!TB,4,FALSE)*-1 -> 26290.97 | O59: =IF(N$160,N59/N$160,0) -> 0.011928358
A60: 4133602 | C60: Road Parts-Linde - Cleveland | E60: =VLOOKUP(A60,TB!TB1_1,5,FALSE)*-1 -> 0 | F60: =IF(E$160,E60/E$160,0) -> 0 | H60: =VLOOKUP(A60,TB!TB,5,FALSE)*-1 -> 0 | I60: =IF(H$160,H60/H$160,0) -> 0 | K60: =VLOOKUP(A60,TB!TB1_1,4,FALSE)*-1 -> 0 | L60: =IF(K$160,K60/K$160,0) -> 0 | N60: =VLOOKUP(A60,TB!TB,4,FALSE)*-1 -> 0 | O60: =IF(N$160,N60/N$160,0) -> 0
A61: 4134601 | C61: Road Parts-Combi - Canton | E61: =VLOOKUP(A61,TB!TB1_1,5,FALSE)*-1 -> 13408.77 | F61: =IF(E$160,E61/E$160,0) -> 0.0045326466 | H61: =VLOOKUP(A61,TB!TB,5,FALSE)*-1 -> 17981.82 | I61: =IF(H$160,H61/H$160,0) -> 0.0081584507 | K61: =VLOOKUP(A61,TB!TB1_1,4,FALSE)*-1 -> 13408.77 | L61: =IF(K$160,K61/K$160,0) -> 0.0045326466 | N61: =VLOOKUP(A61,TB!TB,4,FALSE)*-1 -> 17981.82 | O61: =IF(N$160,N61/N$160,0) -> 0.0081584507
A62: 4134602 | C62: Road Parts-Combi - Cleveland | E62: =VLOOKUP(A62,TB!TB1_1,5,FALSE)*-1 -> 0 | F62: =IF(E$160,E62/E$160,0) -> 0 | H62: =VLOOKUP(A62,TB!TB,5,FALSE)*-1 -> 0 | I62: =IF(H$160,H62/H$160,0) -> 0 | K62: =VLOOKUP(A62,TB!TB1_1,4,FALSE)*-1 -> 0 | L62: =IF(K$160,K62/K$160,0) -> 0 | N62: =VLOOKUP(A62,TB!TB,4,FALSE)*-1 -> 0 | O62: =IF(N$160,N62/N$160,0) -> 0
A63: 4144601 | C63: Road Parts-TVH - Canton | E63: 0 | F63: =IF(E$160,E63/E$160,0) -> 0 | H63: =VLOOKUP(A63,TB!TB,5,FALSE)*-1 -> 565.2 | I63: =IF(H$160,H63/H$160,0) -> 0.00025643435 | K63: 0 | L63: =IF(K$160,K63/K$160,0) -> 0 | N63: =VLOOKUP(A63,TB!TB,4,FALSE)*-1 -> 565.2 | O63: =IF(N$160,N63/N$160,0) -> 0.00025643435
A64: 4135601 | C64: Road Parts-Other - Canton | E64: =VLOOKUP(A64,TB!TB1_1,5,FALSE)*-1 -> 31584.85 | F64: =IF(E$160,E64/E$160,0) -> 0.010676815 | H64: =VLOOKUP(A64,TB!TB,5,FALSE)*-1 -> 40289.65 | I64: =IF(H$160,H64/H$160,0) -> 0.018279636 | K64: =VLOOKUP(A64,TB!TB1_1,4,FALSE)*-1 -> 31584.85 | L64: =IF(K$160,K64/K$160,0) -> 0.010676815 | N64: =VLOOKUP(A64,TB!TB,4,FALSE)*-1 -> 40289.65 | O64: =IF(N$160,N64/N$160,0) -> 0.018279636
A65: 4135602 | C65: Road Parts-Other - Cleveland | E65: =VLOOKUP(A65,TB!TB1_1,5,FALSE)*-1 -> 3812.21 | F65: =IF(E$160,E65/E$160,0) -> 0.0012886641 | H65: =VLOOKUP(A65,TB!TB,5,FALSE)*-1 -> 7526.35 | I65: =IF(H$160,H65/H$160,0) -> 0.0034147464 | K65: =VLOOKUP(A65,TB!TB1_1,4,FALSE)*-1 -> 3812.21 | L65: =IF(K$160,K65/K$160,0) -> 0.0012886641 | N65: =VLOOKUP(A65,TB!TB,4,FALSE)*-1 -> 7526.35 | O65: =IF(N$160,N65/N$160,0) -> 0.0034147464
A66: 4136601 | C66: P M -Linde Parts - Canton | E66: =VLOOKUP(A66,TB!TB1_1,5,FALSE)*-1 -> 6354.38 | F66: =IF(E$160,E66/E$160,0) -> 0.002148009 | H66: =VLOOKUP(A66,TB!TB,5,FALSE)*-1 -> 14301.48 | I66: =IF(H$160,H66/H$160,0) -> 0.0064886602 | K66: =VLOOKUP(A66,TB!TB1_1,4,FALSE)*-1 -> 6354.38 | L66: =IF(K$160,K66/K$160,0) -> 0.002148009 | N66: =VLOOKUP(A66,TB!TB,4,FALSE)*-1 -> 14301.48 | O66: =IF(N$160,N66/N$160,0) -> 0.0064886602
A67: 4136602 | C67: P M -Linde Parts - Cleveland | E67: =VLOOKUP(A67,TB!TB1_1,5,FALSE)*-1 -> 0 | F67: =IF(E$160,E67/E$160,0) -> 0 | H67: =VLOOKUP(A67,TB!TB,5,FALSE)*-1 -> 0 | I67: =IF(H$160,H67/H$160,0) -> 0 | K67: =VLOOKUP(A67,TB!TB1_1,4,FALSE)*-1 -> 0 | L67: =IF(K$160,K67/K$160,0) -> 0 | N67: =VLOOKUP(A67,TB!TB,4,FALSE)*-1 -> 0 | O67: =IF(N$160,N67/N$160,0) -> 0
A68: 4137601 | C68: P M -Combi Parts - Canton | E68: =VLOOKUP(A68,TB!TB1_1,5,FALSE)*-1 -> 0 | F68: =IF(E$160,E68/E$160,0) -> 0 | H68: =VLOOKUP(A68,TB!TB,5,FALSE)*-1 -> 0 | I68: =IF(H$160,H68/H$160,0) -> 0 | K68: =VLOOKUP(A68,TB!TB1_1,4,FALSE)*-1 -> 0 | L68: =IF(K$160,K68/K$160,0) -> 0 | N68: =VLOOKUP(A68,TB!TB,4,FALSE)*-1 -> 0 | O68: =IF(N$160,N68/N$160,0) -> 0
A69: 4137602 | C69: P M -Combi Parts - Cleveland | E69: =VLOOKUP(A69,TB!TB1_1,5,FALSE)*-1 -> 0 | F69: =IF(E$160,E69/E$160,0) -> 0 | H69: =VLOOKUP(A69,TB!TB,5,FALSE)*-1 -> 0 | I69: =IF(H$160,H69/H$160,0) -> 0 | K69: =VLOOKUP(A69,TB!TB1_1,4,FALSE)*-1 -> 0 | L69: =IF(K$160,K69/K$160,0) -> 0 | N69: =VLOOKUP(A69,TB!TB,4,FALSE)*-1 -> 0 | O69: =IF(N$160,N69/N$160,0) -> 0
A70: 4147601 | C70: P M -TVH Parts - Canton | E70: 0 | F70: =IF(E$160,E70/E$160,0) -> 0 | H70: =VLOOKUP(A70,TB!TB,5,FALSE)*-1 -> 333.74 | I70: =IF(H$160,H70/H$160,0) -> 0.00015141967 | K70: 0 | L70: =IF(K$160,K70/K$160,0) -> 0 | N70: =VLOOKUP(A70,TB!TB,4,FALSE)*-1 -> 333.74 | O70: =IF(N$160,N70/N$160,0) -> 0.00015141967
A71: 4138601 | C71: P M - Other Parts - Canton | E71: =VLOOKUP(A71,TB!TB1_1,5,FALSE)*-1 -> 1324.71 | F71: =IF(E$160,E71/E$160,0) -> 0.00044779963 | H71: =VLOOKUP(A71,TB!TB,5,FALSE)*-1 -> 2128.79 | I71: =IF(H$160,H71/H$160,0) -> 0.00096584374 | K71: =VLOOKUP(A71,TB!TB1_1,4,FALSE)*-1 -> 1324.71 | L71: =IF(K$160,K71/K$160,0) -> 0.00044779963 | N71: =VLOOKUP(A71,TB!TB,4,FALSE)*-1 -> 2128.79 | O71: =IF(N$160,N71/N$160,0) -> 0.00096584374
A72: 4138602 | C72: P M - Other Parts - Cleveland | E72: =VLOOKUP(A72,TB!TB1_1,5,FALSE)*-1 -> 310.28 | F72: =IF(E$160,E72/E$160,0) -> 0.0001048858 | H72: =VLOOKUP(A72,TB!TB,5,FALSE)*-1 -> 898.6 | I72: =IF(H$160,H72/H$160,0) -> 0.00040769977 | K72: =VLOOKUP(A72,TB!TB1_1,4,FALSE)*-1 -> 310.28 | L72: =IF(K$160,K72/K$160,0) -> 0.0001048858 | N72: =VLOOKUP(A72,TB!TB,4,FALSE)*-1 -> 898.6 | O72: =IF(N$160,N72/N$160,0) -> 0.00040769977
A73: 4140501 | C73: Allied Lines Sales - Canton | E73: =VLOOKUP(A73,TB!TB1_1,5,FALSE)*-1 -> 28794 | F73: =IF(E$160,E73/E$160,0) -> 0.0097334078 | H73: =VLOOKUP(A73,TB!TB,5,FALSE)*-1 -> 43232.22 | I73: =IF(H$160,H73/H$160,0) -> 0.019614696 | K73: =VLOOKUP(A73,TB!TB1_1,4,FALSE)*-1 -> 28794 | L73: =IF(K$160,K73/K$160,0) -> 0.0097334078 | N73: =VLOOKUP(A73,TB!TB,4,FALSE)*-1 -> 43232.22 | O73: =IF(N$160,N73/N$160,0) -> 0.019614696
A74: 4140502 | C74: Allied Lines Sales - Cleveland | E74: =VLOOKUP(A74,TB!TB1_1,5,FALSE)*-1 -> 0 | F74: =IF(E$160,E74/E$160,0) -> 0 | H74: =VLOOKUP(A74,TB!TB,5,FALSE)*-1 -> 1711.03 | I74: =IF(H$160,H74/H$160,0) -> 0.00077630373 | K74: =VLOOKUP(A74,TB!TB1_1,4,FALSE)*-1 -> 0 | L74: =IF(K$160,K74/K$160,0) -> 0 | N74: =VLOOKUP(A74,TB!TB,4,FALSE)*-1 -> 1711.03 | O74: =IF(N$160,N74/N$160,0) -> 0.00077630373
A75: 4140503 | C75: Allied Lines - C H Steel | E75: =VLOOKUP(A75,TB!TB1_1,5,FALSE)*-1 -> 270923.07 | F75: =IF(E$160,E75/E$160,0) -> 0.091581743 | H75: =VLOOKUP(A75,TB!TB,5,FALSE)*-1 -> 27086.31 | I75: =IF(H$160,H75/H$160,0) -> 0.012289208 | K75: =VLOOKUP(A75,TB!TB1_1,4,FALSE)*-1 -> 270923.07 | L75: =IF(K$160,K75/K$160,0) -> 0.091581743 | N75: =VLOOKUP(A75,TB!TB,4,FALSE)*-1 -> 27086.31 | O75: =IF(N$160,N75/N$160,0) -> 0.012289208
A76: 4140504 | C76: Allied Lines - DSS | E76: =VLOOKUP(A76,TB!TB1_1,5,FALSE)*-1 -> 273457 | F76: =IF(E$160,E76/E$160,0) -> 0.092438303 | H76: =VLOOKUP(A76,TB!TB,5,FALSE)*-1 -> 112711.88 | I76: =IF(H$160,H76/H$160,0) -> 0.051138 | K76: =VLOOKUP(A76,TB!TB1_1,4,FALSE)*-1 -> 273457 | L76: =IF(K$160,K76/K$160,0) -> 0.092438303 | N76: =VLOOKUP(A76,TB!TB,4,FALSE)*-1 -> 112711.88 | O76: =IF(N$160,N76/N$160,0) -> 0.051138
A77: 4143401 | C77: Delivery Charge Used - Canton | E77: =VLOOKUP(A77,TB!TB1_1,5,FALSE)*-1 -> 0 | F77: =IF(E$160,E77/E$160,0) -> 0 | H77: =VLOOKUP(A77,TB!TB,5,FALSE)*-1 -> 0 | I77: =IF(H$160,H77/H$160,0) -> 0 | K77: =VLOOKUP(A77,TB!TB1_1,4,FALSE)*-1 -> 0 | L77: =IF(K$160,K77/K$160,0) -> 0 | N77: =VLOOKUP(A77,TB!TB,4,FALSE)*-1 -> 0 | O77: =IF(N$160,N77/N$160,0) -> 0
A78: 4143402 | C78: Delivery Charge Used - Cleveland | E78: =VLOOKUP(A78,TB!TB1_1,5,FALSE)*-1 -> 0 | F78: =IF(E$160,E78/E$160,0) -> 0 | H78: =VLOOKUP(A78,TB!TB,5,FALSE)*-1 -> 598 | I78: =IF(H$160,H78/H$160,0) -> 0.00027131589 | K78: =VLOOKUP(A78,TB!TB1_1,4,FALSE)*-1 -> 0 | L78: =IF(K$160,K78/K$160,0) -> 0 | N78: =VLOOKUP(A78,TB!TB,4,FALSE)*-1 -> 598 | O78: =IF(N$160,N78/N$160,0) -> 0.00027131589
A79: 4151701 | C79: Field Labor - Canton | E79: =VLOOKUP(A79,TB!TB1_1,5,FALSE)*-1 -> 153442.06 | F79: =IF(E$160,E79/E$160,0) -> 0.051868936 | H79: =VLOOKUP(A79,TB!TB,5,FALSE)*-1 -> 173527.68 | I79: =IF(H$160,H79/H$160,0) -> 0.078730463 | K79: =VLOOKUP(A79,TB!TB1_1,4,FALSE)*-1 -> 153442.06 | L79: =IF(K$160,K79/K$160,0) -> 0.051868936 | N79: =VLOOKUP(A79,TB!TB,4,FALSE)*-1 -> 173527.68 | O79: =IF(N$160,N79/N$160,0) -> 0.078730463
A80: 4151702 | C80: Field Labor - Cleveland | E80: =VLOOKUP(A80,TB!TB1_1,5,FALSE)*-1 -> 5585 | F80: =IF(E$160,E80/E$160,0) -> 0.0018879309 | H80: =VLOOKUP(A80,TB!TB,5,FALSE)*-1 -> 19902.2 | I80: =IF(H$160,H80/H$160,0) -> 0.0090297377 | K80: =VLOOKUP(A80,TB!TB1_1,4,FALSE)*-1 -> 5585 | L80: =IF(K$160,K80/K$160,0) -> 0.0018879309 | N80: =VLOOKUP(A80,TB!TB,4,FALSE)*-1 -> 19902.2 | O80: =IF(N$160,N80/N$160,0) -> 0.0090297377
A81: 4152701 | C81: Delivery Charge-Internal - Canton | E81: =VLOOKUP(A81,TB!TB1_1,5,FALSE)*-1 -> 32.09 | F81: =IF(E$160,E81/E$160,0) -> 1.0847574e-05 | H81: =VLOOKUP(A81,TB!TB,5,FALSE)*-1 -> 2194.01 | I81: =IF(H$160,H81/H$160,0) -> 0.00099543441 | K81: =VLOOKUP(A81,TB!TB1_1,4,FALSE)*-1 -> 32.09 | L81: =IF(K$160,K81/K$160,0) -> 1.0847574e-05 | N81: =VLOOKUP(A81,TB!TB,4,FALSE)*-1 -> 2194.01 | O81: =IF(N$160,N81/N$160,0) -> 0.00099543441
A82: 4152702 | C82: Delivery Charge-Internal - Cleveland | E82: =VLOOKUP(A82,TB!TB1_1,5,FALSE)*-1 -> 399.11 | F82: =IF(E$160,E82/E$160,0) -> 0.00013491354 | H82: =VLOOKUP(A82,TB!TB,5,FALSE)*-1 -> 0 | I82: =IF(H$160,H82/H$160,0) -> 0 | K82: =VLOOKUP(A82,TB!TB1_1,4,FALSE)*-1 -> 399.11 | L82: =IF(K$160,K82/K$160,0) -> 0.00013491354 | N82: =VLOOKUP(A82,TB!TB,4,FALSE)*-1 -> 0 | O82: =IF(N$160,N82/N$160,0) -> 0
... A158: 4410702 | C158: Warranty Internal - Cleveland | E158: =VLOOKUP(A158,TB!TB1_1,5,FALSE)*-1 -> 0 | F158: =IF(E$160,E158/E$160,0) -> 0 | H158: =VLOOKUP(A158,TB!TB,5,FALSE)*-1 -> 0 | I158: =IF(H$160,H158/H$160,0) -> 0 | K158: =VLOOKUP(A158,TB!TB1_1,4,FALSE)*-1 -> 0 | L158: =IF(K$160,K158/K$160,0) -> 0 | N158: =VLOOKUP(A158,TB!TB,4,FALSE)*-1 -> 0 | O158: =IF(N$160,N158/N$160,0) -> 0
F159: =IF(E$160,E159/E$160,0) -> 0 | I159: =IF(H$160,H159/H$160,0) -> 0 | L159: =IF(K$160,K159/K$160,0) -> 0 | O159: =IF(N$160,N159/N$160,0) -> 0
A160: Total Sales | E160: =SUM(E7:E159) -> 2958265 | F160: =IF(E$160,E160/E$160,0) -> 1 | H160: =SUM(H7:H159) -> 2204072.9 | I160: =IF(H$160,H160/H$160,0) -> 1 | K160: =SUM(K7:K159) -> 2958265 | L160: =IF(K$160,K160/K$160,0) -> 1 | N160: =SUM(N7:N159) -> 2204072.9 | O160: =IF(N$160,N160/N$160,0) -> 1
E162: MTD | H162: MTD | K162: YTD | N162: YTD
C163: Cost of Sales | E163: =E4 -> 2025 | F163: % of Sales | H163: =H4 -> 2026 | I163: % of Sales | K163: =K4 -> 2025 | L163: % of Sales | N163: =N4 -> 2026 | O163: % of Sales
A164: 5110501 | C164: New Equip Linde - Canton | E164: =VLOOKUP(A164,TB!TB1_1,5,FALSE) -> 64123.68 | F164: =IF(E$160,E164/E$160,0) -> 0.02167611 | H164: =VLOOKUP(A164,TB!TB,5,FALSE) -> 180524.11 | I164: =IF(H$160,H164/H$160,0) -> 0.081904782 | K164: =VLOOKUP(A164,TB!TB1_1,4,FALSE) -> 64123.68 | L164: =IF(K$160,K164/K$160,0) -> 0.02167611 | N164: =VLOOKUP(A164,TB!TB,4,FALSE) -> 180524.11 | O164: =IF(N$160,N164/N$160,0) -> 0.081904782
A165: 5110502 | C165: New Equip Linde - Cleveland | E165: =VLOOKUP(A165,TB!TB1_1,5,FALSE) -> 78711.41 | F165: =IF(E$160,E165/E$160,0) -> 0.026607288 | H165: =VLOOKUP(A165,TB!TB,5,FALSE) -> 70119.88 | I165: =IF(H$160,H165/H$160,0) -> 0.031813775 | K165: =VLOOKUP(A165,TB!TB1_1,4,FALSE) -> 78711.41 | L165: =IF(K$160,K165/K$160,0) -> 0.026607288 | N165: =VLOOKUP(A165,TB!TB,4,FALSE) -> 70119.88 | O165: =IF(N$160,N165/N$160,0) -> 0.031813775
A166: 5110503 | C166: New Equip Linde - CH Steel | E166: =VLOOKUP(A166,TB!TB1_1,5,FALSE) -> 0 | F166: =IF(E$160,E166/E$160,0) -> 0 | H166: =VLOOKUP(A166,TB!TB,5,FALSE) -> 0 | I166: =IF(H$160,H166/H$160,0) -> 0 | K166: =VLOOKUP(A166,TB!TB1_1,4,FALSE) -> 0 | L166: =IF(K$160,K166/K$160,0) -> 0 | N166: =VLOOKUP(A166,TB!TB,4,FALSE) -> 0 | O166: =IF(N$160,N166/N$160,0) -> 0
A167: 5110504 | C167: New Equip Linde - DSS | E167: =VLOOKUP(A167,TB!TB1_1,5,FALSE) -> 0 | F167: =IF(E$160,E167/E$160,0) -> 0 | H167: =VLOOKUP(A167,TB!TB,5,FALSE) -> 0 | I167: =IF(H$160,H167/H$160,0) -> 0 | K167: =VLOOKUP(A167,TB!TB1_1,4,FALSE) -> 0 | L167: =IF(K$160,K167/K$160,0) -> 0 | N167: =VLOOKUP(A167,TB!TB,4,FALSE) -> 0 | O167: =IF(N$160,N167/N$160,0) -> 0
A168: 5113501 | C168: New Equip Combi - Canton | E168: =VLOOKUP(A168,TB!TB1_1,5,FALSE) -> 172669.05 | F168: =IF(E$160,E168/E$160,0) -> 0.05836835 | H168: =VLOOKUP(A168,TB!TB,5,FALSE) -> 180109.91 | I168: =IF(H$160,H168/H$160,0) -> 0.081716857 | K168: =VLOOKUP(A168,TB!TB1_1,4,FALSE) -> 172669.05 | L168: =IF(K$160,K168/K$160,0) -> 0.05836835 | N168: =VLOOKUP(A168,TB!TB,4,FALSE) -> 180109.91 | O168: =IF(N$160,N168/N$160,0) -> 0.081716857
A169: 5113502 | C169: New Equip Combi - Cleveland | E169: =VLOOKUP(A169,TB!TB1_1,5,FALSE) -> 0 | F169: =IF(E$160,E169/E$160,0) -> 0 | H169: =VLOOKUP(A169,TB!TB,5,FALSE) -> 0 | I169: =IF(H$160,H169/H$160,0) -> 0 | K169: =VLOOKUP(A169,TB!TB1_1,4,FALSE) -> 0 | L169: =IF(K$160,K169/K$160,0) -> 0 | N169: =VLOOKUP(A169,TB!TB,4,FALSE) -> 0 | O169: =IF(N$160,N169/N$160,0) -> 0
A170: 5113503 | C170: New Equip Combi - CH Steel | E170: =VLOOKUP(A170,TB!TB1_1,5,FALSE) -> 659733.31 | F170: =IF(E$160,E170/E$160,0) -> 0.22301359 | H170: =VLOOKUP(A170,TB!TB,5,FALSE) -> 0 | I170: =IF(H$160,H170/H$160,0) -> 0 | K170: =VLOOKUP(A170,TB!TB1_1,4,FALSE) -> 659733.31 | L170: =IF(K$160,K170/K$160,0) -> 0.22301359 | N170: =VLOOKUP(A170,TB!TB,4,FALSE) -> 0 | O170: =IF(N$160,N170/N$160,0) -> 0
A171: 5113504 | C171: New Equip Combi - DSS | E171: =VLOOKUP(A171,TB!TB1_1,5,FALSE) -> 0 | F171: =IF(E$160,E171/E$160,0) -> 0 | H171: =VLOOKUP(A171,TB!TB,5,FALSE) -> 0 | I171: =IF(H$160,H171/H$160,0) -> 0 | K171: =VLOOKUP(A171,TB!TB1_1,4,FALSE) -> 0 | L171: =IF(K$160,K171/K$160,0) -> 0 | N171: =VLOOKUP(A171,TB!TB,4,FALSE) -> 0 | O171: =IF(N$160,N171/N$160,0) -> 0
A172: 5115501 | C172: New Equipment Other Canton | E172: =VLOOKUP(A172,TB!TB1_1,5,FALSE) -> 0 | F172: =IF(E$160,E172/E$160,0) -> 0 | H172: =VLOOKUP(A172,TB!TB,5,FALSE) -> 29129 | I172: =IF(H$160,H172/H$160,0) -> 0.013215988 | K172: =VLOOKUP(A172,TB!TB1_1,4,FALSE) -> 0 | L172: =IF(K$160,K172/K$160,0) -> 0 | N172: =VLOOKUP(A172,TB!TB,4,FALSE) -> 29129 | O172: =IF(N$160,N172/N$160,0) -> 0.013215988
A173: 5115502 | C173: New Equipment Other Cleveland | E173: =VLOOKUP(A173,TB!TB1_1,5,FALSE) -> 20418 | F173: =IF(E$160,E173/E$160,0) -> 0.0069020185 | H173: =VLOOKUP(A173,TB!TB,5,FALSE) -> 27206 | I173: =IF(H$160,H173/H$160,0) -> 0.012343512 | K173: =VLOOKUP(A173,TB!TB1_1,4,FALSE) -> 20418 | L173: =IF(K$160,K173/K$160,0) -> 0.0069020185 | N173: =VLOOKUP(A173,TB!TB,4,FALSE) -> 27206 | O173: =IF(N$160,N173/N$160,0) -> 0.012343512
A174: 5115401 | C174: Demo Equipment Linde - Canton | E174: =VLOOKUP(A174,TB!TB1_1,5,FALSE) -> 0 | F174: =IF(E$160,E174/E$160,0) -> 0 | H174: =VLOOKUP(A174,TB!TB,5,FALSE) -> 0 | I174: =IF(H$160,H174/H$160,0) -> 0 | K174: =VLOOKUP(A174,TB!TB1_1,4,FALSE) -> 0 | L174: =IF(K$160,K174/K$160,0) -> 0 | N174: =VLOOKUP(A174,TB!TB,4,FALSE) -> 0 | O174: =IF(N$160,N174/N$160,0) -> 0
A175: 5115402 | C175: Demo Equipment Linde - Cleveland | E175: =VLOOKUP(A175,TB!TB1_1,5,FALSE) -> 0 | F175: =IF(E$160,E175/E$160,0) -> 0 | H175: =VLOOKUP(A175,TB!TB,5,FALSE) -> 0 | I175: =IF(H$160,H175/H$160,0) -> 0 | K175: =VLOOKUP(A175,TB!TB1_1,4,FALSE) -> 0 | L175: =IF(K$160,K175/K$160,0) -> 0 | N175: =VLOOKUP(A175,TB!TB,4,FALSE) -> 0 | O175: =IF(N$160,N175/N$160,0) -> 0
... A179: 5126602 | C179: Parts-Combi - Cleveland | E179: =VLOOKUP(A179,TB!TB1_1,5,FALSE) -> 0 | F179: =IF(E$160,E179/E$160,0) -> 0 | H179: =VLOOKUP(A179,TB!TB,5,FALSE) -> 0 | I179: =IF(H$160,H179/H$160,0) -> 0 | K179: =VLOOKUP(A179,TB!TB1_1,4,FALSE) -> 0 | L179: =IF(K$160,K179/K$160,0) -> 0 | N179: =VLOOKUP(A179,TB!TB,4,FALSE) -> 0 | O179: =IF(N$160,N179/N$160,0) -> 0
A180: 5146601 | C180: Parts-TVH - Canton | E180: 0 | F180: =IF(E$160,E180/E$160,0) -> 0 | H180: =VLOOKUP(A180,TB!TB,5,FALSE) -> 1197.72 | I180: =IF(H$160,H180/H$160,0) -> 0.00054341216 | K180: 0 | L180: =IF(K$160,K180/K$160,0) -> 0 | N180: =VLOOKUP(A180,TB!TB,4,FALSE) -> 1197.72 | O180: =IF(N$160,N180/N$160,0) -> 0.00054341216
A181: 5127601 | C181: Tires - Canton | E181: =VLOOKUP(A181,TB!TB1_1,5,FALSE) -> 787.62 | F181: =IF(E$160,E181/E$160,0) -> 0.00026624389 | H181: =VLOOKUP(A181,TB!TB,5,FALSE) -> 0 | I181: =IF(H$160,H181/H$160,0) -> 0 | K181: =VLOOKUP(A181,TB!TB1_1,4,FALSE) -> 787.62 | L181: =IF(K$160,K181/K$160,0) -> 0.00026624389 | N181: =VLOOKUP(A181,TB!TB,4,FALSE) -> 0 | O181: =IF(N$160,N181/N$160,0) -> 0
A182: 5127602 | C182: Tires - Cleveland | E182: =VLOOKUP(A182,TB!TB1_1,5,FALSE) -> 0 | F182: =IF(E$160,E182/E$160,0) -> 0 | H182: =VLOOKUP(A182,TB!TB,5,FALSE) -> 0 | I182: =IF(H$160,H182/H$160,0) -> 0 | K182: =VLOOKUP(A182,TB!TB1_1,4,FALSE) -> 0 | L182: =IF(K$160,K182/K$160,0) -> 0 | N182: =VLOOKUP(A182,TB!TB,4,FALSE) -> 0 | O182: =IF(N$160,N182/N$160,0) -> 0
A183: 5129601 | C183: Parts-Other - Canton | E183: =VLOOKUP(A183,TB!TB1_1,5,FALSE) -> 36308.55 | F183: =IF(E$160,E183/E$160,0) -> 0.012273596 | H183: =VLOOKUP(A183,TB!TB,5,FALSE) -> 27131.37 | I183: =IF(H$160,H183/H$160,0) -> 0.012309652 | K183: =VLOOKUP(A183,TB!TB1_1,4,FALSE) -> 36308.55 | L183: =IF(K$160,K183/K$160,0) -> 0.012273596 | N183: =VLOOKUP(A183,TB!TB,4,FALSE) -> 27131.37 | O183: =IF(N$160,N183/N$160,0) -> 0.012309652
A184: 5129602 | C184: Parts-Other - Cleveland | E184: =VLOOKUP(A184,TB!TB1_1,5,FALSE) -> 0 | F184: =IF(E$160,E184/E$160,0) -> 0 | H184: =VLOOKUP(A184,TB!TB,5,FALSE) -> 0 | I184: =IF(H$160,H184/H$160,0) -> 0 | K184: =VLOOKUP(A184,TB!TB1_1,4,FALSE) -> 0 | L184: =IF(K$160,K184/K$160,0) -> 0 | N184: =VLOOKUP(A184,TB!TB,4,FALSE) -> 0 | O184: =IF(N$160,N184/N$160,0) -> 0
A185: 5130601 | C185: Shop Parts-Linde - Canton | E185: =VLOOKUP(A185,TB!TB1_1,5,FALSE) -> 3096.43 | F185: =IF(E$160,E185/E$160,0) -> 0.0010467047 | H185: =VLOOKUP(A185,TB!TB,5,FALSE) -> 8330.02 | I185: =IF(H$160,H185/H$160,0) -> 0.0037793759 | K185: =VLOOKUP(A185,TB!TB1_1,4,FALSE) -> 3096.43 | L185: =IF(K$160,K185/K$160,0) -> 0.0010467047 | N185: =VLOOKUP(A185,TB!TB,4,FALSE) -> 8330.02 | O185: =IF(N$160,N185/N$160,0) -> 0.0037793759
A186: 5130602 | C186: Shop Parts-Linde - Cleveland | E186: =VLOOKUP(A186,TB!TB1_1,5,FALSE) -> 0 | F186: =IF(E$160,E186/E$160,0) -> 0 | H186: =VLOOKUP(A186,TB!TB,5,FALSE) -> 0 | I186: =IF(H$160,H186/H$160,0) -> 0 | K186: =VLOOKUP(A186,TB!TB1_1,4,FALSE) -> 0 | L186: =IF(K$160,K186/K$160,0) -> 0 | N186: =VLOOKUP(A186,TB!TB,4,FALSE) -> 0 | O186: =IF(N$160,N186/N$160,0) -> 0
A187: 5131601 | C187: Shop Parts-Combi - Canton | E187: =VLOOKUP(A187,TB!TB1_1,5,FALSE) -> -98.57 | F187: =IF(E$160,E187/E$160,0) -> -3.3320206e-05 | H187: =VLOOKUP(A187,TB!TB,5,FALSE) -> 627.49 | I187: =IF(H$160,H187/H$160,0) -> 0.00028469567 | K187: =VLOOKUP(A187,TB!TB1_1,4,FALSE) -> -98.57 | L187: =IF(K$160,K187/K$160,0) -> -3.3320206e-05 | N187: =VLOOKUP(A187,TB!TB,4,FALSE) -> 627.49 | O187: =IF(N$160,N187/N$160,0) -> 0.00028469567
A188: 5131602 | C188: Shop Parts-Combi - Cleveland | E188: =VLOOKUP(A188,TB!TB1_1,5,FALSE) -> 0 | F188: =IF(E$160,E188/E$160,0) -> 0 | H188: =VLOOKUP(A188,TB!TB,5,FALSE) -> 0 | I188: =IF(H$160,H188/H$160,0) -> 0 | K188: =VLOOKUP(A188,TB!TB1_1,4,FALSE) -> 0 | L188: =IF(K$160,K188/K$160,0) -> 0 | N188: =VLOOKUP(A188,TB!TB,4,FALSE) -> 0 | O188: =IF(N$160,N188/N$160,0) -> 0
A189: 5141601 | C189: Shop Parts-TVH - Canton | E189: 0 | F189: =IF(E$160,E189/E$160,0) -> 0 | H189: =VLOOKUP(A189,TB!TB,5,FALSE) -> 211.65 | I189: =IF(H$160,H189/H$160,0) -> 9.602677e-05 | K189: 0 | L189: =IF(K$160,K189/K$160,0) -> 0 | N189: =VLOOKUP(A189,TB!TB,4,FALSE) -> 211.65 | O189: =IF(N$160,N189/N$160,0) -> 9.602677e-05
A190: 5132601 | C190: Shop Parts-Other - Canton | E190: =VLOOKUP(A190,TB!TB1_1,5,FALSE) -> 15327.18 | F190: =IF(E$160,E190/E$160,0) -> 0.0051811382 | H190: =VLOOKUP(A190,TB!TB,5,FALSE) -> 7473.65 | I190: =IF(H$160,H190/H$160,0) -> 0.0033908361 | K190: =VLOOKUP(A190,TB!TB1_1,4,FALSE) -> 15327.18 | L190: =IF(K$160,K190/K$160,0) -> 0.0051811382 | N190: =VLOOKUP(A190,TB!TB,4,FALSE) -> 7473.65 | O190: =IF(N$160,N190/N$160,0) -> 0.0033908361
A191: 5132602 | C191: Shop Parts-Other - Cleveland | E191: =VLOOKUP(A191,TB!TB1_1,5,FALSE) -> 0 | F191: =IF(E$160,E191/E$160,0) -> 0 | H191: =VLOOKUP(A191,TB!TB,5,FALSE) -> 0 | I191: =IF(H$160,H191/H$160,0) -> 0 | K191: =VLOOKUP(A191,TB!TB1_1,4,FALSE) -> 0 | L191: =IF(K$160,K191/K$160,0) -> 0 | N191: =VLOOKUP(A191,TB!TB,4,FALSE) -> 0 | O191: =IF(N$160,N191/N$160,0) -> 0
A192: 5133601 | C192: Road Parts-Linde - Canton | E192: =VLOOKUP(A192,TB!TB1_1,5,FALSE) -> 20769.97 | F192: =IF(E$160,E192/E$160,0) -> 0.007020997 | H192: =VLOOKUP(A192,TB!TB,5,FALSE) -> 16905.69 | I192: =IF(H$160,H192/H$160,0) -> 0.0076702046 | K192: =VLOOKUP(A192,TB!TB1_1,4,FALSE) -> 20769.97 | L192: =IF(K$160,K192/K$160,0) -> 0.007020997 | N192: =VLOOKUP(A192,TB!TB,4,FALSE) -> 16905.69 | O192: =IF(N$160,N192/N$160,0) -> 0.0076702046
A193: 5133602 | C193: Road Parts-Linde - Cleveland | E193: =VLOOKUP(A193,TB!TB1_1,5,FALSE) -> 0 | F193: =IF(E$160,E193/E$160,0) -> 0 | H193: =VLOOKUP(A193,TB!TB,5,FALSE) -> 0 | I193: =IF(H$160,H193/H$160,0) -> 0 | K193: =VLOOKUP(A193,TB!TB1_1,4,FALSE) -> 0 | L193: =IF(K$160,K193/K$160,0) -> 0 | N193: =VLOOKUP(A193,TB!TB,4,FALSE) -> 0 | O193: =IF(N$160,N193/N$160,0) -> 0
A194: 5134601 | C194: Road Parts-Combi - Canton | E194: =VLOOKUP(A194,TB!TB1_1,5,FALSE) -> 8849.76 | F194: =IF(E$160,E194/E$160,0) -> 0.0029915372 | H194: =VLOOKUP(A194,TB!TB,5,FALSE) -> 10876.04 | I194: =IF(H$160,H194/H$160,0) -> 0.0049345192 | K194: =VLOOKUP(A194,TB!TB1_1,4,FALSE) -> 8849.76 | L194: =IF(K$160,K194/K$160,0) -> 0.0029915372 | N194: =VLOOKUP(A194,TB!TB,4,FALSE) -> 10876.04 | O194: =IF(N$160,N194/N$160,0) -> 0.0049345192
A195: 5134602 | C195: Road Parts-Combi - Cleveland | E195: =VLOOKUP(A195,TB!TB1_1,5,FALSE) -> 0 | F195: =IF(E$160,E195/E$160,0) -> 0 | H195: =VLOOKUP(A195,TB!TB,5,FALSE) -> 0 | I195: =IF(H$160,H195/H$160,0) -> 0 | K195: =VLOOKUP(A195,TB!TB1_1,4,FALSE) -> 0 | L195: =IF(K$160,K195/K$160,0) -> 0 | N195: =VLOOKUP(A195,TB!TB,4,FALSE) -> 0 | O195: =IF(N$160,N195/N$160,0) -> 0
A196: 5144601 | C196: Road Parts-TVH - Canton | E196: 0 | F196: =IF(E$160,E196/E$160,0) -> 0 | H196: =VLOOKUP(A196,TB!TB,5,FALSE) -> 316 | I196: =IF(H$160,H196/H$160,0) -> 0.00014337094 | K196: 0 | L196: =IF(K$160,K196/K$160,0) -> 0 | N196: =VLOOKUP(A196,TB!TB,4,FALSE) -> 316 | O196: =IF(N$160,N196/N$160,0) -> 0.00014337094
A197: 5135601 | C197: Road Parts-Other - Canton | E197: =VLOOKUP(A197,TB!TB1_1,5,FALSE) -> 21058.75 | F197: =IF(E$160,E197/E$160,0) -> 0.007118615 | H197: =VLOOKUP(A197,TB!TB,5,FALSE) -> 27592.34 | I197: =IF(H$160,H197/H$160,0) -> 0.012518797 | K197: =VLOOKUP(A197,TB!TB1_1,4,FALSE) -> 21058.75 | L197: =IF(K$160,K197/K$160,0) -> 0.007118615 | N197: =VLOOKUP(A197,TB!TB,4,FALSE) -> 27592.34 | O197: =IF(N$160,N197/N$160,0) -> 0.012518797
A198: 5135602 | C198: Road Parts-Other - Cleveland | E198: =VLOOKUP(A198,TB!TB1_1,5,FALSE) -> 2367.28 | F198: =IF(E$160,E198/E$160,0) -> 0.00080022579 | H198: =VLOOKUP(A198,TB!TB,5,FALSE) -> 5029.02 | I198: =IF(H$160,H198/H$160,0) -> 0.0022816941 | K198: =VLOOKUP(A198,TB!TB1_1,4,FALSE) -> 2367.28 | L198: =IF(K$160,K198/K$160,0) -> 0.00080022579 | N198: =VLOOKUP(A198,TB!TB,4,FALSE) -> 5029.02 | O198: =IF(N$160,N198/N$160,0) -> 0.0022816941
A199: 5136601 | C199: P M -Linde Parts - Canton | E199: =VLOOKUP(A199,TB!TB1_1,5,FALSE) -> 3791.53 | F199: =IF(E$160,E199/E$160,0) -> 0.0012816735 | H199: =VLOOKUP(A199,TB!TB,5,FALSE) -> 7745.44 | I199: =IF(H$160,H199/H$160,0) -> 0.0035141488 | K199: =VLOOKUP(A199,TB!TB1_1,4,FALSE) -> 3791.53 | L199: =IF(K$160,K199/K$160,0) -> 0.0012816735 | N199: =VLOOKUP(A199,TB!TB,4,FALSE) -> 7745.44 | O199: =IF(N$160,N199/N$160,0) -> 0.0035141488
A200: 5136602 | C200: P M -Linde Parts - Cleveland | E200: =VLOOKUP(A200,TB!TB1_1,5,FALSE) -> 0 | F200: =IF(E$160,E200/E$160,0) -> 0 | H200: =VLOOKUP(A200,TB!TB,5,FALSE) -> 0 | I200: =IF(H$160,H200/H$160,0) -> 0 | K200: =VLOOKUP(A200,TB!TB1_1,4,FALSE) -> 0 | L200: =IF(K$160,K200/K$160,0) -> 0 | N200: =VLOOKUP(A200,TB!TB,4,FALSE) -> 0 | O200: =IF(N$160,N200/N$160,0) -> 0
A201: 5137601 | C201: P M -Combi - Canton | E201: =VLOOKUP(A201,TB!TB1_1,5,FALSE) -> 0 | F201: =IF(E$160,E201/E$160,0) -> 0 | H201: =VLOOKUP(A201,TB!TB,5,FALSE) -> 0 | I201: =IF(H$160,H201/H$160,0) -> 0 | K201: =VLOOKUP(A201,TB!TB1_1,4,FALSE) -> 0 | L201: =IF(K$160,K201/K$160,0) -> 0 | N201: =VLOOKUP(A201,TB!TB,4,FALSE) -> 0 | O201: =IF(N$160,N201/N$160,0) -> 0
A202: 5137602 | C202: P M -Combi - Cleveland | E202: =VLOOKUP(A202,TB!TB1_1,5,FALSE) -> 0 | F202: =IF(E$160,E202/E$160,0) -> 0 | H202: =VLOOKUP(A202,TB!TB,5,FALSE) -> 0 | I202: =IF(H$160,H202/H$160,0) -> 0 | K202: =VLOOKUP(A202,TB!TB1_1,4,FALSE) -> 0 | L202: =IF(K$160,K202/K$160,0) -> 0 | N202: =VLOOKUP(A202,TB!TB,4,FALSE) -> 0 | O202: =IF(N$160,N202/N$160,0) -> 0
A203: 5147601 | C203: P M - TVH - Canton | E203: 0 | F203: =IF(E$160,E203/E$160,0) -> 0 | H203: =VLOOKUP(A203,TB!TB,5,FALSE) -> 185.58 | I203: =IF(H$160,H203/H$160,0) -> 8.4198667e-05 | K203: 0 | L203: =IF(K$160,K203/K$160,0) -> 0 | N203: =VLOOKUP(A203,TB!TB,4,FALSE) -> 185.58 | O203: =IF(N$160,N203/N$160,0) -> 8.4198667e-05
A204: 5138601 | C204: P M - Other Parts - Canton | E204: =VLOOKUP(A204,TB!TB1_1,5,FALSE) -> 774.5 | F204: =IF(E$160,E204/E$160,0) -> 0.00026180886 | H204: =VLOOKUP(A204,TB!TB,5,FALSE) -> 1274.61 | I204: =IF(H$160,H204/H$160,0) -> 0.00057829757 | K204: =VLOOKUP(A204,TB!TB1_1,4,FALSE) -> 774.5 | L204: =IF(K$160,K204/K$160,0) -> 0.00026180886 | N204: =VLOOKUP(A204,TB!TB,4,FALSE) -> 1274.61 | O204: =IF(N$160,N204/N$160,0) -> 0.00057829757
A205: 5138602 | C205: P M - Other Parts - Cleveland | E205: =VLOOKUP(A205,TB!TB1_1,5,FALSE) -> 203.51 | F205: =IF(E$160,E205/E$160,0) -> 6.8793701e-05 | H205: =VLOOKUP(A205,TB!TB,5,FALSE) -> 502.09 | I205: =IF(H$160,H205/H$160,0) -> 0.000227801 | K205: =VLOOKUP(A205,TB!TB1_1,4,FALSE) -> 203.51 | L205: =IF(K$160,K205/K$160,0) -> 6.8793701e-05 | N205: =VLOOKUP(A205,TB!TB,4,FALSE) -> 502.09 | O205: =IF(N$160,N205/N$160,0) -> 0.000227801
...

Sheet Consolidated Expense Statement
A1: Industrial Parts + Service Company
A2: Consolidated Expense Statement
A3: =DATEVALUE(TB!A3&"/"&TB!A4) -> 46023
A4: Description | C4: YTD | F4: MTD | I4: YTD | L4: MTD
A5: Revenue | C5: =TB!A4 -> 2026 | D5: % of Sales | F5: =TB!A4 -> 2026 | G5: % of Sales | I5: =TB!O4 -> 2025 | J5: % of Sales | L5: =TB!O4 -> 2025 | M5: % of Sales
A7: Total Sales | C7: ='Combined Detail P and L'!N160 -> 2204072.9 | D7: =C7/C$7 -> 1 | F7: ='Combined Detail P and L'!H160 -> 2204072.9 | G7: =F7/F$7 -> 1 | I7: ='Combined Detail P and L'!K160 -> 2958265 | J7: =IF(I7,I7/I$7,0) -> 1 | L7: ='Combined Detail P and L'!E160 -> 2958265 | M7: =IF(L7,L7/L$7,0) -> 1
A8: Total GP | C8: ='Combined Detail P and L'!N322 -> 816525.3 | D8: =C8/C$7 -> 0.37046202 | F8: ='Combined Detail P and L'!H322 -> 816525.3 | G8: =F8/F$7 -> 0.37046202 | I8: ='Combined Detail P and L'!K322 -> 757718.3 | J8: =IF(I8,I8/I$7,0) -> 0.25613604 | L8: ='Combined Detail P and L'!E322 -> 757718.3 | M8: =IF(L8,L8/L$7,0) -> 0.25613604
A10: Supervisory | C10: =SUM('Combined Detail P and L'!N326:N339) -> 57023.88 | D10: =C10/C$7 -> 0.025872048 | F10: =SUM('Combined Detail P and L'!H326:H339) -> 57023.88 | G10: =F10/F$7 -> 0.025872048 | I10: =SUM('Combined Detail P and L'!K326:K339) -> 27960 | J10: =IF(I10,I10/I$7,0) -> 0.0094514858 | L10: =SUM('Combined Detail P and L'!E326:E339) -> 27960 | M10: =IF(L10,L10/L$7,0) -> 0.0094514858
A11: Salesmen Salaries | C11: =SUM('Combined Detail P and L'!N340:N346) -> 135811.9 | D11: =C11/C$7 -> 0.061618606 | F11: =SUM('Combined Detail P and L'!H340:H346) -> 135811.9 | G11: =F11/F$7 -> 0.061618606 | I11: =SUM('Combined Detail P and L'!K340:K346) -> 119679.81 | J11: =IF(I11,I11/I$7,0) -> 0.040456081 | L11: =SUM('Combined Detail P and L'!E340:E346) -> 119679.81 | M11: =IF(L11,L11/L$7,0) -> 0.040456081
A12: Support Salaries | C12: =SUM('Combined Detail P and L'!N347:N360) -> 51729.63 | D12: =C12/C$7 -> 0.023470018 | F12: =SUM('Combined Detail P and L'!H347:H360) -> 51729.63 | G12: =F12/F$7 -> 0.023470018 | I12: =SUM('Combined Detail P and L'!K347:K360) -> 46937.65 | J12: =IF(I12,I12/I$7,0) -> 0.015866614 | L12: =SUM('Combined Detail P and L'!E347:E360) -> 46937.65 | M12: =IF(L12,L12/L$7,0) -> 0.015866614
A13: Commissions | C13: =SUM('Combined Detail P and L'!N361:N385) -> 1047.78 | D13: =C13/C$7 -> 0.00047538355 | F13: =SUM('Combined Detail P and L'!H361:H385) -> 1047.78 | G13: =F13/F$7 -> 0.00047538355 | I13: =SUM('Combined Detail P and L'!K361:K385) -> 101604.82 | J13: =IF(I13,I13/I$7,0) -> 0.034346084 | L13: =SUM('Combined Detail P and L'!E361:E385) -> 101604.82 | M13: =IF(L13,L13/L$7,0) -> 0.034346084
A14: Payroll Taxes | C14: =SUM('Combined Detail P and L'!N386:N399) -> 54392.76 | D14: =C14/C$7 -> 0.024678295 | F14: =SUM('Combined Detail P and L'!H386:H399) -> 54392.76 | G14: =F14/F$7 -> 0.024678295 | I14: =SUM('Combined Detail P and L'!K386:K399) -> 45905.48 | J14: =IF(I14,I14/I$7,0) -> 0.015517704 | L14: =SUM('Combined Detail P and L'!E386:E399) -> 45905.48 | M14: =IF(L14,L14/L$7,0) -> 0.015517704
A15: Employee Exp 100% | C15: =SUM('Combined Detail P and L'!N400:N409) -> 2312.36 | D15: =C15/C$7 -> 0.0010491305 | F15: =SUM('Combined Detail P and L'!H400:H409) -> 2312.36 | G15: =F15/F$7 -> 0.0010491305 | I15: =SUM('Combined Detail P and L'!K400:K409) -> 577.5 | J15: =IF(I15,I15/I$7,0) -> 0.00019521577 | L15: =SUM('Combined Detail P and L'!E400:E409) -> 577.5 | M15: =IF(L15,L15/L$7,0) -> 0.00019521577
A16: Employee Exp 50% | C16: =SUM('Combined Detail P and L'!N410:N419) -> 1999.33 | D16: =C16/C$7 -> 0.00090710702 | F16: =SUM('Combined Detail P and L'!H410:H419) -> 1999.33 | G16: =F16/F$7 -> 0.00090710702 | I16: =SUM('Combined Detail P and L'!K410:K419) -> 893.65 | J16: =IF(I16,I16/I$7,0) -> 0.00030208585 | L16: =SUM('Combined Detail P and L'!E410:E419) -> 893.65 | M16: =IF(L16,L16/L$7,0) -> 0.00030208585
A17: Vehicle Repair & Maint | C17: =SUM('Combined Detail P and L'!N420:N429) -> 19624.32 | D17: =C17/C$7 -> 0.008903662 | F17: =SUM('Combined Detail P and L'!H420:H429) -> 19624.32 | G17: =F17/F$7 -> 0.008903662 | I17: =SUM('Combined Detail P and L'!K420:K429) -> 16265.34 | J17: =IF(I17,I17/I$7,0) -> 0.00549827 | L17: =SUM('Combined Detail P and L'!E420:E429) -> 16265.34 | M17: =IF(L17,L17/L$7,0) -> 0.00549827
A18: Rent | C18: =SUM('Combined Detail P and L'!N430:N443) -> 36800 | D18: =C18/C$7 -> 0.016696363 | F18: =SUM('Combined Detail P and L'!H430:H443) -> 36800 | G18: =F18/F$7 -> 0.016696363 | I18: =SUM('Combined Detail P and L'!K430:K443) -> 18064.75 | J18: =IF(I18,I18/I$7,0) -> 0.0061065353 | L18: =SUM('Combined Detail P and L'!E430:E443) -> 18064.75 | M18: =IF(L18,L18/L$7,0) -> 0.0061065353
A19: Utilities | C19: =SUM('Combined Detail P and L'!N444:N445) -> 8562.44 | D19: =C19/C$7 -> 0.0038848262 | F19: =SUM('Combined Detail P and L'!H444:H445) -> 8562.44 | G19: =F19/F$7 -> 0.0038848262 | I19: =SUM('Combined Detail P and L'!H444:K445) -> 15484.574 | J19: =IF(I19,I19/I$7,0) -> 0.005234343 | L19: =SUM('Combined Detail P and L'!E444:E445) -> 6922.13 | M19: =IF(L19,L19/L$7,0) -> 0.0023399289
A20: Building Maintenance | C20: =SUM('Combined Detail P and L'!N446:N447) -> 3372.83 | D20: =C20/C$7 -> 0.0015302715 | F20: =SUM('Combined Detail P and L'!H446:H447) -> 3372.83 | G20: =F20/F$7 -> 0.0015302715 | I20: =SUM('Combined Detail P and L'!K446:K447) -> 15834.76 | J20: =IF(I20,I20/I$7,0) -> 0.0053527185 | L20: =SUM('Combined Detail P and L'!E446:E447) -> 15834.76 | M20: =IF(L20,L20/L$7,0) -> 0.0053527185
A21: Office Supplies | C21: =SUM('Combined Detail P and L'!N448:N461) -> 13475.4 | D21: =C21/C$7 -> 0.0061138631 | F21: =SUM('Combined Detail P and L'!H448:H461) -> 13475.4 | G21: =F21/F$7 -> 0.0061138631 | I21: =SUM('Combined Detail P and L'!K448:K461) -> 2951.99 | J21: =IF(I21,I21/I$7,0) -> 0.00099787881 | L21: =SUM('Combined Detail P and L'!E448:E461) -> 2951.99 | M21: =IF(L21,L21/L$7,0) -> 0.00099787881
A22: Shop Supplies | C22: =SUM('Combined Detail P and L'!N462:N463) -> 6996.54 | D22: =C22/C$7 -> 0.0031743687 | F22: =SUM('Combined Detail P and L'!H462:H463) -> 6996.54 | G22: =F22/F$7 -> 0.0031743687 | I22: =SUM('Combined Detail P and L'!K462:K463) -> 7216.33 | J22: =IF(I22,I22/I$7,0) -> 0.0024393791 | L22: =SUM('Combined Detail P and L'!E462:E463) -> 7216.33 | M22: =IF(L22,L22/L$7,0) -> 0.0024393791
A23: Internal Orders | C23: =SUM('Combined Detail P and L'!N623:N624) -> -67157.89 | D23: =C23/C$7 -> -0.030469904 | F23: =SUM('Combined Detail P and L'!H623:H624) -> -67157.89 | G23: =F23/F$7 -> -0.030469904 | I23: =SUM('Combined Detail P and L'!K623) -> -98430.83 | J23: =IF(I23,I23/I$7,0) -> -0.033273161 | L23: =SUM('Combined Detail P and L'!E623) -> -98430.83 | M23: =IF(L23,L23/L$7,0) -> -0.033273161
A24: Freight | C24: =SUM('Combined Detail P and L'!N464:N469)+E398 -> 3965.2 | D24: =C24/C$7 -> 0.0017990331 | F24: =SUM('Combined Detail P and L'!H466:H469)+H398 -> 3965.2 | G24: =F24/F$7 -> 0.0017990331 | I24: =SUM('Combined Detail P and L'!K466:K469)+K398 -> 6688.68 | J24: =IF(I24,I24/I$7,0) -> 0.0022610144 | L24: =SUM('Combined Detail P and L'!E466:E469)+N398 -> 6688.68 | M24: =IF(L24,L24/L$7,0) -> 0.0022610144
A25: Postage | C25: =SUM('Combined Detail P and L'!N470) -> 0 | D25: =C25/C$7 -> 0 | F25: =SUM('Combined Detail P and L'!H470) -> 0 | G25: =F25/F$7 -> 0 | I25: =SUM('Combined Detail P and L'!K470) -> 63.44 | J25: =IF(I25,I25/I$7,0) -> 2.1445002e-05 | L25: =SUM('Combined Detail P and L'!E470) -> 63.44 | M25: =IF(L25,L25/L$7,0) -> 2.1445002e-05
A26: Communication | C26: =SUM('Combined Detail P and L'!N472:N481) -> 2381.55 | D26: =C26/C$7 -> 0.0010805223 | F26: =SUM('Combined Detail P and L'!H472:H481) -> 2381.55 | G26: =F26/F$7 -> 0.0010805223 | I26: =SUM('Combined Detail P and L'!K472:K481) -> 3220.56 | J26: =IF(I26,I26/I$7,0) -> 0.0010886651 | L26: =SUM('Combined Detail P and L'!E472:E481) -> 3220.56 | M26: =IF(L26,L26/L$7,0) -> 0.0010886651
A27: Legal & Audit | C27: =SUM('Combined Detail P and L'!N482) -> 12015.99 | D27: =C27/C$7 -> 0.0054517208 | F27: =SUM('Combined Detail P and L'!H482) -> 12015.99 | G27: =F27/F$7 -> 0.0054517208 | I27: =SUM('Combined Detail P and L'!K482) -> 21556.4 | J27: =IF(I27,I27/I$7,0) -> 0.0072868386 | L27: =SUM('Combined Detail P and L'!E482) -> 21556.4 | M27: =IF(L27,L27/L$7,0) -> 0.0072868386
A28: Dues & Subscriptions | C28: =SUM('Combined Detail P and L'!N483:N492) -> 22087.26 | D28: =C28/C$7 -> 0.010021111 | F28: =SUM('Combined Detail P and L'!H483:H492) -> 22087.26 | G28: =F28/F$7 -> 0.010021111 | I28: =SUM('Combined Detail P and L'!K483:K492) -> 7071.75 | J28: =IF(I28,I28/I$7,0) -> 0.0023905059 | L28: =SUM('Combined Detail P and L'!E483:E492) -> 7071.75 | M28: =IF(L28,L28/L$7,0) -> 0.0023905059
A29: Product Promotion | C29: =SUM('Combined Detail P and L'!N493:N505) -> 14039.72 | D29: =C29/C$7 -> 0.0063698982 | F29: =SUM('Combined Detail P and L'!H493:H505) -> 14039.72 | G29: =F29/F$7 -> 0.0063698982 | I29: =SUM('Combined Detail P and L'!K493:K505) -> 3442.7 | J29: =IF(I29,I29/I$7,0) -> 0.0011637564 | L29: =SUM('Combined Detail P and L'!E493:E505) -> 3442.7 | M29: =IF(L29,L29/L$7,0) -> 0.0011637564
A30: Training & Education | C30: =SUM('Combined Detail P and L'!N506:N515) -> 0 | D30: =C30/C$7 -> 0 | F30: =SUM('Combined Detail P and L'!H506:H515) -> 0 | G30: =F30/F$7 -> 0 | I30: =SUM('Combined Detail P and L'!K506:K515) -> 0 | J30: =IF(I30,I30/I$7,0) -> 0 | L30: =SUM('Combined Detail P and L'!E506:E515) -> 0 | M30: =IF(L30,L30/L$7,0) -> 0
A31: Consulting Expense | C31: =SUM('Combined Detail P and L'!N516:N525) -> 0 | D31: =C31/C$7 -> 0 | F31: =SUM('Combined Detail P and L'!H516:H525) -> 0 | G31: =F31/F$7 -> 0 | I31: =SUM('Combined Detail P and L'!K516:K525) -> 0 | J31: =IF(I31,I31/I$7,0) -> 0 | L31: =SUM('Combined Detail P and L'!E516:E525) -> 0 | M31: =IF(L31,L31/L$7,0) -> 0
A32: Bad Debt | C32: =SUM('Combined Detail P and L'!N526) -> 0 | D32: =C32/C$7 -> 0 | F32: =SUM('Combined Detail P and L'!H526) -> 0 | G32: =F32/F$7 -> 0 | I32: =SUM('Combined Detail P and L'!K526) -> 0 | J32: =IF(I32,I32/I$7,0) -> 0 | L32: =SUM('Combined Detail P and L'!E526) -> 0 | M32: =IF(L32,L32/L$7,0) -> 0
A33: Contributions | C33: =SUM('Combined Detail P and L'!N527) -> 0 | D33: =C33/C$7 -> 0 | F33: =SUM('Combined Detail P and L'!H527) -> 0 | G33: =F33/F$7 -> 0 | I33: =SUM('Combined Detail P and L'!K527) -> 100 | J33: =IF(I33,I33/I$7,0) -> 3.3803597e-05 | L33: =SUM('Combined Detail P and L'!E527) -> 100 | M33: =IF(L33,L33/L$7,0) -> 3.3803597e-05
A34: Employee Welfare | C34: =SUM('Combined Detail P and L'!N528:N541) -> 7681.06 | D34: =C34/C$7 -> 0.0034849392 | F34: =SUM('Combined Detail P and L'!H528:H541) -> 7681.06 | G34: =F34/F$7 -> 0.0034849392 | I34: =SUM('Combined Detail P and L'!K528:K541) -> 32534.41 | J34: =IF(I34,I34/I$7,0) -> 0.010997801 | L34: =SUM('Combined Detail P and L'!E528:E541) -> 32534.41 | M34: =IF(L34,L34/L$7,0) -> 0.010997801
A35: 401K Contribution | C35: =SUM('Combined Detail P and L'!N542:N555) -> 9276.7 | D35: =C35/C$7 -> 0.0042088898 | F35: =SUM('Combined Detail P and L'!H542:H555) -> 9276.7 | G35: =F35/F$7 -> 0.0042088898 | I35: =SUM('Combined Detail P and L'!K542:K555) -> 8287.56 | J35: =IF(I35,I35/I$7,0) -> 0.0028014934 | L35: =SUM('Combined Detail P and L'!E542:E555) -> 8287.56 | M35: =IF(L35,L35/L$7,0) -> 0.0028014934
A36: Outside Commission | C36: =SUM('Combined Detail P and L'!N556:N559) -> 1900 | D36: =C36/C$7 -> 0.00086204046 | F36: =SUM('Combined Detail P and L'!H556:H559) -> 1900 | G36: =F36/F$7 -> 0.00086204046 | I36: =SUM('Combined Detail P and L'!K556:K559) -> 18504.53 | J36: =IF(I36,I36/I$7,0) -> 0.0062551968 | L36: =SUM('Combined Detail P and L'!E556:E559) -> 18504.53 | M36: =IF(L36,L36/L$7,0) -> 0.0062551968
A37: Personal Property Tax | C37: =SUM('Combined Detail P and L'!N561) -> 0 | D37: =C37/C$7 -> 0 | F37: =SUM('Combined Detail P and L'!H561) -> 0 | G37: =F37/F$7 -> 0 | I37: =SUM('Combined Detail P and L'!K561) -> 0 | J37: =IF(I37,I37/I$7,0) -> 0 | L37: =SUM('Combined Detail P and L'!E561) -> 0 | M37: =IF(L37,L37/L$7,0) -> 0
A38: Insurance | C38: =SUM('Combined Detail P and L'!N562:N575) -> 5319.43 | D38: =C38/C$7 -> 0.0024134547 | F38: =SUM('Combined Detail P and L'!H562:H575) -> 5319.43 | G38: =F38/F$7 -> 0.0024134547 | I38: =SUM('Combined Detail P and L'!K562:K575) -> 9639.9 | J38: =IF(I38,I38/I$7,0) -> 0.003258633 | L38: =SUM('Combined Detail P and L'!E562:E575) -> 9639.9 | M38: =IF(L38,L38/L$7,0) -> 0.003258633
A39: Life Insurance | C39: =SUM('Combined Detail P and L'!N576) -> 0 | D39: =C39/C$7 -> 0 | F39: =SUM('Combined Detail P and L'!H576) -> 0 | G39: =F39/F$7 -> 0 | I39: =SUM('Combined Detail P and L'!K576) -> 0 | J39: =IF(I39,I39/I$7,0) -> 0 | L39: =SUM('Combined Detail P and L'!E576) -> 0 | M39: =IF(L39,L39/L$7,0) -> 0
A40: Interest | C40: =SUM('Combined Detail P and L'!N577:N588) -> 0 | D40: =C40/C$7 -> 0 | F40: =SUM('Combined Detail P and L'!H577:H588) -> 0 | G40: =F40/F$7 -> 0 | I40: =SUM('Combined Detail P and L'!K577:K588) -> 0 | J40: =IF(I40,I40/I$7,0) -> 0 | L40: =SUM('Combined Detail P and L'!E577:E588) -> 0 | M40: =IF(L40,L40/L$7,0) -> 0
A41: Depreciation F & E | C41: =SUM('Combined Detail P and L'!N589:N593) -> 1972.63 | D41: =C41/C$7 -> 0.00089499309 | F41: =SUM('Combined Detail P and L'!H589:H593) -> 1972.63 | G41: =F41/F$7 -> 0.00089499309 | I41: =SUM('Combined Detail P and L'!K589:K593) -> 2606.09 | J41: =IF(I41,I41/I$7,0) -> 0.00088095216 | L41: =SUM('Combined Detail P and L'!E589:E593) -> 2606.09 | M41: =IF(L41,L41/L$7,0) -> 0.00088095216
A42: Depreciation Vehicles | C42: =SUM('Combined Detail P and L'!N594:N595) -> 25984.72 | D42: =C42/C$7 -> 0.01178941 | F42: =SUM('Combined Detail P and L'!H594:H595) -> 25984.72 | G42: =F42/F$7 -> 0.01178941 | I42: =SUM('Combined Detail P and L'!K594:K595) -> 23959.79 | J42: =IF(I42,I42/I$7,0) -> 0.0080992709 | L42: =SUM('Combined Detail P and L'!E594:E595) -> 23959.79 | M42: =IF(L42,L42/L$7,0) -> 0.0080992709
A43: Accum Depr Demo Trucks | C43: =SUM('Combined Detail P and L'!N597:N598) -> 12406.39 | D43: =C43/C$7 -> 0.0056288474 | F43: =SUM('Combined Detail P and L'!H597:H598) -> 12406.39 | G43: =F43/F$7 -> 0.0056288474 | I43: =SUM('Combined Detail P and L'!K597:K598) -> 15095.2 | J43: =IF(I43,I43/I$7,0) -> 0.0051027206 | L43: =SUM('Combined Detail P and L'!E597:E598) -> 15095.2 | M43: =IF(L43,L43/L$7,0) -> 0.0051027206
A44: Depreciation Building | C44: =SUM('Combined Detail P and L'!N599) -> 0 | D44: =C44/C$7 -> 0 | F44: =SUM('Combined Detail P and L'!H599) -> 0 | G44: =F44/F$7 -> 0 | I44: =SUM('Combined Detail P and L'!K599) -> 0 | J44: =IF(I44,I44/I$7,0) -> 0 | L44: =SUM('Combined Detail P and L'!E599) -> 0 | M44: =IF(L44,L44/L$7,0) -> 0
A45: Depreciation Installment Fleet | C45: =SUM('Combined Detail P and L'!N600:N600) -> 0 | D45: =C45/C$7 -> 0 | F45: =SUM('Combined Detail P and L'!H600:H600) -> 0 | G45: =F45/F$7 -> 0 | I45: =SUM('Combined Detail P and L'!K600:K600) -> 0 | J45: =IF(I45,I45/I$7,0) -> 0 | L45: =SUM('Combined Detail P and L'!E600:E600) -> 0 | M45: =IF(L45,L45/L$7,0) -> 0
A46: Amortization Leashold | C46: =SUM('Combined Detail P and L'!N602) -> 162.76 | D46: =C46/C$7 -> 7.3845108e-05 | F46: =SUM('Combined Detail P and L'!H602) -> 162.76 | G46: =F46/F$7 -> 7.3845108e-05 | I46: =SUM('Combined Detail P and L'!K602) -> 162.78 | J46: =IF(I46,I46/I$7,0) -> 5.5025495e-05 | L46: =SUM('Combined Detail P and L'!E602) -> 162.78 | M46: =IF(L46,L46/L$7,0) -> 5.5025495e-05
A47: Depreciation Rental Fleet | C47: =SUM('Combined Detail P and L'!N603:N603) -> 0 | D47: =C47/C$7 -> 0 | F47: =SUM('Combined Detail P and L'!H603:H603) -> 0 | G47: =F47/F$7 -> 0 | I47: =SUM('Combined Detail P and L'!K603:K603) -> 0 | J47: =IF(I47,I47/I$7,0) -> 0 | L47: =SUM('Combined Detail P and L'!E603:E603) -> 0 | M47: =IF(L47,L47/L$7,0) -> 0
A48: Depreciation Finance AMI Leases | C48: =SUM('Combined Detail P and L'!N601) -> 0 | D48: =C48/C$7 -> 0 | F48: =SUM('Combined Detail P and L'!H601) -> 0 | G48: =F48/F$7 -> 0 | I48: =SUM('Combined Detail P and L'!K601) -> 0 | J48: =IF(I48,I48/I$7,0) -> 0 | L48: =SUM('Combined Detail P and L'!E601) -> 0 | M48: =IF(L48,L48/L$7,0) -> 0
A49: Miscellaneous | C49: =SUM('Combined Detail P and L'!N604:N617) -> -22227.72 | D49: =C49/C$7 -> -0.010084839 | F49: =SUM('Combined Detail P and L'!H604:H617) -> -22227.72 | G49: =F49/F$7 -> -0.010084839 | I49: =SUM('Combined Detail P and L'!K604:K617) -> 0 | J49: =IF(I49,I49/I$7,0) -> 0 | L49: =SUM('Combined Detail P and L'!E604:E617) -> 0 | M49: =IF(L49,L49/L$7,0) -> 0
A50: Other Taxes | C50: =SUM('Combined Detail P and L'!N618:N620) -> 18342 | D50: =C50/C$7 -> 0.0083218663 | F50: =SUM('Combined Detail P and L'!H618:H620) -> 18342 | G50: =F50/F$7 -> 0.0083218663 | I50: =SUM('Combined Detail P and L'!K618:K620) -> 84665.58 | J50: =IF(I50,I50/I$7,0) -> 0.028620012 | L50: =SUM('Combined Detail P and L'!E618:E620) -> 84665.58 | M50: =IF(L50,L50/L$7,0) -> 0.028620012
A51: Uniform Rental | C51: =SUM('Combined Detail P and L'!N621:N622) -> 1203.29 | D51: =C51/C$7 -> 0.0005459393 | F51: =SUM('Combined Detail P and L'!H621:H622) -> 1203.29 | G51: =F51/F$7 -> 0.0005459393 | I51: =SUM('Combined Detail P and L'!K621:K622) -> 1531.13 | J51: =IF(I51,I51/I$7,0) -> 0.00051757702 | L51: =SUM('Combined Detail P and L'!E621:E622) -> 1531.13 | M51: =IF(L51,L51/L$7,0) -> 0.00051757702
A52: Total Expenses | C52: =SUM(C10:C51) -> 442502.26 | D52: =C52/C$7 -> 0.20076571 | F52: =SUM(F10:F51) -> 442502.26 | G52: =F52/F$7 -> 0.20076571 | I52: =SUM(I10:I51) -> 560076.32 | J52: =IF(I52,I52/I$7,0) -> 0.18932594 | L52: =SUM(L10:L51) -> 551513.88 | M52: =IF(L52,L52/L$7,0) -> 0.18643153
C56: ='Combined Detail P and L'!N639-'Consolidated Expense Statement'!C52 -> 0

Sheet Consolitated Income Statement
A1: Industrial Parts and Service Company
A2: Consolidated Income Statement
A3: =DATEVALUE(TB!A3&"/"&TB!A4) -> 46023
C4: Description | E4: YTD | H4: MTD | K4: YTD | N4: MTD
A5: Account # | C5: Revenue | E5: =TB!A4 -> 2026 | F5: % of Sales | H5: =TB!A4 -> 2026 | I5: % of Sales | K5: =TB!O4 -> 2025 | L5: % of Sales | N5: =TB!O4 -> 2025 | O5: % of Sales
C7: CH Steel Sales Department | E7: ='C H Steel Solutions'!E14 -> 27086.31 | F7: =IF(E$16,E7/E$16,0) -> 0.013260272 | H7: ='C H Steel Solutions'!H14 -> 27086.31 | I7: =IF(H$16,H7/H$16,0) -> 0.013260272 | K7: ='C H Steel Solutions'!K14 -> 1041443.8 | L7: =IF(K$16,K7/K$16,0) -> 0.36806631 | N7: ='C H Steel Solutions'!N14 -> 1041443.8 | O7: =IF(N$16,N7/N$16,0) -> 0.36806631
C8: Dynamic Storage Solutions | E8: ='Dynamic Storage Solutions'!E13 -> 120425.57 | F8: =IF(E$16,E8/E$16,0) -> 0.05895509 | H8: ='Dynamic Storage Solutions'!H13 -> 120425.57 | I8: =IF(H$16,H8/H$16,0) -> 0.05895509 | K8: ='Dynamic Storage Solutions'!K13 -> 279057.17 | L8: =IF(K$16,K8/K$16,0) -> 0.098624182 | N8: ='Dynamic Storage Solutions'!N13 -> 279057.17 | O8: =IF(N$16,N8/N$16,0) -> 0.098624182
C9: AMI Sales Department | E9: ='AMI Sales Department'!E10 -> 457719.63 | F9: =IF(E$16,E9/E$16,0) -> 0.22407951 | H9: ='AMI Sales Department'!H10 -> 457719.63 | I9: =IF(H$16,H9/H$16,0) -> 0.22407951 | K9: ='AMI Sales Department'!K10 -> 356640.7 | L9: =IF(K$16,K9/K$16,0) -> 0.1260437 | N9: ='AMI Sales Department'!N10 -> 356640.7 | O9: =IF(N$16,N9/N$16,0) -> 0.1260437
C10: Canton Sales Department | E10: ='Canton Sales Department'!E14 -> 534513.17 | F10: =IF(E$16,E10/E$16,0) -> 0.26167426 | H10: ='Canton Sales Department'!H14 -> 534513.17 | I10: =IF(H$16,H10/H$16,0) -> 0.26167426 | K10: ='Canton Sales Department'!K14 -> 332165.25 | L10: =IF(K$16,K10/K$16,0) -> 0.1173936 | N10: ='Canton Sales Department'!N14 -> 332165.25 | O10: =IF(N$16,N10/N$16,0) -> 0.1173936
C11: Parts Department | E11: ='Canton Parts Department'!E32 -> 356824.8 | F11: =IF(E$16,E11/E$16,0) -> 0.17468581 | H11: ='Canton Parts Department'!H32 -> 356824.8 | I11: =IF(H$16,H11/H$16,0) -> 0.17468581 | K11: ='Canton Parts Department'!K32 -> 359559.03 | L11: =IF(K$16,K11/K$16,0) -> 0.12707509 | N11: ='Canton Parts Department'!N32 -> 359559.03 | O11: =IF(N$16,N11/N$16,0) -> 0.12707509
C12: Service Department | E12: ='Canton Service Department'!G29 -> 262602.77 | F12: =IF(E$16,E12/E$16,0) -> 0.12855883 | H12: ='Canton Service Department'!J29 -> 262602.77 | I12: =IF(H$16,H12/H$16,0) -> 0.12855883 | K12: ='Canton Service Department'!M29 -> 195151.12 | L12: =IF(K$16,K12/K$16,0) -> 0.068970167 | N12: ='Canton Service Department'!P29 -> 195151.12 | O12: =IF(N$16,N12/N$16,0) -> 0.068970167
C13: Rental Department | E13: ='Canton Rental Department'!E11 -> 254808.52 | F13: =IF(E$16,E13/E$16,0) -> 0.1247431 | H13: ='Canton Rental Department'!H11 -> 254808.52 | I13: =IF(H$16,H13/H$16,0) -> 0.1247431 | K13: ='Canton Rental Department'!K11 -> 248311.77 | L13: =IF(K$16,K13/K$16,0) -> 0.087758165 | N13: ='Canton Rental Department'!N11 -> 248311.77 | O13: =IF(N$16,N13/N$16,0) -> 0.087758165
C14: Used Department | E14: ='Canton Used Department'!E14 -> 28739.73 | F14: =IF(E$16,E14/E$16,0) -> 0.014069714 | H14: ='Canton Used Department'!H14 -> 28739.73 | I14: =IF(H$16,H14/H$16,0) -> 0.014069714 | K14: ='Canton Used Department'!K14 -> 0 | L14: =IF(K$16,K14/K$16,0) -> 0 | N14: ='Canton Used Department'!N14 -> 0 | O14: =IF(N$16,N14/N$16,0) -> 0
C15: G & A Department | E15: ='Administration Department'!E12 -> -54.31 | F15: =IF(E$16,E15/E$16,0) -> -2.65878e-05 | H15: ='Administration Department'!H12 -> -54.31 | I15: =IF(H$16,H15/H$16,0) -> -2.65878e-05 | K15: ='Administration Department'!K12 -> 17171.65 | L15: =IF(K$16,K15/K$16,0) -> 0.006068792 | N15: ='Administration Department'!N12 -> 17171.65 | O15: =IF(N$16,N15/N$16,0) -> 0.006068792
C16: Total Revenue | E16: =SUM(E7:E15) -> 2042666.2 | F16: =IF(E$16,E16/E$16,0) -> 1 | H16: =SUM(H7:H15) -> 2042666.2 | I16: =IF(H$16,H16/H$16,0) -> 1 | K16: =SUM(K7:K15) -> 2829500.5 | L16: =IF(K$16,K16/K$16,0) -> 1 | N16: =SUM(N7:N15) -> 2829500.5 | O16: =IF(N$16,N16/N$16,0) -> 1
C18: Cost of Sales
C19: CH Steel Sales Department | E19: ='C H Steel Solutions'!E27 -> 21686.31 | F19: =IF(E$16,E19/E$16,0) -> 0.010616669 | H19: ='C H Steel Solutions'!H27 -> 21686.31 | I19: =IF(H$16,H19/H$16,0) -> 0.010616669 | K19: ='C H Steel Solutions'!K27 -> 873769.09 | L19: =IF(K$16,K19/K$16,0) -> 0.30880684 | N19: ='C H Steel Solutions'!N27 -> 873769.09 | O19: =IF(N$16,N19/N$16,0) -> 0.30880684
C20: Dynamic Storage Solutions | E20: ='Dynamic Storage Solutions'!E26 -> 107914.8 | F20: =IF(E$16,E20/E$16,0) -> 0.052830365 | H20: ='Dynamic Storage Solutions'!H26 -> 107914.8 | I20: =IF(H$16,H20/H$16,0) -> 0.052830365 | K20: ='Dynamic Storage Solutions'!K26 -> 204313.07 | L20: =IF(K$16,K20/K$16,0) -> 0.072208176 | N20: ='Dynamic Storage Solutions'!N26 -> 204313.07 | O20: =IF(N$16,N20/N$16,0) -> 0.072208176
C21: AMI Sales Department | E21: ='AMI Sales Department'!E23 -> 185106.95 | F21: =IF(E$16,E21/E$16,0) -> 0.090620264 | H21: ='AMI Sales Department'!H23 -> 185106.95 | I21: =IF(H$16,H21/H$16,0) -> 0.090620264 | K21: ='AMI Sales Department'!K23 -> 229722.49 | L21: =IF(K$16,K21/K$16,0) -> 0.081188355 | N21: ='AMI Sales Department'!N23 -> 229722.49 | O21: =IF(N$16,N21/N$16,0) -> 0.081188355
C22: Canton Sales Department | E22: ='Canton Sales Department'!E29 -> 478571.83 | F22: =IF(E$16,E22/E$16,0) -> 0.23428783 | H22: ='Canton Sales Department'!H29 -> 478571.83 | I22: =IF(H$16,H22/H$16,0) -> 0.23428783 | K22: ='Canton Sales Department'!K29 -> 307893.49 | L22: =IF(K$16,K22/K$16,0) -> 0.10881549 | N22: ='Canton Sales Department'!N29 -> 307893.49 | O22: =IF(N$16,N22/N$16,0) -> 0.10881549
C23: Parts Department | E23: ='Canton Parts Department'!E55 -> 227645.64 | F23: =IF(E$16,E23/E$16,0) -> 0.11144535 | H23: ='Canton Parts Department'!H55 -> 227645.64 | I23: =IF(H$16,H23/H$16,0) -> 0.11144535 | K23: ='Canton Parts Department'!K55 -> 238562.87 | L23: =IF(K$16,K23/K$16,0) -> 0.084312716 | N23: ='Canton Parts Department'!N55 -> 238562.87 | O23: =IF(N$16,N23/N$16,0) -> 0.084312716
C24: Service Department | E24: ='Canton Service Department'!G48 -> 75002.87 | F24: =IF(E$16,E24/E$16,0) -> 0.036718124 | H24: ='Canton Service Department'!J48 -> 75002.87 | I24: =IF(H$16,H24/H$16,0) -> 0.036718124 | K24: ='Canton Service Department'!M48 -> 173013.95 | L24: =IF(K$16,K24/K$16,0) -> 0.061146464 | N24: ='Canton Service Department'!P48 -> 173013.95 | O24: =IF(N$16,N24/N$16,0) -> 0.061146464
C25: Rental Department | E25: ='Canton Rental Department'!E20 -> 82096.66 | F25: =IF(E$16,E25/E$16,0) -> 0.040190933 | H25: ='Canton Rental Department'!H20 -> 82096.66 | I25: =IF(H$16,H25/H$16,0) -> 0.040190933 | K25: ='Canton Rental Department'!K20 -> 65581.25 | L25: =IF(K$16,K25/K$16,0) -> 0.023177678 | N25: ='Canton Rental Department'!N20 -> 65581.25 | O25: =IF(N$16,N25/N$16,0) -> 0.023177678
C26: Used Department | E26: ='Canton Used Department'!E27 -> 32449.45 | F26: =IF(E$16,E26/E$16,0) -> 0.015885831 | H26: ='Canton Used Department'!H27 -> 32449.45 | I26: =IF(H$16,H26/H$16,0) -> 0.015885831 | K26: ='Canton Used Department'!K27 -> 3418.2 | L26: =IF(K$16,K26/K$16,0) -> 0.0012080578 | N26: ='Canton Used Department'!N27 -> 3418.2 | O26: =IF(N$16,N26/N$16,0) -> 0.0012080578
C27: Total Cost of Goods Sold | E27: =SUM(E19:E26) -> 1210474.5 | F27: =IF(E$16,E27/E$16,0) -> 0.59259536 | H27: =SUM(H19:H26) -> 1210474.5 | I27: =IF(H$16,H27/H$16,0) -> 0.59259536 | K27: =SUM(K19:K26) -> 2096274.4 | L27: =IF(K$16,K27/K$16,0) -> 0.74086378 | N27: =SUM(N19:N26) -> 2096274.4 | O27: =IF(N$16,N27/N$16,0) -> 0.74086378
C29: Gross Profit | E29: =E16-E27 -> 832191.68 | F29: =IF(E$16,E29/E$16,0) -> 0.40740464 | H29: =H16-H27 -> 832191.68 | I29: =IF(H$16,H29/H$16,0) -> 0.40740464 | K29: =K16-K27 -> 733226.07 | L29: =IF(K$16,K29/K$16,0) -> 0.25913622 | N29: =N16-N27 -> 733226.07 | O29: =IF(N$16,N29/N$16,0) -> 0.25913622
C31: Expenses
C32: CH Steel Sales Department | E32: ='C H Steel Solutions'!E57 -> 31211.04 | F32: =IF(E$16,E32/E$16,0) -> 0.01527956 | H32: ='C H Steel Solutions'!H57 -> 31211.04 | I32: =IF(H$16,H32/H$16,0) -> 0.01527956 | K32: ='C H Steel Solutions'!K57 -> 138346.7 | L32: =IF(K$16,K32/K$16,0) -> 0.04889439 | N32: ='C H Steel Solutions'!N57 -> 138346.7 | O32: =IF(N$16,N32/N$16,0) -> 0.04889439
C33: Dynamic Storage Solutions | E33: ='Dynamic Storage Solutions'!E56 -> 14642.78 | F33: =IF(E$16,E33/E$16,0) -> 0.0071684645 | H33: ='Dynamic Storage Solutions'!H56 -> 14642.78 | I33: =IF(H$16,H33/H$16,0) -> 0.0071684645 | K33: ='Dynamic Storage Solutions'!K56 -> 9594.77 | L33: =IF(K$16,K33/K$16,0) -> 0.0033909766 | N33: ='Dynamic Storage Solutions'!N56 -> 9594.77 | O33: =IF(N$16,N33/N$16,0) -> 0.0033909766
C34: AMI Sales Department | E34: ='AMI Sales Department'!E49 -> 24384.32 | F34: =IF(E$16,E34/E$16,0) -> 0.011937496 | H34: ='AMI Sales Department'!H49 -> 24384.32 | I34: =IF(H$16,H34/H$16,0) -> 0.011937496 | K34: ='AMI Sales Department'!K49 -> 24953.32 | L34: =IF(K$16,K34/K$16,0) -> 0.0088189842 | N34: ='AMI Sales Department'!N49 -> -24953.32 | O34: =IF(N$16,N34/N$16,0) -> -0.0088189842
C35: Canton Sales Department | E35: ='Canton Sales Department'!E56 -> 71330.27 | F35: =IF(E$16,E35/E$16,0) -> 0.034920179 | H35: ='Canton Sales Department'!H56 -> 71330.27 | I35: =IF(H$16,H35/H$16,0) -> 0.034920179 | K35: ='Canton Sales Department'!K56 -> 91058.91 | L35: =IF(K$16,K35/K$16,0) -> 0.032181974 | N35: ='Canton Sales Department'!N56 -> 91058.91 | O35: =IF(N$16,N35/N$16,0) -> 0.032181974
C36: Parts Department | E36: ='Canton Parts Department'!E80 -> 52798.53 | F36: =IF(E$16,E36/E$16,0) -> 0.02584785 | H36: ='Canton Parts Department'!H80 -> 52798.53 | I36: =IF(H$16,H36/H$16,0) -> 0.02584785 | K36: ='Canton Parts Department'!K80 -> 47104.21 | L36: =IF(K$16,K36/K$16,0) -> 0.016647536 | N36: ='Canton Parts Department'!N80 -> 47104.21 | O36: =IF(N$16,N36/N$16,0) -> 0.016647536
C37: Service Department | E37: ='Canton Service Department'!G76 -> 118327.93 | F37: =IF(E$16,E37/E$16,0) -> 0.057928178 | H37: ='Canton Service Department'!J76 -> 118327.93 | I37: =IF(H$16,H37/H$16,0) -> 0.057928178 | K37: ='Canton Service Department'!M76 -> 129197.15 | L37: =IF(K$16,K37/K$16,0) -> 0.045660763 | N37: ='Canton Service Department'!P76 -> 129197.15 | O37: =IF(N$16,N37/N$16,0) -> 0.045660763
C38: Rental Department | E38: ='Canton Rental Department'!E35 -> 7639.73 | F38: =IF(E$16,E38/E$16,0) -> 0.0037400776 | H38: ='Canton Rental Department'!H35 -> 7639.73 | I38: =IF(H$16,H38/H$16,0) -> 0.0037400776 | K38: ='Canton Rental Department'!K35 -> 3630.02 | L38: =IF(K$16,K38/K$16,0) -> 0.001282919 | N38: ='Canton Rental Department'!N35 -> 3630.02 | O38: =IF(N$16,N38/N$16,0) -> 0.001282919
C39: Used Department | E39: ='Canton Used Department'!E45 -> 3001.11 | F39: =IF(E$16,E39/E$16,0) -> 0.0014692122 | H39: ='Canton Used Department'!H45 -> 3001.11 | I39: =IF(H$16,H39/H$16,0) -> 0.0014692122 | K39: ='Canton Used Department'!K45 -> -11606.29 | L39: =IF(K$16,K39/K$16,0) -> -0.0041018866 | N39: ='Canton Used Department'!N45 -> -11606.29 | O39: =IF(N$16,N39/N$16,0) -> -0.0041018866
C40: Total Expenses | E40: =SUM(E32:E39) -> 323335.71 | F40: =IF(E$16,E40/E$16,0) -> 0.15829102 | H40: =SUM(H32:H39) -> 323335.71 | I40: =IF(H$16,H40/H$16,0) -> 0.15829102 | K40: =SUM(K32:K39) -> 432278.79 | L40: =IF(K$16,K40/K$16,0) -> 0.15277566 | N40: =SUM(N32:N39) -> 382372.15 | O40: =IF(N$16,N40/N$16,0) -> 0.13513769
C42: G & A Department | E42: ='Administration Department'!E47 -> 141723.25 | F42: =IF(E$16,E42/E$16,0) -> 0.069381503 | H42: ='Administration Department'!H47 -> 141723.25 | I42: =IF(H$16,H42/H$16,0) -> 0.069381503 | K42: ='Administration Department'!K47 -> 110446.34 | L42: =IF(K$16,K42/K$16,0) -> 0.039033865 | N42: ='Administration Department'!N47 -> 110446.34 | O42: =IF(N$16,N42/N$16,0) -> 0.039033865
C44: Net Income | E44: =E29-(E40+E42) -> 367132.72 | F44: =IF(E$16,E44/E$16,0) -> 0.17973212 | H44: =H29-(H40+H42) -> 367132.72 | I44: =IF(H$16,H44/H$16,0) -> 0.17973212 | K44: =K29-(K40+K42) -> 190500.94 | L44: =IF(K$16,K44/K$16,0) -> 0.067326704 | N44: =N29-(N40+N42) -> 240407.58 | O44: =IF(N$16,N44/N$16,0) -> 0.084964672
E47: =E44-'Combined Detail P and L'!N641 -> -6890.32 | H47: =H44-'Combined Detail P and L'!H641 -> -6890.32 | K47: =K44-'Combined Detail P and L'!K641 -> -21055.6 | N47: =N44-'Combined Detail P and L'!E641 -> 28851.04

Sheet Dynamic Storage Solutions
A1: Industrial Parts and Service Company
A2: Dynamic Storage Solutions Financial
A3: =DATEVALUE(TB!A3&"/"&TB!A4) -> 46023
C4: Description | E4: YTD | H4: MTD | K4: YTD | N4: MTD
A5: Account # | C5: Revenue | E5: =TB!A4 -> 2026 | F5: % of Sales | H5: =TB!A4 -> 2026 | I5: % of Sales | K5: =TB!O4 -> 2025 | L5: % of Sales | N5: =TB!O4 -> 2025 | O5: % of Sales
A6: 4110504 | C6: New Equipment-Linde | E6: =VLOOKUP(A6,TB!TB,4,FALSE)*-1 -> 0 | F6: =IF(E$13,E6/E$13,0) -> 0 | H6: =VLOOKUP(A6,TB!TB,5,FALSE)*-1 -> 0 | I6: =IF(H$13,H6/H$13,0) -> 0 | K6: =VLOOKUP(A6,TB!TB1_1,4,FALSE)*-1 -> 0 | L6: =IF(K$14,K6/K$14,0) -> 0 | N6: =VLOOKUP(A6,TB!TB1_1,5,FALSE)*-1 -> 0 | O6: =IF(N$14,N6/N$14,0) -> 0
A7: 4113504 | C7: New Equipment-Combi | E7: =VLOOKUP(A7,TB!TB,4,FALSE)*-1 -> 0 | F7: =IF(E$13,E7/E$13,0) -> 0 | H7: =VLOOKUP(A7,TB!TB,5,FALSE)*-1 -> 0 | I7: =IF(H$13,H7/H$13,0) -> 0 | K7: =VLOOKUP(A7,TB!TB1_1,4,FALSE)*-1 -> 0 | L7: =IF(K$14,K7/K$14,0) -> 0 | N7: =VLOOKUP(A7,TB!TB1_1,5,FALSE)*-1 -> 0 | O7: =IF(N$14,N7/N$14,0) -> 0
A8: 4111404 | C8: Commission-Used | E8: =VLOOKUP(A8,TB!TB,4,FALSE)*-1 -> 0 | F8: =IF(E$13,E8/E$13,0) -> 0 | H8: =VLOOKUP(A8,TB!TB,5,FALSE)*-1 -> 0 | I8: =IF(H$13,H8/H$13,0) -> 0 | K8: =VLOOKUP(A8,TB!TB1_1,4,FALSE)*-1 -> 0 | L8: =IF(K$14,K8/K$14,0) -> 0 | N8: =VLOOKUP(A8,TB!TB1_1,5,FALSE)*-1 -> 0 | O8: =IF(N$14,N8/N$14,0) -> 0
A9: 4111504 | C9: Commission-New Equipment | E9: =VLOOKUP(A9,TB!TB,4,FALSE)*-1 -> 0 | F9: =IF(E$13,E9/E$13,0) -> 0 | H9: =VLOOKUP(A9,TB!TB,5,FALSE)*-1 -> 0 | I9: =IF(H$13,H9/H$13,0) -> 0 | K9: =VLOOKUP(A9,TB!TB1_1,4,FALSE)*-1 -> 0 | L9: =IF(K$14,K9/K$14,0) -> 0 | N9: =VLOOKUP(A9,TB!TB1_1,5,FALSE)*-1 -> 0 | O9: =IF(N$14,N9/N$14,0) -> 0
A10: 4112204 | C10: Commission-Allied | E10: =VLOOKUP(A10,TB!TB,4,FALSE)*-1 -> 0 | F10: =IF(E$13,E10/E$13,0) -> 0 | H10: =VLOOKUP(A10,TB!TB,5,FALSE)*-1 -> 0 | I10: =IF(H$13,H10/H$13,0) -> 0 | K10: =VLOOKUP(A10,TB!TB1_1,4,FALSE)*-1 -> 0 | L10: =IF(K$14,K10/K$14,0) -> 0 | N10: =VLOOKUP(A10,TB!TB1_1,5,FALSE)*-1 -> 0 | O10: =IF(N$14,N10/N$14,0) -> 0
A11: 4140504 | C11: Allied Lines Sale | E11: =VLOOKUP(A11,TB!TB,4,FALSE)*-1 -> 112711.88 | F11: =IF(E$13,E11/E$13,0) -> 0.93594641 | H11: =VLOOKUP(A11,TB!TB,5,FALSE)*-1 -> 112711.88 | I11: =IF(H$13,H11/H$13,0) -> 0.93594641 | K11: =VLOOKUP(A11,TB!TB1_1,4,FALSE)*-1 -> 273457 | L11: =IF(K$14,K11/K$14,0) -> 0 | N11: =VLOOKUP(A11,TB!TB1_1,5,FALSE)*-1 -> 273457 | O11: =IF(N$14,N11/N$14,0) -> 0
A12: 4112504 | C12: Freight Income | E12: =VLOOKUP(A12,TB!TB,4,FALSE)*-1 -> 7713.69 | F12: =IF(E$13,E12/E$13,0) -> 0.064053589 | H12: =VLOOKUP(A12,TB!TB,5,FALSE)*-1 -> 7713.69 | I12: =IF(H$13,H12/H$13,0) -> 0.064053589 | K12: =VLOOKUP(A12,TB!TB1_1,4,FALSE)*-1 -> 5600.17 | L12: =IF(K$14,K12/K$14,0) -> 0 | N12: =VLOOKUP(A12,TB!TB1_1,5,FALSE)*-1 -> 5600.17 | O12: =IF(N$14,N12/N$14,0) -> 0
C13: Total Revenue | E13: =SUM(E6:E12) -> 120425.57 | F13: =IF(E$13,E13/E$13,0) -> 1 | H13: =SUM(H6:H12) -> 120425.57 | I13: =IF(H$13,H13/H$13,0) -> 1 | K13: =SUM(K6:K12) -> 279057.17 | L13: =IF(K$13,K13/K$13,0) -> 1 | N13: =SUM(N6:N12) -> 279057.17 | O13: =IF(N$13,N13/N$13,0) -> 1
A16: 5110504 | C16: New Equipment-Linde | E16: =VLOOKUP(A16,TB!TB,4,FALSE) -> 0 | F16: =IF(E$13,E16/E$13,0) -> 0 | H16: =VLOOKUP(A16,TB!TB,5,FALSE) -> 0 | I16: =IF(H$13,H16/H$13,0) -> 0 | K16: =VLOOKUP(A16,TB!TB1_1,4,FALSE) -> 0 | L16: =IF(K$14,K16/K$14,0) -> 0 | N16: =VLOOKUP(A16,TB!TB1_1,5,FALSE) -> 0 | O16: =IF(N$14,N16/N$14,0) -> 0
A17: 5113504 | C17: New Equipment-Combi | E17: =VLOOKUP(A17,TB!TB,4,FALSE) -> 0 | F17: =IF(E$13,E17/E$13,0) -> 0 | H17: =VLOOKUP(A17,TB!TB,5,FALSE) -> 0 | I17: =IF(H$13,H17/H$13,0) -> 0 | K17: =VLOOKUP(A17,TB!TB1_1,4,FALSE) -> 0 | L17: =IF(K$14,K17/K$14,0) -> 0 | N17: =VLOOKUP(A17,TB!TB1_1,5,FALSE) -> 0 | O17: =IF(N$14,N17/N$14,0) -> 0
A18: 5950504 | C18: Make Ready | E18: =VLOOKUP(A18,TB!TB,4,FALSE) -> 0 | F18: =IF(E$13,E18/E$13,0) -> 0 | H18: =VLOOKUP(A18,TB!TB,5,FALSE) -> 0 | I18: =IF(H$13,H18/H$13,0) -> 0 | K18: =VLOOKUP(A18,TB!TB1_1,4,FALSE) -> 0 | L18: =IF(K$14,K18/K$14,0) -> 0 | N18: =VLOOKUP(A18,TB!TB1_1,5,FALSE) -> 0 | O18: =IF(N$14,N18/N$14,0) -> 0
A19: 5956504 | C19: Demo | E19: =VLOOKUP(A19,TB!TB,4,FALSE) -> 0 | F19: =IF(E$13,E19/E$13,0) -> 0 | H19: =VLOOKUP(A19,TB!TB,5,FALSE) -> 0 | I19: =IF(H$13,H19/H$13,0) -> 0 | K19: =VLOOKUP(A19,TB!TB1_1,4,FALSE) -> 0 | L19: =IF(K$14,K19/K$14,0) -> 0 | N19: =VLOOKUP(A19,TB!TB1_1,5,FALSE) -> 0 | O19: =IF(N$14,N19/N$14,0) -> 0
A20: 5951504 | C20: P/L Installment Trucks DSS | E20: =VLOOKUP(A20,TB!TB,4,FALSE) -> 0 | F20: =IF(E$13,E20/E$13,0) -> 0 | H20: =VLOOKUP(A20,TB!TB,5,FALSE) -> 0 | I20: =IF(H$13,H20/H$13,0) -> 0 | K20: =VLOOKUP(A20,TB!TB1_1,4,FALSE) -> 0 | L20: =IF(K$14,K20/K$14,0) -> 0 | N20: =VLOOKUP(A20,TB!TB1_1,5,FALSE) -> 0 | O20: =IF(N$14,N20/N$14,0) -> 0
A21: 5953504 | C21: Sales Discount C H Solutions | E21: =VLOOKUP(A21,TB!TB,4,FALSE) -> 0 | F21: =IF(E$13,E21/E$13,0) -> 0 | H21: =VLOOKUP(A21,TB!TB,5,FALSE) -> 0 | I21: =IF(H$13,H21/H$13,0) -> 0 | K21: =VLOOKUP(A21,TB!TB1_1,4,FALSE) -> 0 | L21: =IF(K$14,K21/K$14,0) -> 0 | N21: =VLOOKUP(A21,TB!TB1_1,5,FALSE) -> 0 | O21: =IF(N$14,N21/N$14,0) -> 0
A22: 5192504 | C22: Internal Rental | E22: =VLOOKUP(A22,TB!TB,4,FALSE) -> 0 | F22: =IF(E$13,E22/E$13,0) -> 0 | H22: =VLOOKUP(A22,TB!TB,5,FALSE) -> 0 | I22: =IF(H$13,H22/H$13,0) -> 0 | K22: =VLOOKUP(A22,TB!TB1_1,4,FALSE) -> 0 | L22: =IF(K$14,K22/K$14,0) -> 0 | N22: =VLOOKUP(A22,TB!TB1_1,5,FALSE) -> 0 | O22: =IF(N$14,N22/N$14,0) -> 0
A23: 5152504 | C23: Internal Delivery | E23: =VLOOKUP(A23,TB!TB,4,FALSE) -> 0 | F23: =IF(E$13,E23/E$13,0) -> 0 | H23: =VLOOKUP(A23,TB!TB,5,FALSE) -> 0 | I23: =IF(H$13,H23/H$13,0) -> 0 | K23: =VLOOKUP(A23,TB!TB1_1,4,FALSE) -> 0 | L23: =IF(K$14,K23/K$14,0) -> 0 | N23: =VLOOKUP(A23,TB!TB1_1,5,FALSE) -> 0 | O23: =IF(N$14,N23/N$14,0) -> 0
A24: 5140504 | C24: Allied Lines | E24: =VLOOKUP(A24,TB!TB,4,FALSE) -> 90635.54 | F24: =IF(E$13,E24/E$13,0) -> 0.75262704 | H24: =VLOOKUP(A24,TB!TB,5,FALSE) -> 90635.54 | I24: =IF(H$13,H24/H$13,0) -> 0.75262704 | K24: =VLOOKUP(A24,TB!TB1_1,4,FALSE) -> 203048.65 | L24: =IF(K$14,K24/K$14,0) -> 0 | N24: =VLOOKUP(A24,TB!TB1_1,5,FALSE) -> 203048.65 | O24: =IF(N$14,N24/N$14,0) -> 0
A25: 6430504 | C25: Freight | E25: =VLOOKUP(A25,TB!TB,4,FALSE) -> 17279.26 | F25: =IF(E$13,E25/E$13,0) -> 0.14348498 | H25: =VLOOKUP(A25,TB!TB,5,FALSE) -> 17279.26 | I25: =IF(H$13,H25/H$13,0) -> 0.14348498 | K25: =VLOOKUP(A25,TB!TB1_1,4,FALSE) -> 1264.42 | L25: =IF(K$14,K25/K$14,0) -> 0 | N25: =VLOOKUP(A25,TB!TB1_1,5,FALSE) -> 1264.42 | O25: =IF(N$14,N25/N$14,0) -> 0
C26: Total Cost of Goods Sold | E26: =SUM(E16:E25) -> 107914.8 | F26: =IF(E$13,E26/E$13,0) -> 0.89611201 | H26: =SUM(H16:H25) -> 107914.8 | I26: =IF(H$13,H26/H$13,0) -> 0.89611201 | K26: =SUM(K16:K25) -> 204313.07 | L26: =IF(K$13,K26/K$13,0) -> 0.73215488 | N26: =SUM(N16:N25) -> 204313.07 | O26: =IF(N$13,N26/N$13,0) -> 0.73215488
C29: Gross Profit | E29: =E13-E26 -> 12510.77 | F29: =IF(E$13,E29/E$13,0) -> 0.10388799 | H29: =H13-H26 -> 12510.77 | I29: =IF(H$13,H29/H$13,0) -> 0.10388799 | K29: =K13-K26 -> 74744.1 | L29: =IF(K$13,K29/K$13,0) -> 0.26784512 | N29: =N13-N26 -> 74744.1 | O29: =IF(N$13,N29/N$13,0) -> 0.26784512
A32: 6010504 | C32: Supervisory | E32: =VLOOKUP(A32,TB!TB,4,FALSE) -> 0 | F32: =IF(E$13,E32/E$13,0) -> 0 | H32: =VLOOKUP(A32,TB!TB,5,FALSE) -> 0 | I32: =IF(H$13,H32/H$13,0) -> 0 | K32: =VLOOKUP(A32,TB!TB1_1,4,FALSE) -> 0 | L32: =IF(K$14,K32/K$14,0) -> 0 | N32: =VLOOKUP(A32,TB!TB1_1,5,FALSE) -> 0 | O32: =IF(N$14,N32/N$14,0) -> 0
A33: 6020504 | C33: Salesman Salaries | E33: =VLOOKUP(A33,TB!TB,4,FALSE) -> 11539.2 | F33: =IF(E$13,E33/E$13,0) -> 0.095820182 | H33: =VLOOKUP(A33,TB!TB,5,FALSE) -> 11539.2 | I33: =IF(H$13,H33/H$13,0) -> 0.095820182 | K33: =VLOOKUP(A33,TB!TB1_1,4,FALSE) -> 11539.2 | L33: =IF(K$14,K33/K$14,0) -> 0 | N33: =VLOOKUP(A33,TB!TB1_1,5,FALSE) -> 11539.2 | O33: =IF(N$14,N33/N$14,0) -> 0
A34: 6050504 | C34: Support Salaries | E34: =VLOOKUP(A34,TB!TB,4,FALSE) -> 0 | F34: =IF(E$13,E34/E$13,0) -> 0 | H34: =VLOOKUP(A34,TB!TB,5,FALSE) -> 0 | I34: =IF(H$13,H34/H$13,0) -> 0 | K34: =VLOOKUP(A34,TB!TB1_1,4,FALSE) -> 0 | L34: =IF(K$14,K34/K$14,0) -> 0 | N34: =VLOOKUP(A34,TB!TB1_1,5,FALSE) -> 0 | O34: =IF(N$14,N34/N$14,0) -> 0
A35: 6061004 | C35: Commission | E35: =VLOOKUP(A35,TB!TB,4,FALSE) -> 0 | F35: =IF(E$13,E35/E$13,0) -> 0 | H35: =VLOOKUP(A35,TB!TB,5,FALSE) -> 0 | I35: =IF(H$13,H35/H$13,0) -> 0 | K35: =VLOOKUP(A35,TB!TB1_1,4,FALSE) -> 0 | L35: =IF(K$14,K35/K$14,0) -> 0 | N35: =VLOOKUP(A35,TB!TB1_1,5,FALSE) -> 0 | O35: =IF(N$14,N35/N$14,0) -> 0
A36: 6111404 | C36: Accrued Commission Used-DSS | E36: =VLOOKUP(A36,TB!TB,4,FALSE) -> 0 | F36: =IF(E$13,E36/E$13,0) -> 0 | H36: =VLOOKUP(A36,TB!TB,5,FALSE) -> 0 | I36: =IF(H$13,H36/H$13,0) -> 0 | K36: =VLOOKUP(A36,TB!TB1_1,4,FALSE) -> 0 | L36: =IF(K$14,K36/K$14,0) -> 0 | N36: =VLOOKUP(A36,TB!TB1_1,5,FALSE) -> 0 | O36: =IF(N$14,N36/N$14,0) -> 0
A37: 6111504 | C37: Accrued Commission New-DSS | E37: =VLOOKUP(A37,TB!TB,4,FALSE) -> 0 | F37: =IF(E$13,E37/E$13,0) -> 0 | H37: =VLOOKUP(A37,TB!TB,5,FALSE) -> 0 | I37: =IF(H$13,H37/H$13,0) -> 0 | K37: =VLOOKUP(A37,TB!TB1_1,4,FALSE) -> 0 | L37: =IF(K$14,K37/K$14,0) -> 0 | N37: =VLOOKUP(A37,TB!TB1_1,5,FALSE) -> 0 | O37: =IF(N$14,N37/N$14,0) -> 0
A38: 6112204 | C38: Accrued Commission Allied-DSS | E38: =VLOOKUP(A38,TB!TB,4,FALSE) -> 0 | F38: =IF(E$13,E38/E$13,0) -> 0 | H38: =VLOOKUP(A38,TB!TB,5,FALSE) -> 0 | I38: =IF(H$13,H38/H$13,0) -> 0 | K38: =VLOOKUP(A38,TB!TB1_1,4,FALSE) -> -4062.24 | L38: =IF(K$14,K38/K$14,0) -> 0 | N38: =VLOOKUP(A38,TB!TB1_1,5,FALSE) -> -4062.24 | O38: =IF(N$14,N38/N$14,0) -> 0
A39: 6070504 | C39: Payroll Taxes | E39: =VLOOKUP(A39,TB!TB,4,FALSE) -> 1081.71 | F39: =IF(E$13,E39/E$13,0) -> 0.0089823947 | H39: =VLOOKUP(A39,TB!TB,5,FALSE) -> 1081.71 | I39: =IF(H$13,H39/H$13,0) -> 0.0089823947 | K39: =VLOOKUP(A39,TB!TB1_1,4,FALSE) -> 969.21 | L39: =IF(K$14,K39/K$14,0) -> 0 | N39: =VLOOKUP(A39,TB!TB1_1,5,FALSE) -> 969.21 | O39: =IF(N$14,N39/N$14,0) -> 0
A40: 6530504 | C40: Employee Welfare | E40: =VLOOKUP(A40,TB!TB,4,FALSE) -> 191.31 | F40: =IF(E$13,E40/E$13,0) -> 0.0015886161 | H40: =VLOOKUP(A40,TB!TB,5,FALSE) -> 191.31 | I40: =IF(H$13,H40/H$13,0) -> 0.0015886161 | K40: =VLOOKUP(A40,TB!TB1_1,4,FALSE) -> 576.25 | L40: =IF(K$14,K40/K$14,0) -> 0 | N40: =VLOOKUP(A40,TB!TB1_1,5,FALSE) -> 576.25 | O40: =IF(N$14,N40/N$14,0) -> 0
A41: 6540504 | C41: 401K Contribution | E41: =VLOOKUP(A41,TB!TB,4,FALSE) -> 0 | F41: =IF(E$13,E41/E$13,0) -> 0 | H41: =VLOOKUP(A41,TB!TB,5,FALSE) -> 0 | I41: =IF(H$13,H41/H$13,0) -> 0 | K41: =VLOOKUP(A41,TB!TB1_1,4,FALSE) -> 0 | L41: =IF(K$14,K41/K$14,0) -> 0 | N41: =VLOOKUP(A41,TB!TB1_1,5,FALSE) -> 0 | O41: =IF(N$14,N41/N$14,0) -> 0
A42: 6100504 | C42: Employee Exp-100% | E42: =VLOOKUP(A42,TB!TB,4,FALSE) -> 34.23 | F42: =IF(E$13,E42/E$13,0) -> 0.00028424196 | H42: =VLOOKUP(A42,TB!TB,5,FALSE) -> 34.23 | I42: =IF(H$13,H42/H$13,0) -> 0.00028424196 | K42: =VLOOKUP(A42,TB!TB1_1,4,FALSE) -> 0 | L42: =IF(K$14,K42/K$14,0) -> 0 | N42: =VLOOKUP(A42,TB!TB1_1,5,FALSE) -> 0 | O42: =IF(N$14,N42/N$14,0) -> 0
A43: 6110504 | C43: Employee Exp-50% | E43: =VLOOKUP(A43,TB!TB,4,FALSE) -> 0 | F43: =IF(E$13,E43/E$13,0) -> 0 | H43: =VLOOKUP(A43,TB!TB,5,FALSE) -> 0 | I43: =IF(H$13,H43/H$13,0) -> 0 | K43: =VLOOKUP(A43,TB!TB1_1,4,FALSE) -> 0 | L43: =IF(K$14,K43/K$14,0) -> 0 | N43: =VLOOKUP(A43,TB!TB1_1,5,FALSE) -> 0 | O43: =IF(N$14,N43/N$14,0) -> 0
... A55: 6910504 | C55: Misc. Expenses | E55: =VLOOKUP(A55,TB!TB,4,FALSE) -> 0 | F55: =IF(E$13,E55/E$13,0) -> 0 | H55: =VLOOKUP(A55,TB!TB,5,FALSE) -> 0 | I55: =IF(H$13,H55/H$13,0) -> 0 | K55: =VLOOKUP(A55,TB!TB1_1,4,FALSE) -> 0 | L55: =IF(K$14,K55/K$14,0) -> 0 | N55: =VLOOKUP(A55,TB!TB1_1,5,FALSE) -> 0 | O55: =IF(N$14,N55/N$14,0) -> 0
C56: Total Expenses | E56: =SUM(E32:E55) -> 14642.78 | F56: =IF(E$13,E56/E$13,0) -> 0.12159195 | H56: =SUM(H32:H55) -> 14642.78 | I56: =IF(H$13,H56/H$13,0) -> 0.12159195 | K56: =SUM(K32:K55) -> 9594.77 | L56: =IF(K$13,K56/K$13,0) -> 0.034382811 | N56: =SUM(N32:N55) -> 9594.77 | O56: =IF(N$13,N56/N$13,0) -> 0.034382811
C58: Net Income | E58: =E29-E56 -> -2132.01 | F58: =IF(E$13,E58/E$13,0) -> -0.017703964 | H58: =H29-H56 -> -2132.01 | I58: =IF(H$13,H58/H$13,0) -> -0.017703964 | K58: =K29-K56 -> 65149.33 | L58: =IF(K$13,K58/K$13,0) -> 0.2334623 | N58: =N29-N56 -> 65149.33 | O58: =IF(N$13,N58/N$13,0) -> 0.2334623
A59: 6980504 | C59: G & A Allocation | E59: =VLOOKUP(A59,TB!TB,4,FALSE) -> 0 | F59: =IF(E$13,E59/E$13,0) -> 0 | H59: =VLOOKUP(A59,TB!TB,5,FALSE) -> 0 | I59: =IF(H$13,H59/H$13,0) -> 0 | K59: 0 | L59: =IF(K$13,K59/K$13,0) -> 0 | N59: 0 | O59: =IF(N$13,N59/N$13,0) -> 0
C61: Income After Allocation | E61: =E58-E59 -> -2132.01 | F61: =IF(E$13,E61/E$13,0) -> -0.017703964 | H61: =H58-H59 -> -2132.01 | I61: =IF(H$13,H61/H$13,0) -> -0.017703964 | K61: =K58-K59 -> 65149.33 | L61: =IF(K$13,K61/K$13,0) -> 0.2334623 | N61: =N58-N59 -> 65149.33 | O61: =IF(N$13,N61/N$13,0) -> 0.2334623

Sheet C H Steel Solutions
A1: Industrial Parts and Service Company
A2: C H Steel Solutions Financial
A3: =DATEVALUE(TB!A3&"/"&TB!A4) -> 46023
C4: Description | E4: YTD | H4: MTD | K4: YTD | N4: MTD
A5: Account # | C5: Revenue | E5: =TB!A4 -> 2026 | F5: % of Sales | H5: =TB!A4 -> 2026 | I5: % of Sales | K5: =TB!O4 -> 2025 | L5: % of Sales | N5: =TB!O4 -> 2025 | O5: % of Sales
A6: 4110503 | C6: New Equipment-Linde | E6: =VLOOKUP(A6,TB!TB,4,FALSE)*-1 -> 0 | F6: =IF(E$14,E6/E$14,0) -> 0 | H6: =VLOOKUP(A6,TB!TB,5,FALSE)*-1 -> 0 | I6: =IF(H$14,H6/H$14,0) -> 0 | K6: =VLOOKUP(A6,TB!TB1_1,4,FALSE)*-1 -> 0 | L6: =IF(K$14,K6/K$14,0) -> 0 | N6: =VLOOKUP(A6,TB!TB1_1,5,FALSE)*-1 -> 0 | O6: =IF(N$14,N6/N$14,0) -> 0
A7: 4113503 | C7: New Equipment-Combi | E7: =VLOOKUP(A7,TB!TB,4,FALSE)*-1 -> 0 | F7: =IF(E$14,E7/E$14,0) -> 0 | H7: =VLOOKUP(A7,TB!TB,5,FALSE)*-1 -> 0 | I7: =IF(H$14,H7/H$14,0) -> 0 | K7: =VLOOKUP(A7,TB!TB1_1,4,FALSE)*-1 -> 764622.72 | L7: =IF(K$14,K7/K$14,0) -> 0.7341949 | N7: =VLOOKUP(A7,TB!TB1_1,5,FALSE)*-1 -> 764622.72 | O7: =IF(N$14,N7/N$14,0) -> 0.7341949
A8: 4111403 | C8: Commission-Used | E8: =VLOOKUP(A8,TB!TB,4,FALSE)*-1 -> 0 | F8: =IF(E$14,E8/E$14,0) -> 0 | H8: =VLOOKUP(A8,TB!TB,5,FALSE)*-1 -> 0 | I8: =IF(H$14,H8/H$14,0) -> 0 | K8: =VLOOKUP(A8,TB!TB1_1,4,FALSE)*-1 -> 0 | L8: =IF(K$14,K8/K$14,0) -> 0 | N8: =VLOOKUP(A8,TB!TB1_1,5,FALSE)*-1 -> 0 | O8: =IF(N$14,N8/N$14,0) -> 0
A9: 4111503 | C9: Commission-New Equipment | E9: =VLOOKUP(A9,TB!TB,4,FALSE)*-1 -> 0 | F9: =IF(E$14,E9/E$14,0) -> 0 | H9: =VLOOKUP(A9,TB!TB,5,FALSE)*-1 -> 0 | I9: =IF(H$14,H9/H$14,0) -> 0 | K9: =VLOOKUP(A9,TB!TB1_1,4,FALSE)*-1 -> 0 | L9: =IF(K$14,K9/K$14,0) -> 0 | N9: =VLOOKUP(A9,TB!TB1_1,5,FALSE)*-1 -> 0 | O9: =IF(N$14,N9/N$14,0) -> 0
A10: 4112203 | C10: Commission-Allied | E10: =VLOOKUP(A10,TB!TB,4,FALSE)*-1 -> 0 | F10: =IF(E$14,E10/E$14,0) -> 0 | H10: =VLOOKUP(A10,TB!TB,5,FALSE)*-1 -> 0 | I10: =IF(H$14,H10/H$14,0) -> 0 | K10: =VLOOKUP(A10,TB!TB1_1,4,FALSE)*-1 -> 0 | L10: =IF(K$14,K10/K$14,0) -> 0 | N10: =VLOOKUP(A10,TB!TB1_1,5,FALSE)*-1 -> 0 | O10: =IF(N$14,N10/N$14,0) -> 0
A11: 4140503 | C11: Allied Lines Sale | E11: =VLOOKUP(A11,TB!TB,4,FALSE)*-1 -> 27086.31 | F11: =IF(E$14,E11/E$14,0) -> 1 | H11: =VLOOKUP(A11,TB!TB,5,FALSE)*-1 -> 27086.31 | I11: =IF(H$14,H11/H$14,0) -> 1 | K11: =VLOOKUP(A11,TB!TB1_1,4,FALSE)*-1 -> 270923.07 | L11: =IF(K$14,K11/K$14,0) -> 0.26014181 | N11: =VLOOKUP(A11,TB!TB1_1,5,FALSE)*-1 -> 270923.07 | O11: =IF(N$14,N11/N$14,0) -> 0.26014181
A12: 4112503 | C12: Freight Income | E12: =VLOOKUP(A12,TB!TB,4,FALSE)*-1 -> 0 | F12: =IF(E$14,E12/E$14,0) -> 0 | H12: =VLOOKUP(A12,TB!TB,5,FALSE)*-1 -> 0 | I12: =IF(H$14,H12/H$14,0) -> 0 | K12: =VLOOKUP(A12,TB!TB1_1,4,FALSE)*-1 -> 5898 | L12: =IF(K$14,K12/K$14,0) -> 0.0056632917 | N12: =VLOOKUP(A12,TB!TB1_1,5,FALSE)*-1 -> 5898 | O12: =IF(N$14,N12/N$14,0) -> 0.0056632917
A13: 4306503 | C13: Parts Sales to C H Steel | E13: =VLOOKUP(A13,TB!TB,4,FALSE)*-1 -> 0 | F13: =IF(E$14,E13/E$14,0) -> 0 | H13: =VLOOKUP(A13,TB!TB,5,FALSE)*-1 -> 0 | I13: =IF(H$14,H13/H$14,0) -> 0 | K13: =VLOOKUP(A13,TB!TB1_1,4,FALSE)*-1 -> 0 | L13: =IF(K$14,K13/K$14,0) -> 0 | N13: =VLOOKUP(A13,TB!TB1_1,5,FALSE)*-1 -> 0 | O13: =IF(N$14,N13/N$14,0) -> 0
C14: Total Revenue | E14: =SUM(E6:E13) -> 27086.31 | F14: =IF(E$14,E14/E$14,0) -> 1 | H14: =SUM(H6:H13) -> 27086.31 | I14: =IF(H$14,H14/H$14,0) -> 1 | K14: =SUM(K6:K13) -> 1041443.8 | L14: =IF(K$14,K14/K$14,0) -> 1 | N14: =SUM(N6:N13) -> 1041443.8 | O14: =IF(N$14,N14/N$14,0) -> 1
A17: 5110503 | C17: New Equipment-Linde | E17: =VLOOKUP(A17,TB!TB,4,FALSE) -> 0 | F17: =IF(E$14,E17/E$14,0) -> 0 | H17: =VLOOKUP(A17,TB!TB,5,FALSE) -> 0 | I17: =IF(H$14,H17/H$14,0) -> 0 | K17: =VLOOKUP(A17,TB!TB1_1,4,FALSE) -> 0 | L17: =IF(K$14,K17/K$14,0) -> 0 | N17: =VLOOKUP(A17,TB!TB1_1,5,FALSE) -> 0 | O17: =IF(N$14,N17/N$14,0) -> 0
A18: 5113503 | C18: New Equipment-Combi | E18: =VLOOKUP(A18,TB!TB,4,FALSE) -> 0 | F18: =IF(E$14,E18/E$14,0) -> 0 | H18: =VLOOKUP(A18,TB!TB,5,FALSE) -> 0 | I18: =IF(H$14,H18/H$14,0) -> 0 | K18: =VLOOKUP(A18,TB!TB1_1,4,FALSE) -> 659733.31 | L18: =IF(K$14,K18/K$14,0) -> 0.63347952 | N18: =VLOOKUP(A18,TB!TB1_1,5,FALSE) -> 659733.31 | O18: =IF(N$14,N18/N$14,0) -> 0.63347952
A19: 5950503 | C19: Make Ready | E19: =VLOOKUP(A19,TB!TB,4,FALSE) -> 0 | F19: =IF(E$14,E19/E$14,0) -> 0 | H19: =VLOOKUP(A19,TB!TB,5,FALSE) -> 0 | I19: =IF(H$14,H19/H$14,0) -> 0 | K19: =VLOOKUP(A19,TB!TB1_1,4,FALSE) -> 604.25 | L19: =IF(K$14,K19/K$14,0) -> 0.00058020414 | N19: =VLOOKUP(A19,TB!TB1_1,5,FALSE) -> 604.25 | O19: =IF(N$14,N19/N$14,0) -> 0.00058020414
A20: 5956503 | C20: Demo | E20: =VLOOKUP(A20,TB!TB,4,FALSE) -> 0 | F20: =IF(E$14,E20/E$14,0) -> 0 | H20: =VLOOKUP(A20,TB!TB,5,FALSE) -> 0 | I20: =IF(H$14,H20/H$14,0) -> 0 | K20: =VLOOKUP(A20,TB!TB1_1,4,FALSE) -> 0 | L20: =IF(K$14,K20/K$14,0) -> 0 | N20: =VLOOKUP(A20,TB!TB1_1,5,FALSE) -> 0 | O20: =IF(N$14,N20/N$14,0) -> 0
A21: 5951503 | C21: P/L Installment Trucks CH Steel | E21: =VLOOKUP(A21,TB!TB,4,FALSE) -> 0 | F21: =IF(E$14,E21/E$14,0) -> 0 | H21: =VLOOKUP(A21,TB!TB,5,FALSE) -> 0 | I21: =IF(H$14,H21/H$14,0) -> 0 | K21: =VLOOKUP(A21,TB!TB1_1,4,FALSE) -> 0 | L21: =IF(K$14,K21/K$14,0) -> 0 | N21: =VLOOKUP(A21,TB!TB1_1,5,FALSE) -> 0 | O21: =IF(N$14,N21/N$14,0) -> 0
A22: 5953503 | C22: Sales Discount CH Steel | E22: =VLOOKUP(A22,TB!TB,4,FALSE) -> 0 | F22: =IF(E$14,E22/E$14,0) -> 0 | H22: =VLOOKUP(A22,TB!TB,5,FALSE) -> 0 | I22: =IF(H$14,H22/H$14,0) -> 0 | K22: =VLOOKUP(A22,TB!TB1_1,4,FALSE) -> 0 | L22: =IF(K$14,K22/K$14,0) -> 0 | N22: =VLOOKUP(A22,TB!TB1_1,5,FALSE) -> 0 | O22: =IF(N$14,N22/N$14,0) -> 0
A23: 5192503 | C23: Internal Rental | E23: =VLOOKUP(A23,TB!TB,4,FALSE) -> 0 | F23: =IF(E$14,E23/E$14,0) -> 0 | H23: =VLOOKUP(A23,TB!TB,5,FALSE) -> 0 | I23: =IF(H$14,H23/H$14,0) -> 0 | K23: =VLOOKUP(A23,TB!TB1_1,4,FALSE) -> 0 | L23: =IF(K$14,K23/K$14,0) -> 0 | N23: =VLOOKUP(A23,TB!TB1_1,5,FALSE) -> 0 | O23: =IF(N$14,N23/N$14,0) -> 0
A24: 5152503 | C24: Internal Delivery | E24: =VLOOKUP(A24,TB!TB,4,FALSE) -> 0 | F24: =IF(E$14,E24/E$14,0) -> 0 | H24: =VLOOKUP(A24,TB!TB,5,FALSE) -> 0 | I24: =IF(H$14,H24/H$14,0) -> 0 | K24: =VLOOKUP(A24,TB!TB1_1,4,FALSE) -> 0 | L24: =IF(K$14,K24/K$14,0) -> 0 | N24: =VLOOKUP(A24,TB!TB1_1,5,FALSE) -> 0 | O24: =IF(N$14,N24/N$14,0) -> 0
A25: 5140503 | C25: Allied Lines | E25: =VLOOKUP(A25,TB!TB,4,FALSE) -> 21686.31 | F25: =IF(E$14,E25/E$14,0) -> 0.8006373 | H25: =VLOOKUP(A25,TB!TB,5,FALSE) -> 21686.31 | I25: =IF(H$14,H25/H$14,0) -> 0.8006373 | K25: =VLOOKUP(A25,TB!TB1_1,4,FALSE) -> 213156.49 | L25: =IF(K$14,K25/K$14,0) -> 0.20467402 | N25: =VLOOKUP(A25,TB!TB1_1,5,FALSE) -> 213156.49 | O25: =IF(N$14,N25/N$14,0) -> 0.20467402
A26: 6430503 | C26: Freight | E26: =VLOOKUP(A26,TB!TB,4,FALSE) -> 0 | F26: =IF(E$14,E26/E$14,0) -> 0 | H26: =VLOOKUP(A26,TB!TB,5,FALSE) -> 0 | I26: =IF(H$14,H26/H$14,0) -> 0 | K26: =VLOOKUP(A26,TB!TB1_1,4,FALSE) -> 275.04 | L26: =IF(K$14,K26/K$14,0) -> 0.00026409491 | N26: =VLOOKUP(A26,TB!TB1_1,5,FALSE) -> 275.04 | O26: =IF(N$14,N26/N$14,0) -> 0.00026409491
C27: Total Cost of Goods Sold | E27: =SUM(E17:E26) -> 21686.31 | F27: =IF(E$14,E27/E$14,0) -> 0.8006373 | H27: =SUM(H17:H26) -> 21686.31 | I27: =IF(H$14,H27/H$14,0) -> 0.8006373 | K27: =SUM(K17:K26) -> 873769.09 | L27: =IF(K$14,K27/K$14,0) -> 0.83899784 | N27: =SUM(N17:N26) -> 873769.09 | O27: =IF(N$14,N27/N$14,0) -> 0.83899784
C30: Gross Profit | E30: =E14-E27 -> 5400 | F30: =IF(E$14,E30/E$14,0) -> 0.1993627 | H30: =H14-H27 -> 5400 | I30: =IF(H$14,H30/H$14,0) -> 0.1993627 | K30: =K14-K27 -> 167674.7 | L30: =IF(K$14,K30/K$14,0) -> 0.16100216 | N30: =N14-N27 -> 167674.7 | O30: =IF(N$14,N30/N$14,0) -> 0.16100216
A33: 6010503 | C33: Supervisory | E33: =VLOOKUP(A33,TB!TB,4,FALSE) -> 0 | F33: =IF(E$14,E33/E$14,0) -> 0 | H33: =VLOOKUP(A33,TB!TB,5,FALSE) -> 0 | I33: =IF(H$14,H33/H$14,0) -> 0 | K33: =VLOOKUP(A33,TB!TB1_1,4,FALSE) -> 0 | L33: =IF(K$14,K33/K$14,0) -> 0 | N33: =VLOOKUP(A33,TB!TB1_1,5,FALSE) -> 0 | O33: =IF(N$14,N33/N$14,0) -> 0
A34: 6020503 | C34: Salesman Salaries | E34: =VLOOKUP(A34,TB!TB,4,FALSE) -> 8076 | F34: =IF(E$14,E34/E$14,0) -> 0.298158 | H34: =VLOOKUP(A34,TB!TB,5,FALSE) -> 8076 | I34: =IF(H$14,H34/H$14,0) -> 0.298158 | K34: =VLOOKUP(A34,TB!TB1_1,4,FALSE) -> 8076 | L34: =IF(K$14,K34/K$14,0) -> 0.0077546192 | N34: =VLOOKUP(A34,TB!TB1_1,5,FALSE) -> 8076 | O34: =IF(N$14,N34/N$14,0) -> 0.0077546192
A35: 6050503 | C35: Support Salaries | E35: =VLOOKUP(A35,TB!TB,4,FALSE) -> 0 | F35: =IF(E$14,E35/E$14,0) -> 0 | H35: =VLOOKUP(A35,TB!TB,5,FALSE) -> 0 | I35: =IF(H$14,H35/H$14,0) -> 0 | K35: =VLOOKUP(A35,TB!TB1_1,4,FALSE) -> 0 | L35: =IF(K$14,K35/K$14,0) -> 0 | N35: =VLOOKUP(A35,TB!TB1_1,5,FALSE) -> 0 | O35: =IF(N$14,N35/N$14,0) -> 0
A36: 6061003 | C36: Commission | E36: =VLOOKUP(A36,TB!TB,4,FALSE) -> 0 | F36: =IF(E$14,E36/E$14,0) -> 0 | H36: =VLOOKUP(A36,TB!TB,5,FALSE) -> 0 | I36: =IF(H$14,H36/H$14,0) -> 0 | K36: =VLOOKUP(A36,TB!TB1_1,4,FALSE) -> 11843.06 | L36: =IF(K$14,K36/K$14,0) -> 0.011371771 | N36: =VLOOKUP(A36,TB!TB1_1,5,FALSE) -> 11843.06 | O36: =IF(N$14,N36/N$14,0) -> 0.011371771
A37: 6111403 | C37: Accrued Commission Used-CH | E37: =VLOOKUP(A37,TB!TB,4,FALSE) -> 0 | F37: =IF(E$14,E37/E$14,0) -> 0 | H37: =VLOOKUP(A37,TB!TB,5,FALSE) -> 0 | I37: =IF(H$14,H37/H$14,0) -> 0 | K37: =VLOOKUP(A37,TB!TB1_1,4,FALSE) -> 0 | L37: =IF(K$14,K37/K$14,0) -> 0 | N37: =VLOOKUP(A37,TB!TB1_1,5,FALSE) -> 0 | O37: =IF(N$14,N37/N$14,0) -> 0
A38: 6111503 | C38: Accrued Commission New-CH | E38: =VLOOKUP(A38,TB!TB,4,FALSE) -> 0 | F38: =IF(E$14,E38/E$14,0) -> 0 | H38: =VLOOKUP(A38,TB!TB,5,FALSE) -> 0 | I38: =IF(H$14,H38/H$14,0) -> 0 | K38: =VLOOKUP(A38,TB!TB1_1,4,FALSE) -> -27442.51 | L38: =IF(K$14,K38/K$14,0) -> -0.026350448 | N38: =VLOOKUP(A38,TB!TB1_1,5,FALSE) -> -27442.51 | O38: =IF(N$14,N38/N$14,0) -> -0.026350448
A39: 6112203 | C39: Accrued Commission Allied-CH | E39: =VLOOKUP(A39,TB!TB,4,FALSE) -> 0 | F39: =IF(E$14,E39/E$14,0) -> 0 | H39: =VLOOKUP(A39,TB!TB,5,FALSE) -> 0 | I39: =IF(H$14,H39/H$14,0) -> 0 | K39: =VLOOKUP(A39,TB!TB1_1,4,FALSE) -> 114280.7 | L39: =IF(K$14,K39/K$14,0) -> 0.10973295 | N39: =VLOOKUP(A39,TB!TB1_1,5,FALSE) -> 114280.7 | O39: =IF(N$14,N39/N$14,0) -> 0.10973295
A40: 6070503 | C40: Payroll Taxes | E40: =VLOOKUP(A40,TB!TB,4,FALSE) -> 15218.78 | F40: =IF(E$14,E40/E$14,0) -> 0.56186243 | H40: =VLOOKUP(A40,TB!TB,5,FALSE) -> 15218.78 | I40: =IF(H$14,H40/H$14,0) -> 0.56186243 | K40: =VLOOKUP(A40,TB!TB1_1,4,FALSE) -> 14928.07 | L40: =IF(K$14,K40/K$14,0) -> 0.014334014 | N40: =VLOOKUP(A40,TB!TB1_1,5,FALSE) -> 14928.07 | O40: =IF(N$14,N40/N$14,0) -> 0.014334014
A41: 6530503 | C41: Employee Welfare | E41: =VLOOKUP(A41,TB!TB,4,FALSE) -> 430.75 | F41: =IF(E$14,E41/E$14,0) -> 0.015902868 | H41: =VLOOKUP(A41,TB!TB,5,FALSE) -> 430.75 | I41: =IF(H$14,H41/H$14,0) -> 0.015902868 | K41: =VLOOKUP(A41,TB!TB1_1,4,FALSE) -> 1093.73 | L41: =IF(K$14,K41/K$14,0) -> 0.0010502055 | N41: =VLOOKUP(A41,TB!TB1_1,5,FALSE) -> 1093.73 | O41: =IF(N$14,N41/N$14,0) -> 0.0010502055
A42: 6540503 | C42: 401K Contribution | E42: =VLOOKUP(A42,TB!TB,4,FALSE) -> 5161.52 | F42: =IF(E$14,E42/E$14,0) -> 0.19055826 | H42: =VLOOKUP(A42,TB!TB,5,FALSE) -> 5161.52 | I42: =IF(H$14,H42/H$14,0) -> 0.19055826 | K42: =VLOOKUP(A42,TB!TB1_1,4,FALSE) -> 4161.52 | L42: =IF(K$14,K42/K$14,0) -> 0.0039959142 | N42: =VLOOKUP(A42,TB!TB1_1,5,FALSE) -> 4161.52 | O42: =IF(N$14,N42/N$14,0) -> 0.0039959142
A43: 6100503 | C43: Employee Exp-100% | E43: =VLOOKUP(A43,TB!TB,4,FALSE) -> 0 | F43: =IF(E$14,E43/E$14,0) -> 0 | H43: =VLOOKUP(A43,TB!TB,5,FALSE) -> 0 | I43: =IF(H$14,H43/H$14,0) -> 0 | K43: =VLOOKUP(A43,TB!TB1_1,4,FALSE) -> 0 | L43: =IF(K$14,K43/K$14,0) -> 0 | N43: =VLOOKUP(A43,TB!TB1_1,5,FALSE) -> 0 | O43: =IF(N$14,N43/N$14,0) -> 0
A44: 6110503 | C44: Employee Exp-50% | E44: =VLOOKUP(A44,TB!TB,4,FALSE) -> 0 | F44: =IF(E$14,E44/E$14,0) -> 0 | H44: =VLOOKUP(A44,TB!TB,5,FALSE) -> 0 | I44: =IF(H$14,H44/H$14,0) -> 0 | K44: =VLOOKUP(A44,TB!TB1_1,4,FALSE) -> 0 | L44: =IF(K$14,K44/K$14,0) -> 0 | N44: =VLOOKUP(A44,TB!TB1_1,5,FALSE) -> 0 | O44: =IF(N$14,N44/N$14,0) -> 0
... A56: 6910503 | C56: Tariff Expenses | E56: =VLOOKUP(A56,TB!TB,4,FALSE) -> 0 | F56: =IF(E$14,E56/E$14,0) -> 0 | H56: =VLOOKUP(A56,TB!TB,5,FALSE) -> 0 | I56: =IF(H$14,H56/H$14,0) -> 0 | K56: =VLOOKUP(A56,TB!TB1_1,4,FALSE) -> 0 | L56: =IF(K$14,K56/K$14,0) -> 0 | N56: =VLOOKUP(A56,TB!TB1_1,5,FALSE) -> 0 | O56: =IF(N$14,N56/N$14,0) -> 0
C57: Total Expenses | E57: =SUM(E33:E56) -> 31211.04 | F57: =IF(E$14,E57/E$14,0) -> 1.152281 | H57: =SUM(H33:H56) -> 31211.04 | I57: =IF(H$14,H57/H$14,0) -> 1.152281 | K57: =SUM(K33:K56) -> 138346.7 | L57: =IF(K$14,K57/K$14,0) -> 0.13284125 | N57: =SUM(N33:N56) -> 138346.7 | O57: =IF(N$14,N57/N$14,0) -> 0.13284125
C59: Net Income | E59: =E30-E57 -> -25811.04 | F59: =IF(E$14,E59/E$14,0) -> -0.95291828 | H59: =H30-H57 -> -25811.04 | I59: =IF(H$14,H59/H$14,0) -> -0.95291828 | K59: =K30-K57 -> 29328 | L59: =IF(K$14,K59/K$14,0) -> 0.028160905 | N59: =N30-N57 -> 29328 | O59: =IF(N$14,N59/N$14,0) -> 0.028160905
A60: 6980503 | C60: G & A Allocation | E60: =VLOOKUP(A60,TB!TB,4,FALSE) -> 0 | F60: =IF(E$14,E60/E$14,0) -> 0 | H60: =VLOOKUP(A60,TB!TB,5,FALSE) -> 0 | I60: =IF(H$14,H60/H$14,0) -> 0 | K60: =VLOOKUP(A60,TB!TB1_1,4,FALSE) -> 8231.06 | L60: =IF(K$14,K60/K$14,0) -> 0.0079035086 | N60: =VLOOKUP(A60,TB!TB1_1,5,FALSE) -> 8231.06 | O60: =IF(N$14,N60/N$14,0) -> 0.0079035086
C62: Income After Allocation | E62: =E59-E60 -> -25811.04 | F62: =IF(E$14,E62/E$14,0) -> -0.95291828 | H62: =H59-H60 -> -25811.04 | I62: =IF(H$14,H62/H$14,0) -> -0.95291828 | K62: =K59-K60 -> 21096.94 | L62: =IF(K$14,K62/K$14,0) -> 0.020257397 | N62: =N59-N60 -> 21096.94 | O62: =IF(N$14,N62/N$14,0) -> 0.020257397

Sheet AMI Sales Department
A1: Industrial Parts and Service Company
A2: AMI Financial
A3: =DATEVALUE(TB!A3&"/"&TB!A4) -> 46023
C4: Description | E4: YTD | H4: MTD | K4: YTD | N4: MTD
A5: Account # | C5: Revenue | E5: =TB!A4 -> 2026 | F5: % of Sales | H5: =TB!A4 -> 2026 | I5: % of Sales | K5: =TB!O4 -> 2025 | L5: % of Sales | N5: =TB!O4 -> 2025 | O5: % of Sales
A7: 4114201 | C7: Installment Sales-Trucks | E7: =VLOOKUP(A7,TB!TB,4,FALSE)*-1 -> 319444.63 | F7: =IF(E$10,E7/E$10,0) -> 0.69790459 | H7: =VLOOKUP(A7,TB!TB,5,FALSE)*-1 -> 319444.63 | I7: =IF(H$10,H7/H$10,0) -> 0.69790459 | K7: =VLOOKUP(A7,TB!TB1_1,4,FALSE)*-1 -> 314340.7 | L7: =IF(K$10,K7/K$10,0) -> 0.88139323 | N7: =VLOOKUP(A7,TB!TB1_1,5,FALSE)*-1 -> 314340.7 | O7: =IF(N$10,N7/N$10,0) -> 0.88139323
A8: 4112201 | C8: Freight Income | E8: =VLOOKUP(A8,TB!TB,4,FALSE)*-1 -> 23275 | F8: =IF(E$10,E8/E$10,0) -> 0.050849906 | H8: =VLOOKUP(A8,TB!TB,5,FALSE)*-1 -> 23275 | I8: =IF(H$10,H8/H$10,0) -> 0.050849906 | K8: =VLOOKUP(A8,TB!TB1_1,4,FALSE)*-1 -> 42300 | L8: =IF(K$10,K8/K$10,0) -> 0.11860677 | N8: =VLOOKUP(A8,TB!TB1_1,5,FALSE)*-1 -> 42300 | O8: =IF(N$10,N8/N$10,0) -> 0.11860677
A9: 4215401 | C9: AMI Used Equipment Sale | E9: =VLOOKUP(A9,TB!TB,4,FALSE)*-1 -> 115000 | F9: =IF(E$10,E9/E$10,0) -> 0.25124551 | H9: =VLOOKUP(A9,TB!TB,5,FALSE)*-1 -> 115000 | I9: =IF(H$10,H9/H$10,0) -> 0.25124551 | K9: =VLOOKUP(A9,TB!TB1_1,4,FALSE)*-1 -> 0 | L9: =IF(K$10,K9/K$10,0) -> 0 | N9: =VLOOKUP(A9,TB!TB1_1,5,FALSE)*-1 -> 0 | O9: =IF(N$10,N9/N$10,0) -> 0
C10: Total Revenue | E10: =SUM(E7:E9) -> 457719.63 | F10: =IF(E$10,E10/E$10,0) -> 1 | H10: =SUM(H7:H9) -> 457719.63 | I10: =IF(H$10,H10/H$10,0) -> 1 | K10: =SUM(K7:K9) -> 356640.7 | L10: =IF(K$10,K10/K$10,0) -> 1 | N10: =SUM(N7:N9) -> 356640.7 | O10: =IF(N$10,N10/N$10,0) -> 1
A12: 5935201 | C12: Sales discpont IF | E12: =VLOOKUP(A12,TB!TB,4,FALSE) -> 0 | F12: =IF(E$10,E12/E$10,0) -> 0 | H12: =VLOOKUP(A12,TB!TB,5,FALSE) -> 0 | I12: =IF(H$10,H12/H$10,0) -> 0 | K12: =VLOOKUP(A12,TB!TB1_1,4,FALSE) -> 0 | L12: =IF(K$10,K12/K$10,0) -> 0 | N12: =VLOOKUP(A12,TB!TB1_1,5,FALSE) -> 0 | O12: =IF(N$10,N12/N$10,0) -> 0
A13: 5950201 | C13: AMI Lease - Make Ready | E13: =VLOOKUP(A13,TB!TB,4,FALSE) -> 1516.47 | F13: =IF(E$10,E13/E$10,0) -> 0.003313098 | H13: =VLOOKUP(A13,TB!TB,5,FALSE) -> 1516.47 | I13: =IF(H$10,H13/H$10,0) -> 0.003313098 | K13: =VLOOKUP(A13,TB!TB1_1,4,FALSE) -> 2415.22 | L13: =IF(K$10,K13/K$10,0) -> 0.0067721379 | N13: =VLOOKUP(A13,TB!TB1_1,5,FALSE) -> 2415.22 | O13: =IF(N$10,N13/N$10,0) -> 0.0067721379
A14: 5152201 | C14: Internal Delivery | E14: =VLOOKUP(A14,TB!TB,4,FALSE) -> 0 | F14: =IF(E$10,E14/E$10,0) -> 0 | H14: =VLOOKUP(A14,TB!TB,5,FALSE) -> 0 | I14: =IF(H$10,H14/H$10,0) -> 0 | K14: =VLOOKUP(A14,TB!TB1_1,4,FALSE) -> 0 | L14: =IF(K$10,K14/K$10,0) -> 0 | N14: =VLOOKUP(A14,TB!TB1_1,5,FALSE) -> 0 | O14: =IF(N$10,N14/N$10,0) -> 0
A15: 5192201 | C15: Internal Rental | E15: =VLOOKUP(A15,TB!TB,4,FALSE) -> 0 | F15: =IF(E$10,E15/E$10,0) -> 0 | H15: =VLOOKUP(A15,TB!TB,5,FALSE) -> 0 | I15: =IF(H$10,H15/H$10,0) -> 0 | K15: =VLOOKUP(A15,TB!TB1_1,4,FALSE) -> 0 | L15: =IF(K$10,K15/K$10,0) -> 0 | N15: =VLOOKUP(A15,TB!TB1_1,5,FALSE) -> 0 | O15: =IF(N$10,N15/N$10,0) -> 0
A16: 5215401 | C16: AMI Used Equipment Cost | E16: =VLOOKUP(A16,TB!TB,4,FALSE) -> -35903.22 | F16: =IF(E$10,E16/E$10,0) -> -0.078439328 | H16: =VLOOKUP(A16,TB!TB,5,FALSE) -> -35903.22 | I16: =IF(H$10,H16/H$10,0) -> -0.078439328 | K16: =VLOOKUP(A16,TB!TB1_1,4,FALSE) -> 0 | L16: =IF(K$10,K16/K$10,0) -> 0 | N16: =VLOOKUP(A16,TB!TB1_1,5,FALSE) -> 0 | O16: =IF(N$10,N16/N$10,0) -> 0
A17: 5950401 | C17: AMI Used Equipment-Prep | E17: =VLOOKUP(A17,TB!TB,4,FALSE) -> 20198.29 | F17: =IF(E$10,E17/E$10,0) -> 0.044128083 | H17: =VLOOKUP(A17,TB!TB,5,FALSE) -> 20198.29 | I17: =IF(H$10,H17/H$10,0) -> 0.044128083 | K17: =VLOOKUP(A17,TB!TB1_1,4,FALSE) -> 25127.84 | L17: =IF(K$10,K17/K$10,0) -> 0.070457017 | N17: =VLOOKUP(A17,TB!TB1_1,5,FALSE) -> 25127.84 | O17: =IF(N$10,N17/N$10,0) -> 0.070457017
A18: 5951201 | C18: P/L Installment Trucks | E18: =VLOOKUP(A18,TB!TB,4,FALSE) -> 16615.88 | F18: =IF(E$10,E18/E$10,0) -> 0.036301436 | H18: =VLOOKUP(A18,TB!TB,5,FALSE) -> 16615.88 | I18: =IF(H$10,H18/H$10,0) -> 0.036301436 | K18: =VLOOKUP(A18,TB!TB1_1,4,FALSE) -> 0 | L18: =IF(K$10,K18/K$10,0) -> 0 | N18: =VLOOKUP(A18,TB!TB1_1,5,FALSE) -> 0 | O18: =IF(N$10,N18/N$10,0) -> 0
A19: 5956201 | C19: GCS Demo | E19: =VLOOKUP(A19,TB!TB,4,FALSE) -> 0 | F19: =IF(E$10,E19/E$10,0) -> 0 | H19: =VLOOKUP(A19,TB!TB,5,FALSE) -> 0 | I19: =IF(H$10,H19/H$10,0) -> 0 | K19: =VLOOKUP(A19,TB!TB1_1,4,FALSE) -> 0 | L19: =IF(K$10,K19/K$10,0) -> 0 | N19: =VLOOKUP(A19,TB!TB1_1,5,FALSE) -> 0 | O19: =IF(N$10,N19/N$10,0) -> 0
A20: 6430201 | C20: Freight | E20: =VLOOKUP(A20,TB!TB,4,FALSE) -> 24450 | F20: =IF(E$10,E20/E$10,0) -> 0.053416979 | H20: =VLOOKUP(A20,TB!TB,5,FALSE) -> 24450 | I20: =IF(H$10,H20/H$10,0) -> 0.053416979 | K20: =VLOOKUP(A20,TB!TB1_1,4,FALSE) -> 52150 | L20: =IF(K$10,K20/K$10,0) -> 0.1462256 | N20: =VLOOKUP(A20,TB!TB1_1,5,FALSE) -> 52150 | O20: =IF(N$10,N20/N$10,0) -> 0.1462256
A21: 6740201 | C21: Interest Expense | E21: =VLOOKUP(A21,TB!TB,4,FALSE) -> 0 | F21: =IF(E$10,E21/E$10,0) -> 0 | H21: =VLOOKUP(A21,TB!TB,5,FALSE) -> 0 | I21: =IF(H$10,H21/H$10,0) -> 0 | K21: =VLOOKUP(A21,TB!TB1_1,4,FALSE) -> 0 | L21: =IF(K$10,K21/K$10,0) -> 0 | N21: =VLOOKUP(A21,TB!TB1_1,5,FALSE) -> 0 | O21: =IF(N$10,N21/N$10,0) -> 0
A22: 6880201 | C22: Accum Depr Alside Trucks | E22: =VLOOKUP(A22,TB!TB,4,FALSE) -> 158229.53 | F22: =IF(E$10,E22/E$10,0) -> 0.34569094 | H22: =VLOOKUP(A22,TB!TB,5,FALSE) -> 158229.53 | I22: =IF(H$10,H22/H$10,0) -> 0.34569094 | K22: =VLOOKUP(A22,TB!TB1_1,4,FALSE) -> 150029.43 | L22: =IF(K$10,K22/K$10,0) -> 0.42067389 | N22: =VLOOKUP(A22,TB!TB1_1,5,FALSE) -> 150029.43 | O22: =IF(N$10,N22/N$10,0) -> 0.42067389
C23: Total Cost of Goods Sold | E23: =SUM(E12:E22) -> 185106.95 | F23: =IF(E$10,E23/E$10,0) -> 0.40441121 | H23: =SUM(H12:H22) -> 185106.95 | I23: =IF(H$10,H23/H$10,0) -> 0.40441121 | K23: =SUM(K12:K22) -> 229722.49 | L23: =IF(K$10,K23/K$10,0) -> 0.64412864 | N23: =SUM(N12:N22) -> 229722.49 | O23: =IF(N$10,N23/N$10,0) -> 0.64412864
C25: Gross Profit | E25: =E10-E23 -> 272612.68 | F25: =IF(E$10,E25/E$10,0) -> 0.59558879 | H25: =H10-H23 -> 272612.68 | I25: =IF(H$10,H25/H$10,0) -> 0.59558879 | K25: =K10-K23 -> 126918.21 | L25: =IF(K$10,K25/K$10,0) -> 0.35587136 | N25: =N10-N23 -> 126918.21 | O25: =IF(N$10,N25/N$10,0) -> 0.35587136
A28: 6010201 | C28: Supervisory | E28: =VLOOKUP(A28,TB!TB,4,FALSE) -> 0 | F28: =IF(E$10,E28/E$10,0) -> 0 | H28: =VLOOKUP(A28,TB!TB,5,FALSE) -> 0 | I28: =IF(H$10,H28/H$10,0) -> 0 | K28: =VLOOKUP(A28,TB!TB1_1,4,FALSE) -> 0 | L28: =IF(K$10,K28/K$10,0) -> 0 | N28: =VLOOKUP(A28,TB!TB1_1,5,FALSE)*-1 -> 0 | O28: =IF(N$10,N28/N$10,0) -> 0
A29: 6020201 | C29: Salesman Salaries | E29: =VLOOKUP(A29,TB!TB,4,FALSE) -> 0 | F29: =IF(E$10,E29/E$10,0) -> 0 | H29: =VLOOKUP(A29,TB!TB,5,FALSE) -> 0 | I29: =IF(H$10,H29/H$10,0) -> 0 | K29: =VLOOKUP(A29,TB!TB1_1,4,FALSE) -> 0 | L29: =IF(K$10,K29/K$10,0) -> 0 | N29: =VLOOKUP(A29,TB!TB1_1,5,FALSE)*-1 -> 0 | O29: =IF(N$10,N29/N$10,0) -> 0
A30: 6050201 | C30: Support Salaries | E30: =VLOOKUP(A30,TB!TB,4,FALSE) -> 11040 | F30: =IF(E$10,E30/E$10,0) -> 0.024119569 | H30: =VLOOKUP(A30,TB!TB,5,FALSE) -> 11040 | I30: =IF(H$10,H30/H$10,0) -> 0.024119569 | K30: =VLOOKUP(A30,TB!TB1_1,4,FALSE) -> 10240 | L30: =IF(K$10,K30/K$10,0) -> 0.028712371 | N30: =VLOOKUP(A30,TB!TB1_1,5,FALSE)*-1 -> -10240 | O30: =IF(N$10,N30/N$10,0) -> -0.028712371
A31: 6061201 | C31: Commission | E31: =VLOOKUP(A31,TB!TB,4,FALSE) -> 0 | F31: =IF(E$10,E31/E$10,0) -> 0 | H31: =VLOOKUP(A31,TB!TB,5,FALSE) -> 0 | I31: =IF(H$10,H31/H$10,0) -> 0 | K31: =VLOOKUP(A31,TB!TB1_1,4,FALSE) -> 0 | L31: =IF(K$10,K31/K$10,0) -> 0 | N31: =VLOOKUP(A31,TB!TB1_1,5,FALSE)*-1 -> 0 | O31: =IF(N$10,N31/N$10,0) -> 0
A32: 6070201 | C32: Payroll Taxes | E32: =VLOOKUP(A32,TB!TB,4,FALSE) -> 1043.52 | F32: =IF(E$10,E32/E$10,0) -> 0.0022798236 | H32: =VLOOKUP(A32,TB!TB,5,FALSE) -> 1043.52 | I32: =IF(H$10,H32/H$10,0) -> 0.0022798236 | K32: =VLOOKUP(A32,TB!TB1_1,4,FALSE) -> 869.82 | L32: =IF(K$10,K32/K$10,0) -> 0.0024389252 | N32: =VLOOKUP(A32,TB!TB1_1,5,FALSE)*-1 -> -869.82 | O32: =IF(N$10,N32/N$10,0) -> -0.0024389252
A33: 6530201 | C33: Employee Welfare | E33: =VLOOKUP(A33,TB!TB,4,FALSE) -> -139.2 | F33: =IF(E$10,E33/E$10,0) -> -0.0003041163 | H33: =VLOOKUP(A33,TB!TB,5,FALSE) -> -139.2 | I33: =IF(H$10,H33/H$10,0) -> -0.0003041163 | K33: =VLOOKUP(A33,TB!TB1_1,4,FALSE) -> -155.2 | L33: =IF(K$10,K33/K$10,0) -> -0.00043517187 | N33: =VLOOKUP(A33,TB!TB1_1,5,FALSE)*-1 -> 155.2 | O33: =IF(N$10,N33/N$10,0) -> 0.00043517187
A34: 6540201 | C34: 401K Contribution | E34: =VLOOKUP(A34,TB!TB,4,FALSE) -> 0 | F34: =IF(E$10,E34/E$10,0) -> 0 | H34: =VLOOKUP(A34,TB!TB,5,FALSE) -> 0 | I34: =IF(H$10,H34/H$10,0) -> 0 | K34: =VLOOKUP(A34,TB!TB1_1,4,FALSE) -> 0 | L34: =IF(K$10,K34/K$10,0) -> 0 | N34: =VLOOKUP(A34,TB!TB1_1,5,FALSE)*-1 -> 0 | O34: =IF(N$10,N34/N$10,0) -> 0
A35: 6100201 | C35: Employee Exp-100% | E35: =VLOOKUP(A35,TB!TB,4,FALSE) -> 0 | F35: =IF(E$10,E35/E$10,0) -> 0 | H35: =VLOOKUP(A35,TB!TB,5,FALSE) -> 0 | I35: =IF(H$10,H35/H$10,0) -> 0 | K35: =VLOOKUP(A35,TB!TB1_1,4,FALSE) -> 0 | L35: =IF(K$10,K35/K$10,0) -> 0 | N35: =VLOOKUP(A35,TB!TB1_1,5,FALSE)*-1 -> 0 | O35: =IF(N$10,N35/N$10,0) -> 0
A36: 6110201 | C36: Employee Exp-50% | E36: =VLOOKUP(A36,TB!TB,4,FALSE) -> 0 | F36: =IF(E$10,E36/E$10,0) -> 0 | H36: =VLOOKUP(A36,TB!TB,5,FALSE) -> 0 | I36: =IF(H$10,H36/H$10,0) -> 0 | K36: =VLOOKUP(A36,TB!TB1_1,4,FALSE) -> 0 | L36: =IF(K$10,K36/K$10,0) -> 0 | N36: =VLOOKUP(A36,TB!TB1_1,5,FALSE)*-1 -> 0 | O36: =IF(N$10,N36/N$10,0) -> 0
A37: 6210201 | C37: Vehicle Repair & Maint | E37: =VLOOKUP(A37,TB!TB,4,FALSE) -> 0 | F37: =IF(E$10,E37/E$10,0) -> 0 | H37: =VLOOKUP(A37,TB!TB,5,FALSE) -> 0 | I37: =IF(H$10,H37/H$10,0) -> 0 | K37: =VLOOKUP(A37,TB!TB1_1,4,FALSE) -> 0 | L37: =IF(K$10,K37/K$10,0) -> 0 | N37: =VLOOKUP(A37,TB!TB1_1,5,FALSE)*-1 -> 0 | O37: =IF(N$10,N37/N$10,0) -> 0
A38: 6310201 | C38: Rent | E38: =VLOOKUP(A38,TB!TB,4,FALSE) -> 11040 | F38: =IF(E$10,E38/E$10,0) -> 0.024119569 | H38: =VLOOKUP(A38,TB!TB,5,FALSE) -> 11040 | I38: =IF(H$10,H38/H$10,0) -> 0.024119569 | K38: =VLOOKUP(A38,TB!TB1_1,4,FALSE) -> 4937.5 | L38: =IF(K$10,K38/K$10,0) -> 0.013844466 | N38: =VLOOKUP(A38,TB!TB1_1,5,FALSE)*-1 -> -4937.5 | O38: =IF(N$10,N38/N$10,0) -> -0.013844466
A39: 6410201 | C39: Office Supplies | E39: =VLOOKUP(A39,TB!TB,4,FALSE) -> 0 | F39: =IF(E$10,E39/E$10,0) -> 0 | H39: =VLOOKUP(A39,TB!TB,5,FALSE) -> 0 | I39: =IF(H$10,H39/H$10,0) -> 0 | K39: =VLOOKUP(A39,TB!TB1_1,4,FALSE) -> 160 | L39: =IF(K$10,K39/K$10,0) -> 0.00044863079 | N39: =VLOOKUP(A39,TB!TB1_1,5,FALSE)*-1 -> -160 | O39: =IF(N$10,N39/N$10,0) -> -0.00044863079
... A48: 6880001 | C48: Depr - Finance AMI Leases | E48: =VLOOKUP(A48,TB!TB,4,FALSE) -> 0 | F48: =IF(E$10,E48/E$10,0) -> 0 | H48: =VLOOKUP(A48,TB!TB,5,FALSE) -> 0 | I48: =IF(H$10,H48/H$10,0) -> 0 | K48: =VLOOKUP(A48,TB!TB1_1,4,FALSE) -> 0 | L48: =IF(K$10,K48/K$10,0) -> 0 | N48: =VLOOKUP(A48,TB!TB1_1,5,FALSE)*-1 -> 0 | O48: =IF(N$10,N48/N$10,0) -> 0
C49: Total Expenses | E49: =SUM(E28:E47) -> 24384.32 | F49: =IF(E$10,E49/E$10,0) -> 0.053273485 | H49: =SUM(H28:H47) -> 24384.32 | I49: =IF(H$10,H49/H$10,0) -> 0.053273485 | K49: =SUM(K28:K47) -> 24953.32 | L49: =IF(K$10,K49/K$10,0) -> 0.069967673 | N49: =SUM(N28:N47) -> -24953.32 | O49: =IF(N$10,N49/N$10,0) -> -0.069967673
C51: Net Income | E51: =E25-E49 -> 248228.36 | F51: =IF(E$10,E51/E$10,0) -> 0.5423153 | H51: =H25-H49 -> 248228.36 | I51: =IF(H$10,H51/H$10,0) -> 0.5423153 | K51: =K25-K49 -> 101964.89 | L51: =IF(K$10,K51/K$10,0) -> 0.28590368 | N51: =N25-N49 -> 151871.53 | O51: =IF(N$10,N51/N$10,0) -> 0.42583903
A52: 6980201 | C52: G & A Allocation | E52: =VLOOKUP(A52,TB!TB,4,FALSE) -> 0 | F52: =IF(E$10,E52/E$10,0) -> 0 | H52: =VLOOKUP(A52,TB!TB,5,FALSE) -> 0 | I52: =IF(H$10,H52/H$10,0) -> 0 | K52: =VLOOKUP(A52,TB!TB1_1,4,FALSE) -> 8231.06 | L52: =IF(K$10,K52/K$10,0) -> 0.023079419 | N52: =VLOOKUP(A52,TB!TB1_1,5,FALSE)*-1 -> -8231.06 | O52: =IF(N$10,N52/N$10,0) -> -0.023079419
C54: Income After Allocation | E54: =E51-E52 -> 248228.36 | F54: =IF(E$10,E54/E$10,0) -> 0.5423153 | H54: =H51-H52 -> 248228.36 | I54: =IF(H$10,H54/H$10,0) -> 0.5423153 | K54: =K51-K52 -> 93733.83 | L54: =IF(K$10,K54/K$10,0) -> 0.26282427 | N54: =N51-N52 -> 160102.59 | O54: =IF(N$10,N54/N$10,0) -> 0.44891845

Sheet Canton Sales Department
A1: Industrial Parts and Service Company
A2: Canton Sales Department Financial
A3: =DATEVALUE(TB!A3&"/"&TB!A4) -> 46023
C4: Description | E4: YTD | H4: MTD | K4: YTD | N4: MTD
A5: Account # | C5: Revenue | E5: =TB!A4 -> 2026 | F5: % of Sales | H5: =TB!A4 -> 2026 | I5: % of Sales | K5: =TB!O4 -> 2025 | L5: % of Sales | N5: =TB!O4 -> 2025 | O5: % of Sales
A7: 4110501 | C7: New Equipment Linde | E7: =VLOOKUP(A7,TB!TB,4,FALSE)*-1 -> 239550 | F7: =IF(E$14,E7/E$14,0) -> 0.44816482 | H7: =VLOOKUP(A7,TB!TB,5,FALSE)*-1 -> 239550 | I7: =IF(H$14,H7/H$14,0) -> 0.44816482 | K7: =VLOOKUP(A7,TB!TB1_1,4,FALSE)*-1 -> 73800 | L7: =IF(K$14,K7/K$14,0) -> 0.22217857 | N7: =VLOOKUP(A7,TB!TB1_1,5,FALSE)*-1 -> 73800 | O7: =IF(N$14,N7/N$14,0) -> 0.22217857
A8: 4113501 | C8: New Equipment Combi | E8: =VLOOKUP(A8,TB!TB,4,FALSE)*-1 -> 221925 | F8: =IF(E$14,E8/E$14,0) -> 0.41519089 | H8: =VLOOKUP(A8,TB!TB,5,FALSE)*-1 -> 221925 | I8: =IF(H$14,H8/H$14,0) -> 0.41519089 | K8: =VLOOKUP(A8,TB!TB1_1,4,FALSE)*-1 -> 208035 | L8: =IF(K$14,K8/K$14,0) -> 0.62629971 | N8: =VLOOKUP(A8,TB!TB1_1,5,FALSE)*-1 -> 208035 | O8: =IF(N$14,N8/N$14,0) -> 0.62629971
A9: 4112001 | C9: Commission - Allied | E9: =VLOOKUP(A9,TB!TB,4,FALSE)*-1 -> 0 | F9: =IF(E$14,E9/E$14,0) -> 0 | H9: =VLOOKUP(A9,TB!TB,5,FALSE)*-1 -> 0 | I9: =IF(H$14,H9/H$14,0) -> 0 | K9: 0 | L9: =IF(K$14,K9/K$14,0) -> 0 | N9: 0 | O9: =IF(N$14,N9/N$14,0) -> 0
A10: 4111501 | C10: Commission-New Equipment | E10: =VLOOKUP(A10,TB!TB,4,FALSE)*-1 -> 550 | F10: =IF(E$14,E10/E$14,0) -> 0.0010289737 | H10: =VLOOKUP(A10,TB!TB,5,FALSE)*-1 -> 550 | I10: =IF(H$14,H10/H$14,0) -> 0.0010289737 | K10: =VLOOKUP(A10,TB!TB1_1,4,FALSE)*-1 -> 18200 | L10: =IF(K$14,K10/K$14,0) -> 0.054792005 | N10: =VLOOKUP(A10,TB!TB1_1,5,FALSE)*-1 -> 18200 | O10: =IF(N$14,N10/N$14,0) -> 0.054792005
A11: 4115501 | C11: New Equipment Other Canton | E11: =VLOOKUP(A11,TB!TB,4,FALSE)*-1 -> 18495.95 | F11: =IF(E$14,E11/E$14,0) -> 0.034603357 | H11: =VLOOKUP(A11,TB!TB,5,FALSE)*-1 -> 18495.95 | I11: =IF(H$14,H11/H$14,0) -> 0.034603357 | K11: =VLOOKUP(A11,TB!TB1_1,4,FALSE)*-1 -> 0 | L11: =IF(K$14,K11/K$14,0) -> 0 | N11: =VLOOKUP(A11,TB!TB1_1,5,FALSE)*-1 -> 0 | O11: =IF(N$14,N11/N$14,0) -> 0
A12: 4140501 | C12: Allied Lines Sale | E12: =VLOOKUP(A12,TB!TB,4,FALSE)*-1 -> 43232.22 | F12: =IF(E$14,E12/E$14,0) -> 0.080881487 | H12: =VLOOKUP(A12,TB!TB,5,FALSE)*-1 -> 43232.22 | I12: =IF(H$14,H12/H$14,0) -> 0.080881487 | K12: =VLOOKUP(A12,TB!TB1_1,4,FALSE)*-1 -> 28794 | L12: =IF(K$14,K12/K$14,0) -> 0.086685769 | N12: =VLOOKUP(A12,TB!TB1_1,5,FALSE)*-1 -> 28794 | O12: =IF(N$14,N12/N$14,0) -> 0.086685769
A13: 4112501 | C13: Freight Income | E13: =VLOOKUP(A13,TB!TB,4,FALSE)*-1 -> 10760 | F13: =IF(E$14,E13/E$14,0) -> 0.020130468 | H13: =VLOOKUP(A13,TB!TB,5,FALSE)*-1 -> 10760 | I13: =IF(H$14,H13/H$14,0) -> 0.020130468 | K13: =VLOOKUP(A13,TB!TB1_1,4,FALSE)*-1 -> 3336.25 | L13: =IF(K$14,K13/K$14,0) -> 0.010043946 | N13: =VLOOKUP(A13,TB!TB1_1,5,FALSE)*-1 -> 3336.25 | O13: =IF(N$14,N13/N$14,0) -> 0.010043946
C14: Total Revenue | E14: =SUM(E7:E13) -> 534513.17 | F14: =IF(E$14,E14/E$14,0) -> 1 | H14: =SUM(H7:H13) -> 534513.17 | I14: =IF(H$14,H14/H$14,0) -> 1 | K14: =SUM(K7:K13) -> 332165.25 | L14: =IF(K$10,K14/K$10,0) -> 18.250838 | N14: =SUM(N7:N13) -> 332165.25 | O14: =IF(N$10,N14/N$10,0) -> 18.250838
A16: 5110501 | C16: Linde | E16: =VLOOKUP(A16,TB!TB,4,FALSE) -> 180524.11 | F16: =IF(E$14,E16/E$14,0) -> 0.33773557 | H16: =VLOOKUP(A16,TB!TB,5,FALSE) -> 180524.11 | I16: =IF(H$14,H16/H$14,0) -> 0.33773557 | K16: =VLOOKUP(A16,TB!TB1_1,4,FALSE) -> 64123.68 | L16: =IF(K$14,K16/K$14,0) -> 0.19304753 | N16: =VLOOKUP(A16,TB!TB1_1,5,FALSE) -> 64123.68 | O16: =IF(N$14,N16/N$14,0) -> 0.19304753
A17: 5113501 | C17: Combi | E17: =VLOOKUP(A17,TB!TB,4,FALSE) -> 180109.91 | F17: =IF(E$14,E17/E$14,0) -> 0.33696066 | H17: =VLOOKUP(A17,TB!TB,5,FALSE) -> 180109.91 | I17: =IF(H$14,H17/H$14,0) -> 0.33696066 | K17: =VLOOKUP(A17,TB!TB1_1,4,FALSE) -> 172669.05 | L17: =IF(K$14,K17/K$14,0) -> 0.51982876 | N17: =VLOOKUP(A17,TB!TB1_1,5,FALSE) -> 172669.05 | O17: =IF(N$14,N17/N$14,0) -> 0.51982876
A18: 5115501 | C18: New Equipment Other Canton | E18: =VLOOKUP(A18,TB!TB,4,FALSE) -> 29129 | F18: =IF(E$14,E18/E$14,0) -> 0.054496319 | H18: =VLOOKUP(A18,TB!TB,5,FALSE) -> 29129 | I18: =IF(H$14,H18/H$14,0) -> 0.054496319 | K18: =VLOOKUP(A18,TB!TB1_1,4,FALSE) -> 0 | L18: =IF(K$14,K18/K$14,0) -> 0 | N18: =VLOOKUP(A18,TB!TB1_1,5,FALSE) -> 0 | O18: =IF(N$14,N18/N$14,0) -> 0
A19: 5950501 | C19: Make Ready | E19: =VLOOKUP(A19,TB!TB,4,FALSE) -> 7920.08 | F19: =IF(E$14,E19/E$14,0) -> 0.014817371 | H19: =VLOOKUP(A19,TB!TB,5,FALSE) -> 7920.08 | I19: =IF(H$14,H19/H$14,0) -> 0.014817371 | K19: =VLOOKUP(A19,TB!TB1_1,4,FALSE) -> 5532.76 | L19: =IF(K$14,K19/K$14,0) -> 0.016656649 | N19: =VLOOKUP(A19,TB!TB1_1,5,FALSE) -> 5532.76 | O19: =IF(N$14,N19/N$14,0) -> 0.016656649
A20: 5956501 | C20: Demo | E20: =VLOOKUP(A20,TB!TB,4,FALSE) -> 0 | F20: =IF(E$14,E20/E$14,0) -> 0 | H20: =VLOOKUP(A20,TB!TB,5,FALSE) -> 0 | I20: =IF(H$14,H20/H$14,0) -> 0 | K20: =VLOOKUP(A20,TB!TB1_1,4,FALSE) -> 702 | L20: =IF(K$14,K20/K$14,0) -> 0.0021134059 | N20: =VLOOKUP(A20,TB!TB1_1,5,FALSE) -> 702 | O20: =IF(N$14,N20/N$14,0) -> 0.0021134059
A21: 5953501 | C21: P/L Sales Discount | E21: =VLOOKUP(A21,TB!TB,4,FALSE) -> 0 | F21: =IF(E$14,E21/E$14,0) -> 0 | H21: =VLOOKUP(A21,TB!TB,5,FALSE) -> 0 | I21: =IF(H$14,H21/H$14,0) -> 0 | K21: =VLOOKUP(A21,TB!TB1_1,4,FALSE) -> 0 | L21: =IF(K$14,K21/K$14,0) -> 0 | N21: =VLOOKUP(A21,TB!TB1_1,5,FALSE) -> 0 | O21: =IF(N$14,N21/N$14,0) -> 0
A22: 5152501 | C22: Internal Delivery | E22: =VLOOKUP(A22,TB!TB,4,FALSE) -> 0 | F22: =IF(E$14,E22/E$14,0) -> 0 | H22: =VLOOKUP(A22,TB!TB,5,FALSE) -> 0 | I22: =IF(H$14,H22/H$14,0) -> 0 | K22: =VLOOKUP(A22,TB!TB1_1,4,FALSE) -> 0 | L22: =IF(K$14,K22/K$14,0) -> 0 | N22: =VLOOKUP(A22,TB!TB1_1,5,FALSE) -> 0 | O22: =IF(N$14,N22/N$14,0) -> 0
A23: 5192501 | C23: Internal Rental | E23: =VLOOKUP(A23,TB!TB,4,FALSE) -> 0 | F23: =IF(E$14,E23/E$14,0) -> 0 | H23: =VLOOKUP(A23,TB!TB,5,FALSE) -> 0 | I23: =IF(H$14,H23/H$14,0) -> 0 | K23: =VLOOKUP(A23,TB!TB1_1,4,FALSE) -> 0 | L23: =IF(K$14,K23/K$14,0) -> 0 | N23: =VLOOKUP(A23,TB!TB1_1,5,FALSE) -> 0 | O23: =IF(N$14,N23/N$14,0) -> 0
A24: 5140501 | C24: Allied Lines | E24: =VLOOKUP(A24,TB!TB,4,FALSE) -> 33485.77 | F24: =IF(E$14,E24/E$14,0) -> 0.062647231 | H24: =VLOOKUP(A24,TB!TB,5,FALSE) -> 33485.77 | I24: =IF(H$14,H24/H$14,0) -> 0.062647231 | K24: =VLOOKUP(A24,TB!TB1_1,4,FALSE) -> 15191.5 | L24: =IF(K$14,K24/K$14,0) -> 0.045734766 | N24: =VLOOKUP(A24,TB!TB1_1,5,FALSE) -> 15191.5 | O24: =IF(N$14,N24/N$14,0) -> 0.045734766
A25: 6430501 | C25: Freight - Sales | E25: =VLOOKUP(A25,TB!TB,4,FALSE) -> 15044.6 | F25: =IF(E$14,E25/E$14,0) -> 0.02814636 | H25: =VLOOKUP(A25,TB!TB,5,FALSE) -> 15044.6 | I25: =IF(H$14,H25/H$14,0) -> 0.02814636 | K25: =VLOOKUP(A25,TB!TB1_1,4,FALSE) -> 1620.05 | L25: =IF(K$14,K25/K$14,0) -> 0.0048772411 | N25: =VLOOKUP(A25,TB!TB1_1,5,FALSE) -> 1620.05 | O25: =IF(N$14,N25/N$14,0) -> 0.0048772411
A26: 6430101 | C26: Freight - Demo | E26: =VLOOKUP(A26,TB!TB,4,FALSE) -> 0 | F26: =IF(E$14,E26/E$14,0) -> 0 | H26: =VLOOKUP(A26,TB!TB,5,FALSE) -> 0 | I26: =IF(H$14,H26/H$14,0) -> 0 | K26: 0 | L26: =IF(K$14,K26/K$14,0) -> 0 | N26: 0 | O26: =IF(N$14,N26/N$14,0) -> 0
A27: 6850501 | C27: Accum Depr Demo Trucks | E27: =VLOOKUP(A27,TB!TB,4,FALSE) -> 12406.39 | F27: =IF(E$14,E27/E$14,0) -> 0.023210635 | H27: =VLOOKUP(A27,TB!TB,5,FALSE) -> 12406.39 | I27: =IF(H$14,H27/H$14,0) -> 0.023210635 | K27: =VLOOKUP(A27,TB!TB1_1,4,FALSE) -> 15095.2 | L27: =IF(K$14,K27/K$14,0) -> 0.04544485 | N27: =VLOOKUP(A27,TB!TB1_1,5,FALSE) -> 15095.2 | O27: =IF(N$14,N27/N$14,0) -> 0.04544485
A28: 6880501 | C28: Depreciation Installment Fleet | E28: =VLOOKUP(A28,TB!TB,4,FALSE) -> 19951.97 | F28: =IF(E$14,E28/E$14,0) -> 0.037327368 | H28: =VLOOKUP(A28,TB!TB,5,FALSE) -> 19951.97 | I28: =IF(H$14,H28/H$14,0) -> 0.037327368 | K28: =VLOOKUP(A28,TB!TB1_1,4,FALSE) -> 32959.25 | L28: =IF(K$14,K28/K$14,0) -> 0.099225461 | N28: =VLOOKUP(A28,TB!TB1_1,5,FALSE) -> 32959.25 | O28: =IF(N$14,N28/N$14,0) -> 0.099225461
C29: Total Cost of Goods Sold | E29: =SUM(E16:E28) -> 478571.83 | F29: =IF(E$14,E29/E$14,0) -> 0.89534151 | H29: =SUM(H16:H28) -> 478571.83 | I29: =IF(H$14,H29/H$14,0) -> 0.89534151 | K29: =SUM(K16:K28) -> 307893.49 | L29: =IF(K$14,K29/K$14,0) -> 0.92692866 | N29: =SUM(N16:N28) -> 307893.49 | O29: =IF(N$14,N29/N$14,0) -> 0.92692866
C31: Gross Profit | E31: =E14-E29 -> 55941.34 | F31: =IF(E$14,E31/E$14,0) -> 0.10465849 | H31: =H14-H29 -> 55941.34 | I31: =IF(H$14,H31/H$14,0) -> 0.10465849 | K31: =K14-K29 -> 24271.76 | L31: =IF(K$14,K31/K$14,0) -> 0.07307134 | N31: =N14-N29 -> 24271.76 | O31: =IF(N$14,N31/N$14,0) -> 0.07307134
A33: 6010501 | C33: Supervisory | E33: =VLOOKUP(A33,TB!TB,4,FALSE) -> 0 | F33: =IF(E$14,E33/E$14,0) -> 0 | H33: =VLOOKUP(A33,TB!TB,5,FALSE) -> 0 | I33: =IF(H$14,H33/H$14,0) -> 0 | K33: =VLOOKUP(A33,TB!TB1_1,4,FALSE) -> 0 | L33: =IF(K$14,K33/K$14,0) -> 0 | N33: =VLOOKUP(A33,TB!TB1_1,5,FALSE) -> 0 | O33: =IF(N$14,N33/N$14,0) -> 0
A34: 6020501 | C34: Salesman Salaries | E34: =VLOOKUP(A34,TB!TB,4,FALSE) -> 58879.2 | F34: =IF(E$14,E34/E$14,0) -> 0.11015482 | H34: =VLOOKUP(A34,TB!TB,5,FALSE) -> 58879.2 | I34: =IF(H$14,H34/H$14,0) -> 0.11015482 | K34: =VLOOKUP(A34,TB!TB1_1,4,FALSE) -> 46104.61 | L34: =IF(K$14,K34/K$14,0) -> 0.13880022 | N34: =VLOOKUP(A34,TB!TB1_1,5,FALSE) -> 46104.61 | O34: =IF(N$14,N34/N$14,0) -> 0.13880022
A35: 6050501 | C35: Support Salaries | E35: =VLOOKUP(A35,TB!TB,4,FALSE) -> 0 | F35: =IF(E$14,E35/E$14,0) -> 0 | H35: =VLOOKUP(A35,TB!TB,5,FALSE) -> 0 | I35: =IF(H$14,H35/H$14,0) -> 0 | K35: =VLOOKUP(A35,TB!TB1_1,4,FALSE) -> 0 | L35: =IF(K$14,K35/K$14,0) -> 0 | N35: =VLOOKUP(A35,TB!TB1_1,5,FALSE) -> 0 | O35: =IF(N$14,N35/N$14,0) -> 0
A36: 6061001 | C36: Commission | E36: =VLOOKUP(A36,TB!TB,4,FALSE) -> 0 | F36: =IF(E$14,E36/E$14,0) -> 0 | H36: =VLOOKUP(A36,TB!TB,5,FALSE) -> 0 | I36: =IF(H$14,H36/H$14,0) -> 0 | K36: =VLOOKUP(A36,TB!TB1_1,4,FALSE) -> 7386.62 | L36: =IF(K$14,K36/K$14,0) -> 0.022237787 | N36: =VLOOKUP(A36,TB!TB1_1,5,FALSE) -> 7386.62 | O36: =IF(N$14,N36/N$14,0) -> 0.022237787
A37: 6112001 | C37: Accrued Commission Allied-Canton | E37: =VLOOKUP(A37,TB!TB,4,FALSE) -> 0 | F37: =IF(E$14,E37/E$14,0) -> 0 | H37: =VLOOKUP(A37,TB!TB,5,FALSE) -> 0 | I37: =IF(H$14,H37/H$14,0) -> 0 | K37: =VLOOKUP(A37,TB!TB1_1,4,FALSE) -> 19564.72 | L37: =IF(K$14,K37/K$14,0) -> 0.058900562 | N37: =VLOOKUP(A37,TB!TB1_1,5,FALSE) -> 19564.72 | O37: =IF(N$14,N37/N$14,0) -> 0.058900562
A38: 6111501 | C38: Accrued Commission New-Canton | E38: =VLOOKUP(A38,TB!TB,4,FALSE) -> 0 | F38: =IF(E$14,E38/E$14,0) -> 0 | H38: =VLOOKUP(A38,TB!TB,5,FALSE) -> 0 | I38: =IF(H$14,H38/H$14,0) -> 0 | K38: 0 | L38: =IF(K$14,K38/K$14,0) -> 0 | N38: 0 | O38: =IF(N$14,N38/N$14,0) -> 0
A39: 6070501 | C39: Payroll Taxes | E39: =VLOOKUP(A39,TB!TB,4,FALSE) -> 6020.88 | F39: =IF(E$14,E39/E$14,0) -> 0.011264231 | H39: =VLOOKUP(A39,TB!TB,5,FALSE) -> 6020.88 | I39: =IF(H$14,H39/H$14,0) -> 0.011264231 | K39: =VLOOKUP(A39,TB!TB1_1,4,FALSE) -> 5130.59 | L39: =IF(K$14,K39/K$14,0) -> 0.015445896 | N39: =VLOOKUP(A39,TB!TB1_1,5,FALSE) -> 5130.59 | O39: =IF(N$14,N39/N$14,0) -> 0.015445896
A40: 6530501 | C40: Employee Welfare | E40: =VLOOKUP(A40,TB!TB,4,FALSE) -> 867.33 | F40: =IF(E$14,E40/E$14,0) -> 0.0016226541 | H40: =VLOOKUP(A40,TB!TB,5,FALSE) -> 867.33 | I40: =IF(H$14,H40/H$14,0) -> 0.0016226541 | K40: =VLOOKUP(A40,TB!TB1_1,4,FALSE) -> 2658.83 | L40: =IF(K$14,K40/K$14,0) -> 0.0080045399 | N40: =VLOOKUP(A40,TB!TB1_1,5,FALSE) -> 2658.83 | O40: =IF(N$14,N40/N$14,0) -> 0.0080045399
A41: 6540501 | C41: 401K Contribution | E41: =VLOOKUP(A41,TB!TB,4,FALSE) -> 818.76 | F41: =IF(E$14,E41/E$14,0) -> 0.0015317864 | H41: =VLOOKUP(A41,TB!TB,5,FALSE) -> 818.76 | I41: =IF(H$14,H41/H$14,0) -> 0.0015317864 | K41: =VLOOKUP(A41,TB!TB1_1,4,FALSE) -> 749.55 | L41: =IF(K$14,K41/K$14,0) -> 0.0022565575 | N41: =VLOOKUP(A41,TB!TB1_1,5,FALSE) -> 749.55 | O41: =IF(N$14,N41/N$14,0) -> 0.0022565575
A42: 6100501 | C42: Employee Exp-100% | E42: =VLOOKUP(A42,TB!TB,4,FALSE) -> 2278.13 | F42: =IF(E$14,E42/E$14,0) -> 0.0042620652 | H42: =VLOOKUP(A42,TB!TB,5,FALSE) -> 2278.13 | I42: =IF(H$14,H42/H$14,0) -> 0.0042620652 | K42: =VLOOKUP(A42,TB!TB1_1,4,FALSE) -> 0 | L42: =IF(K$14,K42/K$14,0) -> 0 | N42: =VLOOKUP(A42,TB!TB1_1,5,FALSE) -> 0 | O42: =IF(N$14,N42/N$14,0) -> 0
A43: 6110501 | C43: Employee Exp-50% | E43: =VLOOKUP(A43,TB!TB,4,FALSE) -> 783.91 | F43: =IF(E$14,E43/E$14,0) -> 0.0014665869 | H43: =VLOOKUP(A43,TB!TB,5,FALSE) -> 783.91 | I43: =IF(H$14,H43/H$14,0) -> 0.0014665869 | K43: =VLOOKUP(A43,TB!TB1_1,4,FALSE) -> 893.65 | L43: =IF(K$14,K43/K$14,0) -> 0.0026903778 | N43: =VLOOKUP(A43,TB!TB1_1,5,FALSE) -> 893.65 | O43: =IF(N$14,N43/N$14,0) -> 0.0026903778
A44: 6210501 | C44: Vehicle Repair & Maint | E44: =VLOOKUP(A44,TB!TB,4,FALSE) -> 6921.88 | F44: =IF(E$14,E44/E$14,0) -> 0.012949877 | H44: =VLOOKUP(A44,TB!TB,5,FALSE) -> 6921.88 | I44: =IF(H$14,H44/H$14,0) -> 0.012949877 | K44: =VLOOKUP(A44,TB!TB1_1,4,FALSE) -> 3686.79 | L44: =IF(K$14,K44/K$14,0) -> 0.011099265 | N44: =VLOOKUP(A44,TB!TB1_1,5,FALSE) -> 3686.79 | O44: =IF(N$14,N44/N$14,0) -> 0.011099265
A45: 6310501 | C45: Rent Canton | E45: =VLOOKUP(A45,TB!TB,4,FALSE) -> 1840 | F45: =IF(E$14,E45/E$14,0) -> 0.0034423848 | H45: =VLOOKUP(A45,TB!TB,5,FALSE) -> 1840 | I45: =IF(H$14,H45/H$14,0) -> 0.0034423848 | K45: =VLOOKUP(A45,TB!TB1_1,4,FALSE) -> 562.5 | L45: =IF(K$14,K45/K$14,0) -> 0.0016934342 | N45: =VLOOKUP(A45,TB!TB1_1,5,FALSE) -> 562.5 | O45: =IF(N$14,N45/N$14,0) -> 0.0016934342
A46: 6410501 | C46: Office Supplies | E46: =VLOOKUP(A46,TB!TB,4,FALSE) -> 456.25 | F46: =IF(E$14,E46/E$14,0) -> 0.00085358046 | H46: =VLOOKUP(A46,TB!TB,5,FALSE) -> 456.25 | I46: =IF(H$14,H46/H$14,0) -> 0.00085358046 | K46: =VLOOKUP(A46,TB!TB1_1,4,FALSE) -> 279.05 | L46: =IF(K$14,K46/K$14,0) -> 0.0008400939 | N46: =VLOOKUP(A46,TB!TB1_1,5,FALSE) -> 279.05 | O46: =IF(N$14,N46/N$14,0) -> 0.0008400939
A47: 6440501 | C47: Communication Expense | E47: =VLOOKUP(A47,TB!TB,4,FALSE) -> 436.36 | F47: =IF(E$14,E47/E$14,0) -> 0.00081636903 | H47: =VLOOKUP(A47,TB!TB,5,FALSE) -> 436.36 | I47: =IF(H$14,H47/H$14,0) -> 0.00081636903 | K47: =VLOOKUP(A47,TB!TB1_1,4,FALSE) -> 630.94 | L47: =IF(K$14,K47/K$14,0) -> 0.0018994762 | N47: =VLOOKUP(A47,TB!TB1_1,5,FALSE) -> 630.94 | O47: =IF(N$14,N47/N$14,0) -> 0.0018994762
A48: 6460501 | C48: Dues & Subscriptions | E48: =VLOOKUP(A48,TB!TB,4,FALSE) -> 11912.05 | F48: =IF(E$14,E48/E$14,0) -> 0.022285793 | H48: =VLOOKUP(A48,TB!TB,5,FALSE) -> 11912.05 | I48: =IF(H$14,H48/H$14,0) -> 0.022285793 | K48: =VLOOKUP(A48,TB!TB1_1,4,FALSE) -> 2200 | L48: =IF(K$14,K48/K$14,0) -> 0.0066232094 | N48: =VLOOKUP(A48,TB!TB1_1,5,FALSE) -> 2200 | O48: =IF(N$14,N48/N$14,0) -> 0.0066232094
A49: 6470501 | C49: Promotion | E49: =VLOOKUP(A49,TB!TB,4,FALSE) -> 4110.35 | F49: =IF(E$14,E49/E$14,0) -> 0.0076898947 | H49: =VLOOKUP(A49,TB!TB,5,FALSE) -> 4110.35 | I49: =IF(H$14,H49/H$14,0) -> 0.0076898947 | K49: =VLOOKUP(A49,TB!TB1_1,4,FALSE) -> 59.95 | L49: =IF(K$14,K49/K$14,0) -> 0.00018048246 | N49: =VLOOKUP(A49,TB!TB1_1,5,FALSE) -> 59.95 | O49: =IF(N$14,N49/N$14,0) -> 0.00018048246
A50: 6480501 | C50: Training & Education | E50: =VLOOKUP(A50,TB!TB,4,FALSE) -> 0 | F50: =IF(E$14,E50/E$14,0) -> 0 | H50: =VLOOKUP(A50,TB!TB,5,FALSE) -> 0 | I50: =IF(H$14,H50/H$14,0) -> 0 | K50: =VLOOKUP(A50,TB!TB1_1,4,FALSE) -> 0 | L50: =IF(K$14,K50/K$14,0) -> 0 | N50: =VLOOKUP(A50,TB!TB1_1,5,FALSE) -> 0 | O50: =IF(N$14,N50/N$14,0) -> 0
... A55: 6910501 | C55: Tariff Expenses | E55: =VLOOKUP(A55,TB!TB,4,FALSE) -> -24385.81 | F55: =IF(E$14,E55/E$14,0) -> -0.045622468 | H55: =VLOOKUP(A55,TB!TB,5,FALSE) -> -24385.81 | I55: =IF(H$14,H55/H$14,0) -> -0.045622468 | K55: =VLOOKUP(A55,TB!TB1_1,4,FALSE) -> 0 | L55: =IF(K$14,K55/K$14,0) -> 0 | N55: =VLOOKUP(A55,TB!TB1_1,5,FALSE) -> 0 | O55: =IF(N$14,N55/N$14,0) -> 0
C56: Total Expenses | E56: =SUM(E33:E55) -> 71330.27 | F56: =IF(E$14,E56/E$14,0) -> 0.13344904 | H56: =SUM(H33:H55) -> 71330.27 | I56: =IF(H$14,H56/H$14,0) -> 0.13344904 | K56: =SUM(K33:K55) -> 91058.91 | L56: =IF(K$14,K56/K$14,0) -> 0.27413738 | N56: =SUM(N33:N55) -> 91058.91 | O56: =IF(N$14,N56/N$14,0) -> 0.27413738
C58: Net Income | E58: =E31-E56 -> -15388.93 | F58: =IF(E$14,E58/E$14,0) -> -0.028790553 | H58: =H31-H56 -> -15388.93 | I58: =IF(H$14,H58/H$14,0) -> -0.028790553 | K58: =K31-K56 -> -66787.15 | L58: =IF(K$14,K58/K$14,0) -> -0.20106604 | N58: =N31-N56 -> -66787.15 | O58: =IF(N$14,N58/N$14,0) -> -0.20106604
A59: 6980501 | C59: G & A Allocation | E59: =VLOOKUP(A59,TB!TB,4,FALSE) -> 0 | F59: =IF(E$14,E59/E$14,0) -> 0 | H59: =VLOOKUP(A59,TB!TB,5,FALSE) -> 0 | I59: =IF(H$14,H59/H$14,0) -> 0 | K59: =VLOOKUP(A59,TB!TB1_1,4,FALSE) -> 16462.12 | L59: =IF(K$14,K59/K$14,0) -> 0.049560031 | N59: =VLOOKUP(A59,TB!TB1_1,5,FALSE)*-1 -> -16462.12 | O59: =IF(N$14,N59/N$14,0) -> -0.049560031
C61: Income After Allocation | E61: =E58-E59 -> -15388.93 | F61: =IF(E$14,E61/E$14,0) -> -0.028790553 | H61: =H58-H59 -> -15388.93 | I61: =IF(H$14,H61/H$14,0) -> -0.028790553 | K61: =K58-K59 -> -83249.27 | L61: =IF(K$14,K61/K$14,0) -> -0.25062607 | N61: =N58-N59 -> -50325.03 | O61: =IF(N$14,N61/N$14,0) -> -0.151506

Sheet Canton Parts Department
A1: Industrial Parts and Service Company
A2: Canton Parts Department Financial
A3: =DATEVALUE(TB!A3&"/"&TB!A4) -> 46023
C4: Description | E4: YTD | H4: MTD | K4: YTD | N4: MTD
A5: Account # | C5: Revenue | E5: =TB!A4 -> 2026 | F5: % of Sales | H5: =TB!A4 -> 2026 | I5: % of Sales | K5: =TB!O4 -> 2025 | L5: % of Sales | N5: =TB!O4 -> 2025 | O5: % of Sales
A7: 4125601 | C7: Linde Parts Sales | E7: =VLOOKUP(A7,TB!TB,4,FALSE)*-1 -> 132129.07 | F7: =IF(E$32,E7/E$32,0) -> 0.37029116 | H7: =VLOOKUP(A7,TB!TB,5,FALSE)*-1 -> 132129.07 | I7: =IF(H$32,H7/H$32,0) -> 0.37029116 | K7: =VLOOKUP(A7,TB!TB1_1,4,FALSE)*-1 -> 136717.11 | L7: =IF(K$32,K7/K$32,0) -> 0.38023551 | N7: =VLOOKUP(A7,TB!TB1_1,5,FALSE)*-1 -> 136717.11 | O7: =IF(N$32,N7/N$32,0) -> 0.38023551
A8: 4126601 | C8: Combi Parts Sales | E8: =VLOOKUP(A8,TB!TB,4,FALSE)*-1 -> 47878.25 | F8: =IF(E$32,E8/E$32,0) -> 0.13417859 | H8: =VLOOKUP(A8,TB!TB,5,FALSE)*-1 -> 47878.25 | I8: =IF(H$32,H8/H$32,0) -> 0.13417859 | K8: =VLOOKUP(A8,TB!TB1_1,4,FALSE)*-1 -> 51636.03 | L8: =IF(K$32,K8/K$32,0) -> 0.14360933 | N8: =VLOOKUP(A8,TB!TB1_1,5,FALSE)*-1 -> 51636.03 | O8: =IF(N$32,N8/N$32,0) -> 0.14360933
A9: 4127601 | C9: Tire Sales | E9: =VLOOKUP(A9,TB!TB,4,FALSE)*-1 -> 0 | F9: =IF(E$32,E9/E$32,0) -> 0 | H9: =VLOOKUP(A9,TB!TB,5,FALSE)*-1 -> 0 | I9: =IF(H$32,H9/H$32,0) -> 0 | K9: =VLOOKUP(A9,TB!TB1_1,4,FALSE)*-1 -> 1272.33 | L9: =IF(K$32,K9/K$32,0) -> 0.0035385845 | N9: =VLOOKUP(A9,TB!TB1_1,5,FALSE)*-1 -> 1272.33 | O9: =IF(N$32,N9/N$32,0) -> 0.0035385845
A10: 4129601 | C10: Parts Sales Other | E10: =VLOOKUP(A10,TB!TB,4,FALSE)*-1 -> 42014.11 | F10: =IF(E$32,E10/E$32,0) -> 0.11774437 | H10: =VLOOKUP(A10,TB!TB,5,FALSE)*-1 -> 42014.11 | I10: =IF(H$32,H10/H$32,0) -> 0.11774437 | K10: =VLOOKUP(A10,TB!TB1_1,4,FALSE)*-1 -> 52716.39 | L10: =IF(K$32,K10/K$32,0) -> 0.14661401 | N10: =VLOOKUP(A10,TB!TB1_1,5,FALSE)*-1 -> 52716.39 | O10: =IF(N$32,N10/N$32,0) -> 0.14661401
A11: 4146601 | C11: TVH Parts Sales | E11: =VLOOKUP(A11,TB!TB,4,FALSE)*-1 -> 2046.32 | F11: =IF(E$32,E11/E$32,0) -> 0.0057348032 | H11: =VLOOKUP(A11,TB!TB,5,FALSE)*-1 -> 2046.32 | I11: =IF(H$32,H11/H$32,0) -> 0.0057348032 | K11: 0 | L11: =IF(K$32,K11/K$32,0) -> 0 | N11: 0 | O11: =IF(N$32,N11/N$32,0) -> 0
A12: 4130601 | C12: Shop Parts- Linde | E12: =VLOOKUP(A12,TB!TB,4,FALSE)*-1 -> 13032.79 | F12: =IF(E$32,E12/E$32,0) -> 0.036524339 | H12: =VLOOKUP(A12,TB!TB,5,FALSE)*-1 -> 13032.79 | I12: =IF(H$32,H12/H$32,0) -> 0.036524339 | K12: =VLOOKUP(A12,TB!TB1_1,4,FALSE)*-1 -> 5050.8 | L12: =IF(K$32,K12/K$32,0) -> 0.014047207 | N12: =VLOOKUP(A12,TB!TB1_1,5,FALSE)*-1 -> 5050.8 | O12: =IF(N$32,N12/N$32,0) -> 0.014047207
A13: 4131601 | C13: Shop Parts-Combi | E13: =VLOOKUP(A13,TB!TB,4,FALSE)*-1 -> 1044.46 | F13: =IF(E$32,E13/E$32,0) -> 0.0029270948 | H13: =VLOOKUP(A13,TB!TB,5,FALSE)*-1 -> 1044.46 | I13: =IF(H$32,H13/H$32,0) -> 0.0029270948 | K13: =VLOOKUP(A13,TB!TB1_1,4,FALSE)*-1 -> -360.16 | L13: =IF(K$32,K13/K$32,0) -> -0.0010016714 | N13: =VLOOKUP(A13,TB!TB1_1,5,FALSE)*-1 -> -360.16 | O13: =IF(N$32,N13/N$32,0) -> -0.0010016714
A14: 4141601 | C14: Shop Parts-TVH | E14: =VLOOKUP(A14,TB!TB,4,FALSE)*-1 -> 357.17 | F14: =IF(E$32,E14/E$32,0) -> 0.0010009674 | H14: =VLOOKUP(A14,TB!TB,5,FALSE)*-1 -> 357.17 | I14: =IF(H$32,H14/H$32,0) -> 0.0010009674 | K14: 0 | L14: =IF(K$32,K14/K$32,0) -> 0 | N14: 0 | O14: =IF(N$32,N14/N$32,0) -> 0
A15: 4132601 | C15: Shop Parts-Other | E15: =VLOOKUP(A15,TB!TB,4,FALSE)*-1 -> 9825.13 | F15: =IF(E$32,E15/E$32,0) -> 0.027534885 | H15: =VLOOKUP(A15,TB!TB,5,FALSE)*-1 -> 9825.13 | I15: =IF(H$32,H15/H$32,0) -> 0.027534885 | K15: =VLOOKUP(A15,TB!TB1_1,4,FALSE)*-1 -> 17214.34 | L15: =IF(K$32,K15/K$32,0) -> 0.047876256 | N15: =VLOOKUP(A15,TB!TB1_1,5,FALSE)*-1 -> 17214.34 | O15: =IF(N$32,N15/N$32,0) -> 0.047876256
A16: 4133601 | C16: Road Parts-Linde | E16: =VLOOKUP(A16,TB!TB,4,FALSE)*-1 -> 26290.97 | F16: =IF(E$32,E16/E$32,0) -> 0.073680333 | H16: =VLOOKUP(A16,TB!TB,5,FALSE)*-1 -> 26290.97 | I16: =IF(H$32,H16/H$32,0) -> 0.073680333 | K16: =VLOOKUP(A16,TB!TB1_1,4,FALSE)*-1 -> 31657.28 | L16: =IF(K$32,K16/K$32,0) -> 0.088044736 | N16: =VLOOKUP(A16,TB!TB1_1,5,FALSE)*-1 -> 31657.28 | O16: =IF(N$32,N16/N$32,0) -> 0.088044736
A17: 4134601 | C17: Road Parts-Combi | E17: =VLOOKUP(A17,TB!TB,4,FALSE)*-1 -> 17981.82 | F17: =IF(E$32,E17/E$32,0) -> 0.050393975 | H17: =VLOOKUP(A17,TB!TB,5,FALSE)*-1 -> 17981.82 | I17: =IF(H$32,H17/H$32,0) -> 0.050393975 | K17: =VLOOKUP(A17,TB!TB1_1,4,FALSE)*-1 -> 13408.77 | L17: =IF(K$32,K17/K$32,0) -> 0.037292263 | N17: =VLOOKUP(A17,TB!TB1_1,5,FALSE)*-1 -> 13408.77 | O17: =IF(N$32,N17/N$32,0) -> 0.037292263
A18: 4144601 | C18: Road Parts-TVH | E18: =VLOOKUP(A18,TB!TB,4,FALSE)*-1 -> 565.2 | F18: =IF(E$32,E18/E$32,0) -> 0.0015839706 | H18: =VLOOKUP(A18,TB!TB,5,FALSE)*-1 -> 565.2 | I18: =IF(H$32,H18/H$32,0) -> 0.0015839706 | K18: 0 | L18: =IF(K$32,K18/K$32,0) -> 0 | N18: 0 | O18: =IF(N$32,N18/N$32,0) -> 0
A19: 4135601 | C19: Road Parts-Other | E19: =VLOOKUP(A19,TB!TB,4,FALSE)*-1 -> 40289.65 | F19: =IF(E$32,E19/E$32,0) -> 0.11291157 | H19: =VLOOKUP(A19,TB!TB,5,FALSE)*-1 -> 40289.65 | I19: =IF(H$32,H19/H$32,0) -> 0.11291157 | K19: =VLOOKUP(A19,TB!TB1_1,4,FALSE)*-1 -> 31584.85 | L19: =IF(K$32,K19/K$32,0) -> 0.087843295 | N19: =VLOOKUP(A19,TB!TB1_1,5,FALSE)*-1 -> 31584.85 | O19: =IF(N$32,N19/N$32,0) -> 0.087843295
A20: 4136601 | C20: P M -Linde Parts | E20: =VLOOKUP(A20,TB!TB,4,FALSE)*-1 -> 14301.48 | F20: =IF(E$32,E20/E$32,0) -> 0.040079838 | H20: =VLOOKUP(A20,TB!TB,5,FALSE)*-1 -> 14301.48 | I20: =IF(H$32,H20/H$32,0) -> 0.040079838 | K20: =VLOOKUP(A20,TB!TB1_1,4,FALSE)*-1 -> 6354.38 | L20: =IF(K$32,K20/K$32,0) -> 0.017672703 | N20: =VLOOKUP(A20,TB!TB1_1,5,FALSE)*-1 -> 6354.38 | O20: =IF(N$32,N20/N$32,0) -> 0.017672703
A21: 4137601 | C21: P M -Combi Parts | E21: =VLOOKUP(A21,TB!TB,4,FALSE)*-1 -> 0 | F21: =IF(E$32,E21/E$32,0) -> 0 | H21: =VLOOKUP(A21,TB!TB,5,FALSE)*-1 -> 0 | I21: =IF(H$32,H21/H$32,0) -> 0 | K21: =VLOOKUP(A21,TB!TB1_1,4,FALSE)*-1 -> 0 | L21: =IF(K$32,K21/K$32,0) -> 0 | N21: =VLOOKUP(A21,TB!TB1_1,5,FALSE)*-1 -> 0 | O21: =IF(N$32,N21/N$32,0) -> 0
A22: 4147601 | C22: P M -TVH Parts | E22: =VLOOKUP(A22,TB!TB,4,FALSE)*-1 -> 333.74 | F22: =IF(E$32,E22/E$32,0) -> 0.00093530495 | H22: =VLOOKUP(A22,TB!TB,5,FALSE)*-1 -> 333.74 | I22: =IF(H$32,H22/H$32,0) -> 0.00093530495 | K22: 0 | L22: =IF(K$32,K22/K$32,0) -> 0 | N22: 0 | O22: =IF(N$32,N22/N$32,0) -> 0
A23: 4138601 | C23: P M - Other Parts | E23: =VLOOKUP(A23,TB!TB,4,FALSE)*-1 -> 2128.79 | F23: =IF(E$32,E23/E$32,0) -> 0.005965925 | H23: =VLOOKUP(A23,TB!TB,5,FALSE)*-1 -> 2128.79 | I23: =IF(H$32,H23/H$32,0) -> 0.005965925 | K23: =VLOOKUP(A23,TB!TB1_1,4,FALSE)*-1 -> 1324.71 | L23: =IF(K$32,K23/K$32,0) -> 0.0036842629 | N23: =VLOOKUP(A23,TB!TB1_1,5,FALSE)*-1 -> 1324.71 | O23: =IF(N$32,N23/N$32,0) -> 0.0036842629
A24: 4300601 | C24: Internal Parts Sales-Serv | E24: =VLOOKUP(A24,TB!TB,4,FALSE)*-1 -> 0 | F24: =IF(E$32,E24/E$32,0) -> 0 | H24: =VLOOKUP(A24,TB!TB,5,FALSE)*-1 -> 0 | I24: =IF(H$32,H24/H$32,0) -> 0 | K24: =VLOOKUP(A24,TB!TB1_1,4,FALSE)*-1 -> 0 | L24: =IF(K$32,K24/K$32,0) -> 0 | N24: =VLOOKUP(A24,TB!TB1_1,5,FALSE)*-1 -> 0 | O24: =IF(N$32,N24/N$32,0) -> 0
A25: 4306201 | C25: Parts Sales to Alside | E25: =VLOOKUP(A25,TB!TB,4,FALSE)*-1 -> 0 | F25: =IF(E$32,E25/E$32,0) -> 0 | H25: =VLOOKUP(A25,TB!TB,5,FALSE)*-1 -> 0 | I25: =IF(H$32,H25/H$32,0) -> 0 | K25: =VLOOKUP(A25,TB!TB1_1,4,FALSE)*-1 -> 0 | L25: =IF(K$32,K25/K$32,0) -> 0 | N25: =VLOOKUP(A25,TB!TB1_1,5,FALSE)*-1 -> 0 | O25: =IF(N$32,N25/N$32,0) -> 0
A26: 4306401 | C26: Parts Sales to Used | E26: =VLOOKUP(A26,TB!TB,4,FALSE)*-1 -> 0 | F26: =IF(E$32,E26/E$32,0) -> 0 | H26: =VLOOKUP(A26,TB!TB,5,FALSE)*-1 -> 0 | I26: =IF(H$32,H26/H$32,0) -> 0 | K26: =VLOOKUP(A26,TB!TB1_1,4,FALSE)*-1 -> 0 | L26: =IF(K$32,K26/K$32,0) -> 0 | N26: =VLOOKUP(A26,TB!TB1_1,5,FALSE)*-1 -> 0 | O26: =IF(N$32,N26/N$32,0) -> 0
A27: 4306501 | C27: Parts Sales to Sales | E27: =VLOOKUP(A27,TB!TB,4,FALSE)*-1 -> 0 | F27: =IF(E$32,E27/E$32,0) -> 0 | H27: =VLOOKUP(A27,TB!TB,5,FALSE)*-1 -> 0 | I27: =IF(H$32,H27/H$32,0) -> 0 | K27: =VLOOKUP(A27,TB!TB1_1,4,FALSE)*-1 -> 0 | L27: =IF(K$32,K27/K$32,0) -> 0 | N27: =VLOOKUP(A27,TB!TB1_1,5,FALSE)*-1 -> 0 | O27: =IF(N$32,N27/N$32,0) -> 0
A28: 4306701 | C28: Parts Sales to Service | E28: =VLOOKUP(A28,TB!TB,4,FALSE)*-1 -> 0 | F28: =IF(E$32,E28/E$32,0) -> 0 | H28: =VLOOKUP(A28,TB!TB,5,FALSE)*-1 -> 0 | I28: =IF(H$32,H28/H$32,0) -> 0 | K28: =VLOOKUP(A28,TB!TB1_1,4,FALSE)*-1 -> 0 | L28: =IF(K$32,K28/K$32,0) -> 0 | N28: =VLOOKUP(A28,TB!TB1_1,5,FALSE)*-1 -> 0 | O28: =IF(N$32,N28/N$32,0) -> 0
A29: 4306901 | C29: Parts Sales to Rental | E29: =VLOOKUP(A29,TB!TB,4,FALSE)*-1 -> 0 | F29: =IF(E$32,E29/E$32,0) -> 0 | H29: =VLOOKUP(A29,TB!TB,5,FALSE)*-1 -> 0 | I29: =IF(H$32,H29/H$32,0) -> 0 | K29: =VLOOKUP(A29,TB!TB1_1,4,FALSE)*-1 -> 0 | L29: =IF(K$32,K29/K$32,0) -> 0 | N29: =VLOOKUP(A29,TB!TB1_1,5,FALSE)*-1 -> 0 | O29: =IF(N$32,N29/N$32,0) -> 0
A30: 4306601 | C30: Parts Sales to Parts | E30: =VLOOKUP(A30,TB!TB,4,FALSE)*-1 -> -1372 | F30: =IF(E$32,E30/E$32,0) -> -0.0038450242 | H30: =VLOOKUP(A30,TB!TB,5,FALSE)*-1 -> -1372 | I30: =IF(H$32,H30/H$32,0) -> -0.0038450242 | K30: =VLOOKUP(A30,TB!TB1_1,4,FALSE)*-1 -> 428.01 | L30: =IF(K$32,K30/K$32,0) -> 0.0011903748 | N30: =VLOOKUP(A30,TB!TB1_1,5,FALSE)*-1 -> 428.01 | O30: =IF(N$32,N30/N$32,0) -> 0.0011903748
A31: 4128601 | C31: Freight Income | E31: =VLOOKUP(A31,TB!TB,4,FALSE)*-1 -> 7977.85 | F31: =IF(E$32,E31/E$32,0) -> 0.022357891 | H31: =VLOOKUP(A31,TB!TB,5,FALSE)*-1 -> 7977.85 | I31: =IF(H$32,H31/H$32,0) -> 0.022357891 | K31: =VLOOKUP(A31,TB!TB1_1,4,FALSE)*-1 -> 10554.19 | L31: =IF(K$32,K31/K$32,0) -> 0.02935315 | N31: =VLOOKUP(A31,TB!TB1_1,5,FALSE)*-1 -> 10554.19 | O31: =IF(N$32,N31/N$32,0) -> 0.02935315
C32: Total Revenue | E32: =SUM(E7:E31) -> 356824.8 | F32: =IF(E$32,E32/E$32,0) -> 1 | H32: =SUM(H7:H31) -> 356824.8 | I32: =IF(H$32,H32/H$32,0) -> 1 | K32: =SUM(K7:K31) -> 359559.03 | L32: =IF(K$32,K32/K$32,0) -> 1 | N32: =SUM(N7:N31) -> 359559.03 | O32: =IF(N$32,N32/N$32,0) -> 1
A34: 5125601 | C34: Linde Parts | E34: =VLOOKUP(A34,TB!TB,4,FALSE) -> 81638.13 | F34: =IF(E$32,E34/E$32,0) -> 0.22879052 | H34: =VLOOKUP(A34,TB!TB,5,FALSE) -> 81638.13 | I34: =IF(H$32,H34/H$32,0) -> 0.22879052 | K34: =VLOOKUP(A34,TB!TB1_1,4,FALSE) -> 84969.87 | L34: =IF(K$32,K34/K$32,0) -> 0.23631689 | N34: =VLOOKUP(A34,TB!TB1_1,5,FALSE) -> 84969.87 | O34: =IF(N$32,N34/N$32,0) -> 0.23631689
A35: 5126601 | C35: Combi Parts | E35: =VLOOKUP(A35,TB!TB,4,FALSE) -> 28710.34 | F35: =IF(E$32,E35/E$32,0) -> 0.080460607 | H35: =VLOOKUP(A35,TB!TB,5,FALSE) -> 28710.34 | I35: =IF(H$32,H35/H$32,0) -> 0.080460607 | K35: =VLOOKUP(A35,TB!TB1_1,4,FALSE) -> 32756.66 | L35: =IF(K$32,K35/K$32,0) -> 0.091102315 | N35: =VLOOKUP(A35,TB!TB1_1,5,FALSE) -> 32756.66 | O35: =IF(N$32,N35/N$32,0) -> 0.091102315
A36: 5127601 | C36: Tires | E36: =VLOOKUP(A36,TB!TB,4,FALSE) -> 0 | F36: =IF(E$32,E36/E$32,0) -> 0 | H36: =VLOOKUP(A36,TB!TB,5,FALSE) -> 0 | I36: =IF(H$32,H36/H$32,0) -> 0 | K36: =VLOOKUP(A36,TB!TB1_1,4,FALSE) -> 787.62 | L36: =IF(K$32,K36/K$32,0) -> 0.0021905165 | N36: =VLOOKUP(A36,TB!TB1_1,5,FALSE) -> 787.62 | O36: =IF(N$32,N36/N$32,0) -> 0.0021905165
A37: 5146601 | C37: TVH Parts | E37: =VLOOKUP(A37,TB!TB,4,FALSE) -> 1197.72 | F37: =IF(E$32,E37/E$32,0) -> 0.0033566053 | H37: =VLOOKUP(A37,TB!TB,5,FALSE) -> 1197.72 | I37: =IF(H$32,H37/H$32,0) -> 0.0033566053 | K37: 0 | L37: =IF(K$32,K37/K$32,0) -> 0 | N37: 0 | O37: =IF(N$32,N37/N$32,0) -> 0
A38: 5129601 | C38: Parts Other | E38: =VLOOKUP(A38,TB!TB,4,FALSE) -> 27131.37 | F38: =IF(E$32,E38/E$32,0) -> 0.07603555 | H38: =VLOOKUP(A38,TB!TB,5,FALSE) -> 27131.37 | I38: =IF(H$32,H38/H$32,0) -> 0.07603555 | K38: =VLOOKUP(A38,TB!TB1_1,4,FALSE) -> 36308.55 | L38: =IF(K$32,K38/K$32,0) -> 0.10098078 | N38: =VLOOKUP(A38,TB!TB1_1,5,FALSE) -> 36308.55 | O38: =IF(N$32,N38/N$32,0) -> 0.10098078
A39: 5130601 | C39: Shop Parts-Linde | E39: =VLOOKUP(A39,TB!TB,4,FALSE) -> 8330.02 | F39: =IF(E$32,E39/E$32,0) -> 0.023344846 | H39: =VLOOKUP(A39,TB!TB,5,FALSE) -> 8330.02 | I39: =IF(H$32,H39/H$32,0) -> 0.023344846 | K39: =VLOOKUP(A39,TB!TB1_1,4,FALSE) -> 3096.43 | L39: =IF(K$32,K39/K$32,0) -> 0.0086117431 | N39: =VLOOKUP(A39,TB!TB1_1,5,FALSE) -> 3096.43 | O39: =IF(N$32,N39/N$32,0) -> 0.0086117431
A40: 5131601 | C40: Shop Parts-Combi | E40: =VLOOKUP(A40,TB!TB,4,FALSE) -> 627.49 | F40: =IF(E$32,E40/E$32,0) -> 0.0017585381 | H40: =VLOOKUP(A40,TB!TB,5,FALSE) -> 627.49 | I40: =IF(H$32,H40/H$32,0) -> 0.0017585381 | K40: =VLOOKUP(A40,TB!TB1_1,4,FALSE) -> -98.57 | L40: =IF(K$32,K40/K$32,0) -> -0.00027414136 | N40: =VLOOKUP(A40,TB!TB1_1,5,FALSE) -> -98.57 | O40: =IF(N$32,N40/N$32,0) -> -0.00027414136
A41: 5141601 | C41: Shop Parts-TVH | E41: =VLOOKUP(A41,TB!TB,4,FALSE) -> 211.65 | F41: =IF(E$32,E41/E$32,0) -> 0.00059314823 | H41: =VLOOKUP(A41,TB!TB,5,FALSE) -> 211.65 | I41: =IF(H$32,H41/H$32,0) -> 0.00059314823 | K41: 0 | L41: =IF(K$32,K41/K$32,0) -> 0 | N41: 0 | O41: =IF(N$32,N41/N$32,0) -> 0
A42: 5132601 | C42: Shop Parts -Other | E42: =VLOOKUP(A42,TB!TB,4,FALSE) -> 7473.65 | F42: =IF(E$32,E42/E$32,0) -> 0.020944873 | H42: =VLOOKUP(A42,TB!TB,5,FALSE) -> 7473.65 | I42: =IF(H$32,H42/H$32,0) -> 0.020944873 | K42: =VLOOKUP(A42,TB!TB1_1,4,FALSE) -> 15327.18 | L42: =IF(K$32,K42/K$32,0) -> 0.042627715 | N42: =VLOOKUP(A42,TB!TB1_1,5,FALSE) -> 15327.18 | O42: =IF(N$32,N42/N$32,0) -> 0.042627715
A43: 5133601 | C43: Road Parts-Linde | E43: =VLOOKUP(A43,TB!TB,4,FALSE) -> 16905.69 | F43: =IF(E$32,E43/E$32,0) -> 0.047378125 | H43: =VLOOKUP(A43,TB!TB,5,FALSE) -> 16905.69 | I43: =IF(H$32,H43/H$32,0) -> 0.047378125 | K43: =VLOOKUP(A43,TB!TB1_1,4,FALSE) -> 20769.97 | L43: =IF(K$32,K43/K$32,0) -> 0.057765119 | N43: =VLOOKUP(A43,TB!TB1_1,5,FALSE) -> 20769.97 | O43: =IF(N$32,N43/N$32,0) -> 0.057765119
A44: 5134601 | C44: Road Parts-Combi | E44: =VLOOKUP(A44,TB!TB,4,FALSE) -> 10876.04 | F44: =IF(E$32,E44/E$32,0) -> 0.030480056 | H44: =VLOOKUP(A44,TB!TB,5,FALSE) -> 10876.04 | I44: =IF(H$32,H44/H$32,0) -> 0.030480056 | K44: =VLOOKUP(A44,TB!TB1_1,4,FALSE) -> 8849.76 | L44: =IF(K$32,K44/K$32,0) -> 0.024612815 | N44: =VLOOKUP(A44,TB!TB1_1,5,FALSE) -> 8849.76 | O44: =IF(N$32,N44/N$32,0) -> 0.024612815
A45: 5144601 | C45: Road Parts-TVH | E45: =VLOOKUP(A45,TB!TB,4,FALSE) -> 316 | F45: =IF(E$32,E45/E$32,0) -> 0.00088558867 | H45: =VLOOKUP(A45,TB!TB,5,FALSE) -> 316 | I45: =IF(H$32,H45/H$32,0) -> 0.00088558867 | K45: 0 | L45: =IF(K$32,K45/K$32,0) -> 0 | N45: 0 | O45: =IF(N$32,N45/N$32,0) -> 0
A46: 5135601 | C46: Road Parts-Other | E46: =VLOOKUP(A46,TB!TB,4,FALSE) -> 27592.34 | F46: =IF(E$32,E46/E$32,0) -> 0.077327417 | H46: =VLOOKUP(A46,TB!TB,5,FALSE) -> 27592.34 | I46: =IF(H$32,H46/H$32,0) -> 0.077327417 | K46: =VLOOKUP(A46,TB!TB1_1,4,FALSE) -> 21058.75 | L46: =IF(K$32,K46/K$32,0) -> 0.058568269 | N46: =VLOOKUP(A46,TB!TB1_1,5,FALSE) -> 21058.75 | O46: =IF(N$32,N46/N$32,0) -> 0.058568269
A47: 5136601 | C47: P M -Linde Parts | E47: =VLOOKUP(A47,TB!TB,4,FALSE) -> 7745.44 | F47: =IF(E$32,E47/E$32,0) -> 0.021706563 | H47: =VLOOKUP(A47,TB!TB,5,FALSE) -> 7745.44 | I47: =IF(H$32,H47/H$32,0) -> 0.021706563 | K47: =VLOOKUP(A47,TB!TB1_1,4,FALSE) -> 3791.53 | L47: =IF(K$32,K47/K$32,0) -> 0.010544944 | N47: =VLOOKUP(A47,TB!TB1_1,5,FALSE) -> 3791.53 | O47: =IF(N$32,N47/N$32,0) -> 0.010544944
A48: 5137601 | C48: P M -Combi Parts | E48: =VLOOKUP(A48,TB!TB,4,FALSE) -> 0 | F48: =IF(E$32,E48/E$32,0) -> 0 | H48: =VLOOKUP(A48,TB!TB,5,FALSE) -> 0 | I48: =IF(H$32,H48/H$32,0) -> 0 | K48: =VLOOKUP(A48,TB!TB1_1,4,FALSE) -> 0 | L48: =IF(K$32,K48/K$32,0) -> 0 | N48: =VLOOKUP(A48,TB!TB1_1,5,FALSE) -> 0 | O48: =IF(N$32,N48/N$32,0) -> 0
A49: 5147601 | C49: P M -TVH Parts | E49: =VLOOKUP(A49,TB!TB,4,FALSE) -> 185.58 | F49: =IF(E$32,E49/E$32,0) -> 0.00052008717 | H49: =VLOOKUP(A49,TB!TB,5,FALSE) -> 185.58 | I49: =IF(H$32,H49/H$32,0) -> 0.00052008717 | K49: 0 | L49: =IF(K$32,K49/K$32,0) -> 0 | N49: 0 | O49: =IF(N$32,N49/N$32,0) -> 0
A50: 5138601 | C50: P M -Other Parts | E50: =VLOOKUP(A50,TB!TB,4,FALSE) -> 1274.61 | F50: =IF(E$32,E50/E$32,0) -> 0.0035720892 | H50: =VLOOKUP(A50,TB!TB,5,FALSE) -> 1274.61 | I50: =IF(H$32,H50/H$32,0) -> 0.0035720892 | K50: =VLOOKUP(A50,TB!TB1_1,4,FALSE) -> 774.5 | L50: =IF(K$32,K50/K$32,0) -> 0.0021540274 | N50: =VLOOKUP(A50,TB!TB1_1,5,FALSE) -> 774.5 | O50: =IF(N$32,N50/N$32,0) -> 0.0021540274
A51: 5300601 | C51: Internal Parts | E51: =VLOOKUP(A51,TB!TB,4,FALSE) -> -1374.23 | F51: =IF(E$32,E51/E$32,0) -> -0.0038512738 | H51: =VLOOKUP(A51,TB!TB,5,FALSE) -> -1374.23 | I51: =IF(H$32,H51/H$32,0) -> -0.0038512738 | K51: =VLOOKUP(A51,TB!TB1_1,4,FALSE) -> 450.52 | L51: =IF(K$32,K51/K$32,0) -> 0.0012529792 | N51: =VLOOKUP(A51,TB!TB1_1,5,FALSE) -> 450.52 | O51: =IF(N$32,N51/N$32,0) -> 0.0012529792
A52: 5306601 | C52: Parts Obsolecence | E52: =VLOOKUP(A52,TB!TB,4,FALSE) -> -1264.71 | F52: =IF(E$32,E52/E$32,0) -> -0.0035443445 | H52: =VLOOKUP(A52,TB!TB,5,FALSE) -> -1264.71 | I52: =IF(H$32,H52/H$32,0) -> -0.0035443445 | K52: =VLOOKUP(A52,TB!TB1_1,4,FALSE) -> 421.74 | L52: =IF(K$32,K52/K$32,0) -> 0.0011729367 | N52: =VLOOKUP(A52,TB!TB1_1,5,FALSE) -> 421.74 | O52: =IF(N$32,N52/N$32,0) -> 0.0011729367
A53: 5960601 | C53: Labor | E53: =VLOOKUP(A53,TB!TB,4,FALSE) -> 0 | F53: =IF(E$32,E53/E$32,0) -> 0 | H53: =VLOOKUP(A53,TB!TB,5,FALSE) -> 0 | I53: =IF(H$32,H53/H$32,0) -> 0 | K53: =VLOOKUP(A53,TB!TB1_1,4,FALSE) -> 0 | L53: =IF(K$32,K53/K$32,0) -> 0 | N53: =VLOOKUP(A53,TB!TB1_1,5,FALSE) -> 0 | O53: =IF(N$32,N53/N$32,0) -> 0
A54: 6430601 | C54: Freight | E54: =VLOOKUP(A54,TB!TB,4,FALSE) -> 10068.51 | F54: =IF(E$32,E54/E$32,0) -> 0.028216957 | H54: =VLOOKUP(A54,TB!TB,5,FALSE) -> 10068.51 | I54: =IF(H$32,H54/H$32,0) -> 0.028216957 | K54: =VLOOKUP(A54,TB!TB1_1,4,FALSE) -> 9298.36 | L54: =IF(K$32,K54/K$32,0) -> 0.025860455 | N54: =VLOOKUP(A54,TB!TB1_1,5,FALSE) -> 9298.36 | O54: =IF(N$32,N54/N$32,0) -> 0.025860455
C55: Total Cost of Goods Sold | E55: =SUM(E34:E54) -> 227645.64 | F55: =IF(E$32,E55/E$32,0) -> 0.63797595 | H55: =SUM(H34:H54) -> 227645.64 | I55: =IF(H$32,H55/H$32,0) -> 0.63797595 | K55: =SUM(K34:K54) -> 238562.87 | L55: =IF(K$32,K55/K$32,0) -> 0.66348736 | N55: =SUM(N34:N54) -> 238562.87 | O55: =IF(N$32,N55/N$32,0) -> 0.66348736
C57: Gross Profit | E57: =E32-E55 -> 129179.16 | F57: =IF(E$32,E57/E$32,0) -> 0.36202405 | H57: =H32-H55 -> 129179.16 | I57: =IF(H$32,H57/H$32,0) -> 0.36202405 | K57: =K32-K55 -> 120996.16 | L57: =IF(K$32,K57/K$32,0) -> 0.33651264 | N57: =N32-N55 -> 120996.16 | O57: =IF(N$32,N57/N$32,0) -> 0.33651264
A59: 6010601 | C59: Supervisory | E59: =VLOOKUP(A59,TB!TB,4,FALSE) -> 0 | F59: =IF(E$32,E59/E$32,0) -> 0 | H59: =VLOOKUP(A59,TB!TB,5,FALSE) -> 0 | I59: =IF(H$32,H59/H$32,0) -> 0 | K59: =VLOOKUP(A59,TB!TB1_1,4,FALSE) -> 0 | L59: =IF(K$32,K59/K$32,0) -> 0 | N59: =VLOOKUP(A59,TB!TB1_1,5,FALSE) -> 0 | O59: =IF(N$32,N59/N$32,0) -> 0
A60: 6020601 | C60: Salesman Salaries | E60: =VLOOKUP(A60,TB!TB,4,FALSE) -> 38117.5 | F60: =IF(E$32,E60/E$32,0) -> 0.10682413 | H60: =VLOOKUP(A60,TB!TB,5,FALSE) -> 38117.5 | I60: =IF(H$32,H60/H$32,0) -> 0.10682413 | K60: =VLOOKUP(A60,TB!TB1_1,4,FALSE) -> 35160 | L60: =IF(K$32,K60/K$32,0) -> 0.097786447 | N60: =VLOOKUP(A60,TB!TB1_1,5,FALSE) -> 35160 | O60: =IF(N$32,N60/N$32,0) -> 0.097786447
A61: 6050601 | C61: Support Salaries | E61: =VLOOKUP(A61,TB!TB,4,FALSE) -> 0 | F61: =IF(E$32,E61/E$32,0) -> 0 | H61: =VLOOKUP(A61,TB!TB,5,FALSE) -> 0 | I61: =IF(H$32,H61/H$32,0) -> 0 | K61: =VLOOKUP(A61,TB!TB1_1,4,FALSE) -> 0 | L61: =IF(K$32,K61/K$32,0) -> 0 | N61: =VLOOKUP(A61,TB!TB1_1,5,FALSE) -> 0 | O61: =IF(N$32,N61/N$32,0) -> 0
A62: 6061601 | C62: Commission | E62: =VLOOKUP(A62,TB!TB,4,FALSE) -> 1047.78 | F62: =IF(E$32,E62/E$32,0) -> 0.002936399 | H62: =VLOOKUP(A62,TB!TB,5,FALSE) -> 1047.78 | I62: =IF(H$32,H62/H$32,0) -> 0.002936399 | K62: =VLOOKUP(A62,TB!TB1_1,4,FALSE) -> 1380.98 | L62: =IF(K$32,K62/K$32,0) -> 0.0038407602 | N62: =VLOOKUP(A62,TB!TB1_1,5,FALSE) -> 1380.98 | O62: =IF(N$32,N62/N$32,0) -> 0.0038407602
A63: 6070601 | C63: Payroll Taxes | E63: =VLOOKUP(A63,TB!TB,4,FALSE) -> 3727.41 | F63: =IF(E$32,E63/E$32,0) -> 0.010446051 | H63: =VLOOKUP(A63,TB!TB,5,FALSE) -> 3727.41 | I63: =IF(H$32,H63/H$32,0) -> 0.010446051 | K63: =VLOOKUP(A63,TB!TB1_1,4,FALSE) -> 3079.62 | L63: =IF(K$32,K63/K$32,0) -> 0.0085649914 | N63: =VLOOKUP(A63,TB!TB1_1,5,FALSE) -> 3079.62 | O63: =IF(N$32,N63/N$32,0) -> 0.0085649914
A64: 6530601 | C64: Employee Welfare | E64: =VLOOKUP(A64,TB!TB,4,FALSE) -> -579.65 | F64: =IF(E$32,E64/E$32,0) -> -0.0016244667 | H64: =VLOOKUP(A64,TB!TB,5,FALSE) -> -579.65 | I64: =IF(H$32,H64/H$32,0) -> -0.0016244667 | K64: =VLOOKUP(A64,TB!TB1_1,4,FALSE) -> 1308.01 | L64: =IF(K$32,K64/K$32,0) -> 0.0036378171 | N64: =VLOOKUP(A64,TB!TB1_1,5,FALSE) -> 1308.01 | O64: =IF(N$32,N64/N$32,0) -> 0.0036378171
A65: 6540601 | C65: 401K Contribution | E65: =VLOOKUP(A65,TB!TB,4,FALSE) -> 622.14 | F65: =IF(E$32,E65/E$32,0) -> 0.0017435447 | H65: =VLOOKUP(A65,TB!TB,5,FALSE) -> 622.14 | I65: =IF(H$32,H65/H$32,0) -> 0.0017435447 | K65: =VLOOKUP(A65,TB!TB1_1,4,FALSE) -> 468.41 | L65: =IF(K$32,K65/K$32,0) -> 0.0013027346 | N65: =VLOOKUP(A65,TB!TB1_1,5,FALSE) -> 468.41 | O65: =IF(N$32,N65/N$32,0) -> 0.0013027346
A66: 6100601 | C66: Employee Exp-100% | E66: =VLOOKUP(A66,TB!TB,4,FALSE) -> 0 | F66: =IF(E$32,E66/E$32,0) -> 0 | H66: =VLOOKUP(A66,TB!TB,5,FALSE) -> 0 | I66: =IF(H$32,H66/H$32,0) -> 0 | K66: =VLOOKUP(A66,TB!TB1_1,4,FALSE) -> 0 | L66: =IF(K$32,K66/K$32,0) -> 0 | N66: =VLOOKUP(A66,TB!TB1_1,5,FALSE) -> 0 | O66: =IF(N$32,N66/N$32,0) -> 0
A67: 6110601 | C67: Employee Exp-50% | E67: =VLOOKUP(A67,TB!TB,4,FALSE) -> 1069.5 | F67: =IF(E$32,E67/E$32,0) -> 0.0029972692 | H67: =VLOOKUP(A67,TB!TB,5,FALSE) -> 1069.5 | I67: =IF(H$32,H67/H$32,0) -> 0.0029972692 | K67: =VLOOKUP(A67,TB!TB1_1,4,FALSE) -> 0 | L67: =IF(K$32,K67/K$32,0) -> 0 | N67: =VLOOKUP(A67,TB!TB1_1,5,FALSE) -> 0 | O67: =IF(N$32,N67/N$32,0) -> 0
A68: 6210601 | C68: Vehicle Repair & Maint | E68: =VLOOKUP(A68,TB!TB,4,FALSE) -> 436.58 | F68: =IF(E$32,E68/E$32,0) -> 0.0012235136 | H68: =VLOOKUP(A68,TB!TB,5,FALSE) -> 436.58 | I68: =IF(H$32,H68/H$32,0) -> 0.0012235136 | K68: =VLOOKUP(A68,TB!TB1_1,4,FALSE) -> 394.17 | L68: =IF(K$32,K68/K$32,0) -> 0.0010962595 | N68: =VLOOKUP(A68,TB!TB1_1,5,FALSE) -> 394.17 | O68: =IF(N$32,N68/N$32,0) -> 0.0010962595
A69: 6310601 | C69: Rent | E69: =VLOOKUP(A69,TB!TB,4,FALSE) -> 3680 | F69: =IF(E$32,E69/E$32,0) -> 0.010313185 | H69: =VLOOKUP(A69,TB!TB,5,FALSE) -> 3680 | I69: =IF(H$32,H69/H$32,0) -> 0.010313185 | K69: =VLOOKUP(A69,TB!TB1_1,4,FALSE) -> 1687.5 | L69: =IF(K$32,K69/K$32,0) -> 0.0046932488 | N69: =VLOOKUP(A69,TB!TB1_1,5,FALSE) -> 1687.5 | O69: =IF(N$32,N69/N$32,0) -> 0.0046932488
A70: 6410601 | C70: Office Supplies | E70: =VLOOKUP(A70,TB!TB,4,FALSE) -> 456.25 | F70: =IF(E$32,E70/E$32,0) -> 0.0012786387 | H70: =VLOOKUP(A70,TB!TB,5,FALSE) -> 456.25 | I70: =IF(H$32,H70/H$32,0) -> 0.0012786387 | K70: =VLOOKUP(A70,TB!TB1_1,4,FALSE) -> 180 | L70: =IF(K$32,K70/K$32,0) -> 0.00050061321 | N70: =VLOOKUP(A70,TB!TB1_1,5,FALSE) -> 180 | O70: =IF(N$32,N70/N$32,0) -> 0.00050061321
... A79: 6910601 | C79: Tariff Expenses | E79: =VLOOKUP(A79,TB!TB,4,FALSE) -> 168.97 | F79: =IF(E$32,E79/E$32,0) -> 0.00047353771 | H79: =VLOOKUP(A79,TB!TB,5,FALSE) -> 168.97 | I79: =IF(H$32,H79/H$32,0) -> 0.00047353771 | K79: =VLOOKUP(A79,TB!TB1_1,4,FALSE) -> 0 | L79: =IF(K$32,K79/K$32,0) -> 0 | N79: =VLOOKUP(A79,TB!TB1_1,5,FALSE) -> 0 | O79: =IF(N$32,N79/N$32,0) -> 0
C80: Total Expenses | E80: =SUM(E59:E79) -> 52798.53 | F80: =IF(E$32,E80/E$32,0) -> 0.14796766 | H80: =SUM(H59:H79) -> 52798.53 | I80: =IF(H$32,H80/H$32,0) -> 0.14796766 | K80: =SUM(K59:K79) -> 47104.21 | L80: =IF(K$32,K80/K$32,0) -> 0.1310055 | N80: =SUM(N59:N79) -> 47104.21 | O80: =IF(N$32,N80/N$32,0) -> 0.1310055
C83: Net Income | E83: =E57-E80 -> 76380.63 | F83: =IF(E$32,E83/E$32,0) -> 0.21405639 | H83: =H57-H80 -> 76380.63 | I83: =IF(H$32,H83/H$32,0) -> 0.21405639 | K83: =K57-K80 -> 73891.95 | L83: =IF(K$32,K83/K$32,0) -> 0.20550715 | N83: =N57-N80 -> 73891.95 | O83: =IF(N$32,N83/N$32,0) -> 0.20550715
A85: 6980601 | C85: G & A Allocation | E85: =VLOOKUP(A85,TB!TB,4,FALSE) -> 0 | F85: =IF(E$32,E85/E$32,0) -> 0 | H85: =VLOOKUP(A85,TB!TB,5,FALSE) -> 0 | I85: =IF(H$32,H85/H$32,0) -> 0 | K85: =VLOOKUP(A85,TB!TB1_1,4,FALSE) -> 32924.27 | L85: =IF(K$32,K85/K$32,0) -> 0.091568469 | N85: =VLOOKUP(A85,TB!TB1_1,5,FALSE) -> 32924.27 | O85: =IF(N$32,N85/N$32,0) -> 0.091568469
C87: Income After Allocation | E87: =E83-E85 -> 76380.63 | F87: =IF(E$32,E87/E$32,0) -> 0.21405639 | H87: =H83-H85 -> 76380.63 | I87: =IF(H$32,H87/H$32,0) -> 0.21405639 | K87: =K83-K85 -> 40967.68 | L87: =IF(K$32,K87/K$32,0) -> 0.11393868 | N87: =N83-N85 -> 40967.68 | O87: =IF(N$32,N87/N$32,0) -> 0.11393868

Sheet Canton Service Department
A1: Industrial Parts and Service Company
A2: Canton Service Departmant Financial
A3: =DATEVALUE(TB!A3&"/"&TB!A4) -> 46023
C4: Description | G4: YTD | J4: MTD | M4: YTD | P4: MTD
A5: Account # | C5: Revenue | G5: =TB!A4 -> 2026 | H5: % of Sales | J5: =TB!A4 -> 2026 | K5: % of Sales | M5: =TB!O4 -> 2025 | N5: % of Sales | P5: =TB!O4 -> 2025 | Q5: % of Sales
A7: 4151701 | C7: Road Labor | G7: =VLOOKUP(A7,TB!TB,4,FALSE)*-1 -> 173527.68 | H7: =IF(G$29,G7/G$29,0) -> 0.66079912 | J7: =VLOOKUP(A7,TB!TB,5,FALSE)*-1 -> 173527.68 | K7: =IF(J$29,J7/J$29,0) -> 0.66079912 | M7: =VLOOKUP(A7,TB!TB1_1,4,FALSE)*-1 -> 153442.06 | N7: =IF(M$29,M7/M$29,0) -> 0.78627302 | P7: =VLOOKUP(A7,TB!TB1_1,5,FALSE)*-1 -> 153442.06 | Q7: =IF(P$29,P7/P$29,0) -> 0.78627302
A8: 4155701 | C8: Shop Labor | G8: =VLOOKUP(A8,TB!TB,4,FALSE)*-1 -> 30654.62 | H8: =IF(G$29,G8/G$29,0) -> 0.1167338 | J8: =VLOOKUP(A8,TB!TB,5,FALSE)*-1 -> 30654.62 | K8: =IF(J$29,J8/J$29,0) -> 0.1167338 | M8: =VLOOKUP(A8,TB!TB1_1,4,FALSE)*-1 -> -5638.7 | N8: =IF(M$29,M8/M$29,0) -> -0.028894018 | P8: =VLOOKUP(A8,TB!TB1_1,5,FALSE)*-1 -> -5638.7 | Q8: =IF(P$29,P8/P$29,0) -> -0.028894018
A9: 4154701 | C9: Shop Quote Variance | G9: =VLOOKUP(A9,TB!TB,4,FALSE)*-1 -> 0 | H9: =IF(G$29,G9/G$29,0) -> 0 | J9: =VLOOKUP(A9,TB!TB,5,FALSE)*-1 -> 0 | K9: =IF(J$29,J9/J$29,0) -> 0 | M9: =VLOOKUP(A9,TB!TB1_1,4,FALSE)*-1 -> 0 | N9: =IF(M$29,M9/M$29,0) -> 0 | P9: =VLOOKUP(A9,TB!TB1_1,5,FALSE)*-1 -> 0 | Q9: =IF(P$29,P9/P$29,0) -> 0
A10: 4153701 | C10: Road Labor Variance | G10: =VLOOKUP(A10,TB!TB,4,FALSE)*-1 -> 0 | H10: =IF(G$29,G10/G$29,0) -> 0 | J10: =VLOOKUP(A10,TB!TB,5,FALSE)*-1 -> 0 | K10: =IF(J$29,J10/J$29,0) -> 0 | M10: =VLOOKUP(A10,TB!TB1_1,4,FALSE)*-1 -> 0 | N10: =IF(M$29,M10/M$29,0) -> 0 | P10: =VLOOKUP(A10,TB!TB1_1,5,FALSE)*-1 -> 0 | Q10: =IF(P$29,P10/P$29,0) -> 0
A11: 4160701 | C11: Lease Maintenance | G11: =VLOOKUP(A11,TB!TB,4,FALSE)*-1 -> 3538.74 | H11: =IF(G$29,G11/G$29,0) -> 0.013475639 | J11: =VLOOKUP(A11,TB!TB,5,FALSE)*-1 -> 3538.74 | K11: =IF(J$29,J11/J$29,0) -> 0.013475639 | M11: =VLOOKUP(A11,TB!TB1_1,4,FALSE)*-1 -> 7077.48 | N11: =IF(M$29,M11/M$29,0) -> 0.036266663 | P11: =VLOOKUP(A11,TB!TB1_1,5,FALSE)*-1 -> 7077.48 | Q11: =IF(P$29,P11/P$29,0) -> 0.036266663
A12: 4157701 | C12: Customer P M Labor | G12: =VLOOKUP(A12,TB!TB,4,FALSE)*-1 -> 28594.48 | H12: =IF(G$29,G12/G$29,0) -> 0.10888872 | J12: =VLOOKUP(A12,TB!TB,5,FALSE)*-1 -> 28594.48 | K12: =IF(J$29,J12/J$29,0) -> 0.10888872 | M12: =VLOOKUP(A12,TB!TB1_1,4,FALSE)*-1 -> 20610 | N12: =IF(M$29,M12/M$29,0) -> 0.10561046 | P12: =VLOOKUP(A12,TB!TB1_1,5,FALSE)*-1 -> 20610 | Q12: =IF(P$29,P12/P$29,0) -> 0.10561046
A13: 4158701 | C13: Shop Supplies | G13: =VLOOKUP(A13,TB!TB,4,FALSE)*-1 -> 17544.43 | H13: =IF(G$29,G13/G$29,0) -> 0.066809767 | J13: =VLOOKUP(A13,TB!TB,5,FALSE)*-1 -> 17544.43 | K13: =IF(J$29,J13/J$29,0) -> 0.066809767 | M13: =VLOOKUP(A13,TB!TB1_1,4,FALSE)*-1 -> 16631.45 | N13: =IF(M$29,M13/M$29,0) -> 0.085223441 | P13: =VLOOKUP(A13,TB!TB1_1,5,FALSE)*-1 -> 16631.45 | Q13: =IF(P$29,P13/P$29,0) -> 0.085223441
A14: 4171701 | C14: Customer Pickup / Delivery | G14: =VLOOKUP(A14,TB!TB,4,FALSE)*-1 -> 4237.6 | H14: =IF(G$29,G14/G$29,0) -> 0.01613692 | J14: =VLOOKUP(A14,TB!TB,5,FALSE)*-1 -> 4237.6 | K14: =IF(J$29,J14/J$29,0) -> 0.01613692 | M14: =VLOOKUP(A14,TB!TB1_1,4,FALSE)*-1 -> 1065 | N14: =IF(M$29,M14/M$29,0) -> 0.0054573092 | P14: =VLOOKUP(A14,TB!TB1_1,5,FALSE)*-1 -> 1065 | Q14: =IF(P$29,P14/P$29,0) -> 0.0054573092
A15: 4173701 | C15: SVC Parts - Freight Recovery | G15: =VLOOKUP(A15,TB!TB,4,FALSE)*-1 -> 2311.21 | H15: =IF(G$29,G15/G$29,0) -> 0.0088011638 | J15: =VLOOKUP(A15,TB!TB,5,FALSE)*-1 -> 2311.21 | K15: =IF(J$29,J15/J$29,0) -> 0.0088011638 | M15: =VLOOKUP(A15,TB!TB1_1,4,FALSE)*-1 -> 1931.74 | N15: =IF(M$29,M15/M$29,0) -> 0.0098986877 | P15: =VLOOKUP(A15,TB!TB1_1,5,FALSE)*-1 -> 1931.74 | Q15: =IF(P$29,P15/P$29,0) -> 0.0098986877
A16: 4400701 | C16: Warranty Income | G16: =VLOOKUP(A16,TB!TB,4,FALSE)*-1 -> 0 | H16: =IF(G$29,G16/G$29,0) -> 0 | J16: =VLOOKUP(A16,TB!TB,5,FALSE)*-1 -> 0 | K16: =IF(J$29,J16/J$29,0) -> 0 | M16: =VLOOKUP(A16,TB!TB1_1,4,FALSE)*-1 -> 0 | N16: =IF(M$29,M16/M$29,0) -> 0 | P16: =VLOOKUP(A16,TB!TB1_1,5,FALSE)*-1 -> 0 | Q16: =IF(P$29,P16/P$29,0) -> 0
A17: 4410701 | C17: Local Warranty Used | G17: =VLOOKUP(A17,TB!TB,4,FALSE)*-1 -> 0 | H17: =IF(G$29,G17/G$29,0) -> 0 | J17: =VLOOKUP(A17,TB!TB,5,FALSE)*-1 -> 0 | K17: =IF(J$29,J17/J$29,0) -> 0 | M17: =VLOOKUP(A17,TB!TB1_1,4,FALSE)*-1 -> 0 | N17: =IF(M$29,M17/M$29,0) -> 0 | P17: =VLOOKUP(A17,TB!TB1_1,5,FALSE)*-1 -> 0 | Q17: =IF(P$29,P17/P$29,0) -> 0
A18: 4311701 | C18: Nonbillable Road Labor | G18: =VLOOKUP(A18,TB!TB,4,FALSE)*-1 -> 0 | H18: =IF(G$29,G18/G$29,0) -> 0 | J18: =VLOOKUP(A18,TB!TB,5,FALSE)*-1 -> 0 | K18: =IF(J$29,J18/J$29,0) -> 0 | M18: =VLOOKUP(A18,TB!TB1_1,4,FALSE)*-1 -> 0 | N18: =IF(M$29,M18/M$29,0) -> 0 | P18: =VLOOKUP(A18,TB!TB1_1,5,FALSE)*-1 -> 0 | Q18: =IF(P$29,P18/P$29,0) -> 0
... A28: 4380701 | C28: Labor B & G | G28: =VLOOKUP(A28,TB!TB,4,FALSE)*-1 -> 0 | H28: =IF(G$29,G28/G$29,0) -> 0 | J28: =VLOOKUP(A28,TB!TB,5,FALSE)*-1 -> 0 | K28: =IF(J$29,J28/J$29,0) -> 0 | M28: =VLOOKUP(A28,TB!TB1_1,4,FALSE)*-1 -> 0 | N28: =IF(M$29,M28/M$29,0) -> 0 | P28: =VLOOKUP(A28,TB!TB1_1,5,FALSE)*-1 -> 0 | Q28: =IF(P$29,P28/P$29,0) -> 0
C29: Total Revenue | G29: =SUM(G7:G28) -> 262602.77 | H29: =IF(G$29,G29/G$29,0) -> 1 | J29: =SUM(J7:J28) -> 262602.77 | K29: =IF(J$29,J29/J$29,0) -> 1 | M29: =SUM(M7:M28) -> 195151.12 | N29: =IF(M$29,M29/M$29,0) -> 1 | P29: =SUM(P7:P28) -> 195151.12 | Q29: =IF(P$29,P29/P$29,0) -> 1
A31: 5151701 | C31: CGS -Customer Labor | G31: =VLOOKUP(A31,TB!TB,4,FALSE) -> 52951.75 | H31: =IF(G$29,G31/G$29,0) -> 0.20164201 | J31: =VLOOKUP(A31,TB!TB,5,FALSE) -> 52951.75 | K31: =IF(J$29,J31/J$29,0) -> 0.20164201 | M31: =VLOOKUP(A31,TB!TB1_1,4,FALSE) -> 45417.75 | N31: =IF(M$29,M31/M$29,0) -> 0.23273118 | P31: =VLOOKUP(A31,TB!TB1_1,5,FALSE) -> 45417.75 | Q31: =IF(P$29,P31/P$29,0) -> 0.23273118
A32: 5152701 | C32: Lease Maintenance | G32: =VLOOKUP(A32,TB!TB,4,FALSE) -> 0 | H32: =IF(G$29,G32/G$29,0) -> 0 | J32: =VLOOKUP(A32,TB!TB,5,FALSE) -> 0 | K32: =IF(J$29,J32/J$29,0) -> 0 | M32: =VLOOKUP(A32,TB!TB1_1,4,FALSE) -> 0 | N32: =IF(M$29,M32/M$29,0) -> 0 | P32: =VLOOKUP(A32,TB!TB1_1,5,FALSE) -> 0 | Q32: =IF(P$29,P32/P$29,0) -> 0
A33: 5155701 | C33: CGS-Customer Shop | G33: =VLOOKUP(A33,TB!TB,4,FALSE) -> 6964.75 | H33: =IF(G$29,G33/G$29,0) -> 0.026521997 | J33: =VLOOKUP(A33,TB!TB,5,FALSE) -> 6964.75 | K33: =IF(J$29,J33/J$29,0) -> 0.026521997 | M33: =VLOOKUP(A33,TB!TB1_1,4,FALSE) -> -1302.5 | N33: =IF(M$29,M33/M$29,0) -> -0.0066743148 | P33: =VLOOKUP(A33,TB!TB1_1,5,FALSE) -> -1302.5 | Q33: =IF(P$29,P33/P$29,0) -> -0.0066743148
A34: 5156701 | C34: CGS-Service Training | G34: =VLOOKUP(A34,TB!TB,4,FALSE) -> 0 | H34: =IF(G$29,G34/G$29,0) -> 0 | J34: =VLOOKUP(A34,TB!TB,5,FALSE) -> 0 | K34: =IF(J$29,J34/J$29,0) -> 0 | M34: =VLOOKUP(A34,TB!TB1_1,4,FALSE) -> 0 | N34: =IF(M$29,M34/M$29,0) -> 0 | P34: =VLOOKUP(A34,TB!TB1_1,5,FALSE) -> 0 | Q34: =IF(P$29,P34/P$29,0) -> 0
A35: 5157701 | C35: CGS-Customer P M Labor | G35: =VLOOKUP(A35,TB!TB,4,FALSE) -> 9618.25 | H35: =IF(G$29,G35/G$29,0) -> 0.036626613 | J35: =VLOOKUP(A35,TB!TB,5,FALSE) -> 9618.25 | K35: =IF(J$29,J35/J$29,0) -> 0.036626613 | M35: =VLOOKUP(A35,TB!TB1_1,4,FALSE) -> 7870.5 | N35: =IF(M$29,M35/M$29,0) -> 0.040330284 | P35: =VLOOKUP(A35,TB!TB1_1,5,FALSE) -> 7870.5 | Q35: =IF(P$29,P35/P$29,0) -> 0.040330284
A36: 5159701 | C36: Rework | G36: =VLOOKUP(A36,TB!TB,4,FALSE) -> 1497.58 | H36: =IF(G$29,G36/G$29,0) -> 0.005702834 | J36: =VLOOKUP(A36,TB!TB,5,FALSE) -> 1497.58 | K36: =IF(J$29,J36/J$29,0) -> 0.005702834 | M36: =VLOOKUP(A36,TB!TB1_1,4,FALSE) -> 1932.15 | N36: =IF(M$29,M36/M$29,0) -> 0.0099007887 | P36: =VLOOKUP(A36,TB!TB1_1,5,FALSE) -> 1932.15 | Q36: =IF(P$29,P36/P$29,0) -> 0.0099007887
A37: 5175701 | C37: Van Maintenance | G37: =VLOOKUP(A37,TB!TB,4,FALSE) -> 8952.66 | H37: =IF(G$29,G37/G$29,0) -> 0.034092024 | J37: =VLOOKUP(A37,TB!TB,5,FALSE) -> 8952.66 | K37: =IF(J$29,J37/J$29,0) -> 0.034092024 | M37: =VLOOKUP(A37,TB!TB1_1,4,FALSE) -> 5453.66 | N37: =IF(M$29,M37/M$29,0) -> 0.02794583 | P37: =VLOOKUP(A37,TB!TB1_1,5,FALSE) -> 5453.66 | Q37: =IF(P$29,P37/P$29,0) -> 0.02794583
A38: 5192701 | C38: CGS Internal Rental to Service | G38: =VLOOKUP(A38,TB!TB,4,FALSE) -> 0 | H38: =IF(G$29,G38/G$29,0) -> 0 | J38: =VLOOKUP(A38,TB!TB,5,FALSE) -> 0 | K38: =IF(J$29,J38/J$29,0) -> 0 | M38: =VLOOKUP(A38,TB!TB1_1,4,FALSE) -> 0 | N38: =IF(M$29,M38/M$29,0) -> 0 | P38: =VLOOKUP(A38,TB!TB1_1,5,FALSE) -> 0 | Q38: =IF(P$29,P38/P$29,0) -> 0
A39: 5200701 | C39: CGS-Material | G39: =VLOOKUP(A39,TB!TB,4,FALSE) -> 0 | H39: =IF(G$29,G39/G$29,0) -> 0 | J39: =VLOOKUP(A39,TB!TB,5,FALSE) -> 0 | K39: =IF(J$29,J39/J$29,0) -> 0 | M39: =VLOOKUP(A39,TB!TB1_1,4,FALSE) -> 0 | N39: =IF(M$29,M39/M$29,0) -> 0 | P39: =VLOOKUP(A39,TB!TB1_1,5,FALSE) -> 0 | Q39: =IF(P$29,P39/P$29,0) -> 0
A40: 5220701 | C40: CGS - Internal Labor | G40: =VLOOKUP(A40,TB!TB,4,FALSE) -> 0 | H40: =IF(G$29,G40/G$29,0) -> 0 | J40: =VLOOKUP(A40,TB!TB,5,FALSE) -> 0 | K40: =IF(J$29,J40/J$29,0) -> 0 | M40: =VLOOKUP(A40,TB!TB1_1,4,FALSE) -> 0 | N40: =IF(M$29,M40/M$29,0) -> 0 | P40: =VLOOKUP(A40,TB!TB1_1,5,FALSE) -> 0 | Q40: =IF(P$29,P40/P$29,0) -> 0
A41: 5311701 | C41: Nonbillable Field Labor | G41: =VLOOKUP(A41,TB!TB,4,FALSE) -> 8764.75 | H41: =IF(G$29,G41/G$29,0) -> 0.033376457 | J41: =VLOOKUP(A41,TB!TB,5,FALSE) -> 8764.75 | K41: =IF(J$29,J41/J$29,0) -> 0.033376457 | M41: =VLOOKUP(A41,TB!TB1_1,4,FALSE) -> 12935.75 | N41: =IF(M$29,M41/M$29,0) -> 0.06628581 | P41: =VLOOKUP(A41,TB!TB1_1,5,FALSE) -> 12935.75 | Q41: =IF(P$29,P41/P$29,0) -> 0.06628581
A42: 5322701 | C42: Nonbillable Shop Labor | G42: =VLOOKUP(A42,TB!TB,4,FALSE) -> 4558.25 | H42: =IF(G$29,G42/G$29,0) -> 0.017357966 | J42: =VLOOKUP(A42,TB!TB,5,FALSE) -> 4558.25 | K42: =IF(J$29,J42/J$29,0) -> 0.017357966 | M42: =VLOOKUP(A42,TB!TB1_1,4,FALSE) -> 10271 | N42: =IF(M$29,M42/M$29,0) -> 0.052631007 | P42: =VLOOKUP(A42,TB!TB1_1,5,FALSE) -> 10271 | Q42: =IF(P$29,P42/P$29,0) -> 0.052631007
... A45: 5980701 | C45: Building and Grounds | G45: =VLOOKUP(A45,TB!TB,4,FALSE) -> 1846 | H45: =IF(G$29,G45/G$29,0) -> 0.0070296288 | J45: =VLOOKUP(A45,TB!TB,5,FALSE) -> 1846 | K45: =IF(J$29,J45/J$29,0) -> 0.0070296288 | M45: =VLOOKUP(A45,TB!TB1_1,4,FALSE) -> 16431.53 | N45: =IF(M$29,M45/M$29,0) -> 0.084199004 | P45: =VLOOKUP(A45,TB!TB1_1,5,FALSE) -> 16431.53 | Q45: =IF(P$29,P45/P$29,0) -> 0.084199004
A46: 6930001 | C46: Internal Labor | G46: =VLOOKUP(A46,TB!TB,4,FALSE) -> -67399.39 | H46: =IF(G$29,G46/G$29,0) -> -0.2566591 | J46: =VLOOKUP(A46,TB!TB,5,FALSE) -> -67399.39 | K46: =IF(J$29,J46/J$29,0) -> -0.2566591 | M46: 0 | N46: =IF(M$29,M46/M$29,0) -> 0 | P46: 0 | Q46: =IF(P$29,P46/P$29,0) -> 0
A47: 6030701 | C47: Mechanics Wages | G47: =VLOOKUP(A47,TB!TB,4,FALSE) -> 7044.8 | H47: =IF(G$29,G47/G$29,0) -> 0.026826831 | J47: =VLOOKUP(A47,TB!TB,5,FALSE) -> 7044.8 | K47: =IF(J$29,J47/J$29,0) -> 0.026826831 | M47: =VLOOKUP(A47,TB!TB1_1,4,FALSE) -> 6216.35 | N47: =IF(M$29,M47/M$29,0) -> 0.031854032 | P47: =VLOOKUP(A47,TB!TB1_1,5,FALSE) -> 6216.35 | Q47: =IF(P$29,P47/P$29,0) -> 0.031854032
C48: Total Cost of Goods Sold | G48: =SUM(G31:G47) -> 75002.87 | H48: =IF(G$29,G48/G$29,0) -> 0.2856134 | J48: =SUM(J31:J47) -> 75002.87 | K48: =IF(J$29,J48/J$29,0) -> 0.2856134 | M48: =SUM(M31:M47) -> 173013.95 | N48: =IF(M$29,M48/M$29,0) -> 0.88656396 | P48: =SUM(P31:P47) -> 173013.95 | Q48: =IF(P$29,P48/P$29,0) -> 0.88656396
C50: Gross Profit | G50: =G29-G48 -> 187599.9 | H50: =IF(G$29,G50/G$29,0) -> 0.7143866 | J50: =J29-J48 -> 187599.9 | K50: =IF(J$29,J50/J$29,0) -> 0.7143866 | M50: =M29-M48 -> 22137.17 | N50: =IF(M$29,M50/M$29,0) -> 0.11343604 | P50: =P29-P48 -> 22137.17 | Q50: =IF(P$29,P50/P$29,0) -> 0.11343604
A52: 6010701 | C52: Supervisory | G52: =VLOOKUP(A52,TB!TB,4,FALSE) -> 10870.02 | H52: =IF(G$29,G52/G$29,0) -> 0.041393394 | J52: =VLOOKUP(A52,TB!TB,5,FALSE) -> 10870.02 | K52: =IF(J$29,J52/J$29,0) -> 0.041393394 | M52: =VLOOKUP(A52,TB!TB1_1,4,FALSE) -> 9960 | N52: =IF(M$29,M52/M$29,0) -> 0.05103737 | P52: =VLOOKUP(A52,TB!TB1_1,5,FALSE) -> 9960 | Q52: =IF(P$29,P52/P$29,0) -> 0.05103737
A53: 6050701 | C53: Support Salaries | G53: =VLOOKUP(A53,TB!TB,4,FALSE) -> 16717.38 | H53: =IF(G$29,G53/G$29,0) -> 0.063660334 | J53: =VLOOKUP(A53,TB!TB,5,FALSE) -> 16717.38 | K53: =IF(J$29,J53/J$29,0) -> 0.063660334 | M53: =VLOOKUP(A53,TB!TB1_1,4,FALSE) -> 16805.4 | N53: =IF(M$29,M53/M$29,0) -> 0.086114802 | P53: =VLOOKUP(A53,TB!TB1_1,5,FALSE) -> 16805.4 | Q53: =IF(P$29,P53/P$29,0) -> 0.086114802
A54: 6061701 | C54: Commission | G54: =VLOOKUP(A54,TB!TB,4,FALSE) -> 0 | H54: =IF(G$29,G54/G$29,0) -> 0 | J54: =VLOOKUP(A54,TB!TB,5,FALSE) -> 0 | K54: =IF(J$29,J54/J$29,0) -> 0 | M54: =VLOOKUP(A54,TB!TB1_1,4,FALSE) -> 0 | N54: =IF(M$29,M54/M$29,0) -> 0 | P54: =VLOOKUP(A54,TB!TB1_1,5,FALSE) -> 0 | Q54: =IF(P$29,P54/P$29,0) -> 0
A55: 6070701 | C55: Payroll Taxes | G55: =VLOOKUP(A55,TB!TB,4,FALSE) -> 19489.78 | H55: =IF(G$29,G55/G$29,0) -> 0.074217724 | J55: =VLOOKUP(A55,TB!TB,5,FALSE) -> 19489.78 | K55: =IF(J$29,J55/J$29,0) -> 0.074217724 | M55: =VLOOKUP(A55,TB!TB1_1,4,FALSE) -> 16263.21 | N55: =IF(M$29,M55/M$29,0) -> 0.083336493 | P55: =VLOOKUP(A55,TB!TB1_1,5,FALSE) -> 16263.21 | Q55: =IF(P$29,P55/P$29,0) -> 0.083336493
A56: 6530701 | C56: Employee Welfare | G56: =VLOOKUP(A56,TB!TB,4,FALSE) -> 4110.6 | H56: =IF(G$29,G56/G$29,0) -> 0.0156533 | J56: =VLOOKUP(A56,TB!TB,5,FALSE) -> 4110.6 | K56: =IF(J$29,J56/J$29,0) -> 0.0156533 | M56: =VLOOKUP(A56,TB!TB1_1,4,FALSE) -> 22407.33 | N56: =IF(M$29,M56/M$29,0) -> 0.1148204 | P56: =VLOOKUP(A56,TB!TB1_1,5,FALSE) -> 22407.33 | Q56: =IF(P$29,P56/P$29,0) -> 0.1148204
A57: 6540701 | C57: 401K Contribution | G57: =VLOOKUP(A57,TB!TB,4,FALSE) -> 2212.25 | H57: =IF(G$29,G57/G$29,0) -> 0.0084243209 | J57: =VLOOKUP(A57,TB!TB,5,FALSE) -> 2212.25 | K57: =IF(J$29,J57/J$29,0) -> 0.0084243209 | M57: =VLOOKUP(A57,TB!TB1_1,4,FALSE) -> 2106.48 | N57: =IF(M$29,M57/M$29,0) -> 0.010794096 | P57: =VLOOKUP(A57,TB!TB1_1,5,FALSE) -> 2106.48 | Q57: =IF(P$29,P57/P$29,0) -> 0.010794096
A58: 6100701 | C58: Employee Exp-100% | G58: =VLOOKUP(A58,TB!TB,4,FALSE) -> 0 | H58: =IF(G$29,G58/G$29,0) -> 0 | J58: =VLOOKUP(A58,TB!TB,5,FALSE) -> 0 | K58: =IF(J$29,J58/J$29,0) -> 0 | M58: =VLOOKUP(A58,TB!TB1_1,4,FALSE) -> 0 | N58: =IF(M$29,M58/M$29,0) -> 0 | P58: =VLOOKUP(A58,TB!TB1_1,5,FALSE) -> 0 | Q58: =IF(P$29,P58/P$29,0) -> 0
A59: 6110701 | C59: Employee Exp-50% | G59: =VLOOKUP(A59,TB!TB,4,FALSE) -> 145.92 | H59: =IF(G$29,G59/G$29,0) -> 0.00055566817 | J59: =VLOOKUP(A59,TB!TB,5,FALSE) -> 145.92 | K59: =IF(J$29,J59/J$29,0) -> 0.00055566817 | M59: =VLOOKUP(A59,TB!TB1_1,4,FALSE) -> 0 | N59: =IF(M$29,M59/M$29,0) -> 0 | P59: =VLOOKUP(A59,TB!TB1_1,5,FALSE) -> 0 | Q59: =IF(P$29,P59/P$29,0) -> 0
A60: 6210701 | C60: Vehicle Repair & Maint | G60: =VLOOKUP(A60,TB!TB,4,FALSE) -> 9077 | H60: =IF(G$29,G60/G$29,0) -> 0.034565515 | J60: =VLOOKUP(A60,TB!TB,5,FALSE) -> 9077 | K60: =IF(J$29,J60/J$29,0) -> 0.034565515 | M60: =VLOOKUP(A60,TB!TB1_1,4,FALSE) -> 9756.11 | N60: =IF(M$29,M60/M$29,0) -> 0.04999259 | P60: =VLOOKUP(A60,TB!TB1_1,5,FALSE) -> 9756.11 | Q60: =IF(P$29,P60/P$29,0) -> 0.04999259
A61: 6310701 | C61: Rent | G61: =VLOOKUP(A61,TB!TB,4,FALSE) -> 11040 | H61: =IF(G$29,G61/G$29,0) -> 0.042040684 | J61: =VLOOKUP(A61,TB!TB,5,FALSE) -> 11040 | K61: =IF(J$29,J61/J$29,0) -> 0.042040684 | M61: =VLOOKUP(A61,TB!TB1_1,4,FALSE) -> 4533.75 | N61: =IF(M$29,M61/M$29,0) -> 0.023231996 | P61: =VLOOKUP(A61,TB!TB1_1,5,FALSE) -> 4533.75 | Q61: =IF(P$29,P61/P$29,0) -> 0.023231996
A62: 6410701 | C62: Office Supplies | G62: =VLOOKUP(A62,TB!TB,4,FALSE) -> 456.25 | H62: =IF(G$29,G62/G$29,0) -> 0.001737415 | J62: =VLOOKUP(A62,TB!TB,5,FALSE) -> 456.25 | K62: =IF(J$29,J62/J$29,0) -> 0.001737415 | M62: =VLOOKUP(A62,TB!TB1_1,4,FALSE) -> 180 | N62: =IF(M$29,M62/M$29,0) -> 0.00092236212 | P62: =VLOOKUP(A62,TB!TB1_1,5,FALSE) -> 180 | Q62: =IF(P$29,P62/P$29,0) -> 0.00092236212
A63: 6420701 | C63: Shop Supplies | G63: =VLOOKUP(A63,TB!TB,4,FALSE) -> 6996.54 | H63: =IF(G$29,G63/G$29,0) -> 0.026643055 | J63: =VLOOKUP(A63,TB!TB,5,FALSE) -> 6996.54 | K63: =IF(J$29,J63/J$29,0) -> 0.026643055 | M63: =VLOOKUP(A63,TB!TB1_1,4,FALSE) -> 7216.33 | N63: =IF(M$29,M63/M$29,0) -> 0.036978163 | P63: =VLOOKUP(A63,TB!TB1_1,5,FALSE) -> 7216.33 | Q63: =IF(P$29,P63/P$29,0) -> 0.036978163
... A75: 6920701 | C75: Uniform Rental | G75: =VLOOKUP(A75,TB!TB,4,FALSE) -> 1027.68 | H75: =IF(G$29,G75/G$29,0) -> 0.0039134393 | J75: =VLOOKUP(A75,TB!TB,5,FALSE) -> 1027.68 | K75: =IF(J$29,J75/J$29,0) -> 0.0039134393 | M75: =VLOOKUP(A75,TB!TB1_1,4,FALSE) -> 1531.13 | N75: =IF(M$29,M75/M$29,0) -> 0.0078458684 | P75: =VLOOKUP(A75,TB!TB1_1,5,FALSE) -> 1531.13 | Q75: =IF(P$29,P75/P$29,0) -> 0.0078458684
C76: Total Expenses | G76: =SUM(G52:G75) -> 118327.93 | H76: =IF(G$29,G76/G$29,0) -> 0.45059666 | J76: =SUM(J52:J75) -> 118327.93 | K76: =IF(J$29,J76/J$29,0) -> 0.45059666 | M76: =SUM(M52:M75) -> 129197.15 | N76: =IF(M$29,M76/M$29,0) -> 0.66203643 | P76: =SUM(P52:P75) -> 129197.15 | Q76: =IF(P$29,P76/P$29,0) -> 0.66203643
C78: Net Income | G78: =G50-G76 -> 69271.97 | H78: =IF(G$29,G78/G$29,0) -> 0.26378994 | J78: =J50-J76 -> 69271.97 | K78: =IF(J$29,J78/J$29,0) -> 0.26378994 | M78: =M50-M76 -> -107059.98 | N78: =IF(M$29,M78/M$29,0) -> -0.54860039 | P78: =P50-P76 -> -107059.98 | Q78: =IF(P$29,P78/P$29,0) -> -0.54860039
A80: 6980701 | C80: G & A Allocation | G80: =VLOOKUP(A80,TB!TB,4,FALSE) -> 0 | H80: =IF(G$29,G80/G$29,0) -> 0 | J80: =VLOOKUP(A80,TB!TB,5,FALSE) -> 0 | K80: =IF(J$29,J80/J$29,0) -> 0 | M80: =VLOOKUP(A80,TB!TB1_1,4,FALSE) -> 49386.38 | N80: =IF(M$29,M80/M$29,0) -> 0.25306737 | P80: =VLOOKUP(A80,TB!TB1_1,5,FALSE) -> 49386.38 | Q80: =IF(P$29,P80/P$29,0) -> 0.25306737
C82: Income After Allocation | G82: =G78-G80 -> 69271.97 | H82: =IF(G$29,G82/G$29,0) -> 0.26378994 | J82: =J78-J80 -> 69271.97 | K82: =IF(J$29,J82/J$29,0) -> 0.26378994 | M82: =M78-M80 -> -156446.36 | N82: =IF(M$29,M82/M$29,0) -> -0.80166775 | P82: =P78-P80 -> -156446.36 | Q82: =IF(P$29,P82/P$29,0) -> -0.80166775

Sheet Canton Rental Department
A1: Industrial Parts and Service
A2: Canton Rental Department Financial
A3: =DATEVALUE(TB!A3&"/"&TB!A4) -> 46023
C4: Description | E4: YTD | H4: MTD | K4: YTD | N4: MTD
A5: Account # | C5: Revenue | E5: =TB!A4 -> 2026 | F5: % of Sales | H5: =TB!A4 -> 2026 | I5: % of Sales | K5: =TB!O4 -> 2025 | L5: % of Sales | N5: =TB!O4 -> 2025 | O5: % of Sales
A7: 4114501 | C7: Installment Sales - Trucks | E7: =VLOOKUP(A7,TB!TB,4,FALSE)*-1 -> 25150.94 | F7: =IF(E$11,E7/E$11,0) -> 0.098705255 | H7: =VLOOKUP(A7,TB!TB,5,FALSE)*-1 -> 25150.94 | I7: =IF(H$11,H7/H$11,0) -> 0.098705255 | K7: =VLOOKUP(A7,TB!TB1_1,4,FALSE)*-1 -> 67512.98 | L7: =IF(K$11,K7/K$11,0) -> 0.27188796 | N7: =VLOOKUP(A7,TB!TB1_1,5,FALSE)*-1 -> 67512.98 | O7: =IF(N$11,N7/N$11,0) -> 0.27188796
A8: 4191901 | C8: Rental Income | E8: =VLOOKUP(A8,TB!TB,4,FALSE)*-1 -> 226195.08 | F8: =IF(E$11,E8/E$11,0) -> 0.88770611 | H8: =VLOOKUP(A8,TB!TB,5,FALSE)*-1 -> 226195.08 | I8: =IF(H$11,H8/H$11,0) -> 0.88770611 | K8: =VLOOKUP(A8,TB!TB1_1,4,FALSE)*-1 -> 180536.29 | L8: =IF(K$11,K8/K$11,0) -> 0.7270549 | N8: =VLOOKUP(A8,TB!TB1_1,5,FALSE)*-1 -> 180536.29 | O8: =IF(N$11,N8/N$11,0) -> 0.7270549
A9: 4192901 | C9: Internal Rental Income | E9: =VLOOKUP(A9,TB!TB,4,FALSE)*-1 -> 0 | F9: =IF(E$11,E9/E$11,0) -> 0 | H9: =VLOOKUP(A9,TB!TB,5,FALSE)*-1 -> 0 | I9: =IF(H$11,H9/H$11,0) -> 0 | K9: =VLOOKUP(A9,TB!TB1_1,4,FALSE)*-1 -> 0 | L9: =IF(K$11,K9/K$11,0) -> 0 | N9: =VLOOKUP(A9,TB!TB1_1,5,FALSE)*-1 -> 0 | O9: =IF(N$11,N9/N$11,0) -> 0
A10: 4193901 | C10: Rental Delivery Income | E10: =VLOOKUP(A10,TB!TB,4,FALSE)*-1 -> 3462.5 | F10: =IF(E$11,E10/E$11,0) -> 0.013588635 | H10: =VLOOKUP(A10,TB!TB,5,FALSE)*-1 -> 3462.5 | I10: =IF(H$11,H10/H$11,0) -> 0.013588635 | K10: =VLOOKUP(A10,TB!TB1_1,4,FALSE)*-1 -> 262.5 | L10: =IF(K$11,K10/K$11,0) -> 0.0010571388 | N10: =VLOOKUP(A10,TB!TB1_1,5,FALSE)*-1 -> 262.5 | O10: =IF(N$11,N10/N$11,0) -> 0.0010571388
C11: Total Revenue | E11: =SUM(E7:E10) -> 254808.52 | F11: =IF(E$11,E11/E$11,0) -> 1 | H11: =SUM(H7:H10) -> 254808.52 | I11: =IF(H$11,H11/H$11,0) -> 1 | K11: =SUM(K7:K10) -> 248311.77 | L11: =IF(K$11,K11/K$11,0) -> 1 | N11: =SUM(N7:N10) -> 248311.77 | O11: =IF(N$11,N11/N$11,0) -> 1
A13: 5152901 | C13: Internal Delivery | E13: =VLOOKUP(A13,TB!TB,4,FALSE) -> 0 | F13: =IF(E$11,E13/E$11,0) -> 0 | H13: =VLOOKUP(A13,TB!TB,5,FALSE) -> 0 | I13: =IF(H$11,H13/H$11,0) -> 0 | K13: =VLOOKUP(A13,TB!TB1_1,4,FALSE) -> 0 | L13: =IF(K$11,K13/K$11,0) -> 0 | N13: =VLOOKUP(A13,TB!TB1_1,5,FALSE) -> 0 | O13: =IF(N$11,N13/N$11,0) -> 0
A14: 5371901 | C14: Rental Material | E14: =VLOOKUP(A14,TB!TB,4,FALSE) -> 7600 | F14: =IF(E$11,E14/E$11,0) -> 0.029826318 | H14: =VLOOKUP(A14,TB!TB,5,FALSE) -> 7600 | I14: =IF(H$11,H14/H$11,0) -> 0.029826318 | K14: =VLOOKUP(A14,TB!TB1_1,4,FALSE) -> 9374 | L14: =IF(K$11,K14/K$11,0) -> 0.037750929 | N14: =VLOOKUP(A14,TB!TB1_1,5,FALSE) -> 9374 | O14: =IF(N$11,N14/N$11,0) -> 0.037750929
A15: 5951501 | C15: P/L Installment Trucks | E15: =VLOOKUP(A15,TB!TB,4,FALSE) -> 1515.64 | F15: =IF(E$11,E15/E$11,0) -> 0.0059481528 | H15: =VLOOKUP(A15,TB!TB,5,FALSE) -> 1515.64 | I15: =IF(H$11,H15/H$11,0) -> 0.0059481528 | K15: =VLOOKUP(A15,TB!TB1_1,4,FALSE) -> 447.97 | L15: =IF(K$11,K15/K$11,0) -> 0.0018040627 | N15: =VLOOKUP(A15,TB!TB1_1,5,FALSE) -> 447.97 | O15: =IF(N$11,N15/N$11,0) -> 0.0018040627
A16: 5990901 | C16: P/L Rental | E16: =VLOOKUP(A16,TB!TB,4,FALSE) -> 22625.76 | F16: =IF(E$11,E16/E$11,0) -> 0.088795147 | H16: =VLOOKUP(A16,TB!TB,5,FALSE) -> 22625.76 | I16: =IF(H$11,H16/H$11,0) -> 0.088795147 | K16: =VLOOKUP(A16,TB!TB1_1,4,FALSE) -> 26362.72 | L16: =IF(K$11,K16/K$11,0) -> 0.10616782 | N16: =VLOOKUP(A16,TB!TB1_1,5,FALSE) -> 26362.72 | O16: =IF(N$11,N16/N$11,0) -> 0.10616782
A17: 6430901 | C17: Freight Expense Rental | E17: =VLOOKUP(A17,TB!TB,4,FALSE) -> 0 | F17: =IF(E$11,E17/E$11,0) -> 0 | H17: =VLOOKUP(A17,TB!TB,5,FALSE) -> 0 | I17: =IF(H$11,H17/H$11,0) -> 0 | K17: =VLOOKUP(A17,TB!TB1_1,4,FALSE) -> 0 | L17: =IF(K$11,K17/K$11,0) -> 0 | N17: =VLOOKUP(A17,TB!TB1_1,5,FALSE) -> 0 | O17: =IF(N$11,N17/N$11,0) -> 0
